Workbook
Name ItemCodeList: Inventory!$A$5:$A$604
Name VendorList: 'Shop Summary'!$F$5:$F$35

Sheet Dashboard
A1: PAWFECT BD — BUSINESS TRACKER
A2: Overview of cash, stock and profit. All figures pull live from the other sheets.
A4: CASH POSITION
A5: Total Investment (Tk) | B5: =SUM(Investment!$C$5:$C$204) -> 345000
A6: Total Purchases / Cash Out (Tk) | B6: =SUM(Purchases!$I$5:$I$1004) -> 370966.55
A7: Total Expenses / Cash Out (Tk) | B7: =SUM(Expenses!$D$5:$D$1004) -> 42722
A8: Total Sales Revenue / Cash In (Tk) | B8: =SUM(Sales!$L$7:$L$1506) -> 147710.01
A9: Less: Amount Due from Customers (Tk) | B9: =SUMIFS(Sales!$L$7:$L$1506,Sales!$M$7:$M$1506,"Due") -> 6812.004
A10: Cash In: money collected from shops (Tk) | B10: =SUM('Shop Collections'!$C$5:$C$504) -> 13500
A11: CASH ON HAND (Tk) | B11: =B5-B6-B7+B8-B9+B10 -> 85709.457
A13: STOCK POSITION
A14: Units Purchased (total) | B14: =SUM(Inventory!$D$5:$D$604) -> 3031
A15: Units Sold (total) | B15: =SUM(Inventory!$E$5:$E$604) -> 1005
A16: Units Returned (total) | B16: =SUM(Inventory!$F$5:$F$604) -> 1
A17: Units given to shops (total) | B17: =SUM(Inventory!$G$5:$G$604) -> 458
A18: Current Stock (units) | B18: =SUM(Inventory!$H$5:$H$604) -> 1569
A19: Current Stock Value (Tk) | B19: =SUM(Inventory!$J$5:$J$604) -> 204214.08
A20: Money shops still owe you (Tk) | B20: ='Shop Summary'!D35 -> 43713
A21: PROFIT SNAPSHOT
A22: Total Money In — customers + shops (Tk) | B22: ='Profit Share'!B14 -> 204923.01
A23: Total Money Out — product cost + delivery + running costs (Tk) | B23: ='Profit Share'!B21 -> 209579.47
A24: PROFIT / LOSS (Tk) | B24: ='Profit Share'!B7 -> -4656.4615
A25: Money customers still owe you (Tk) | B25: ='Profit Share'!B24 -> 6812.004
A26: Money shops still owe you (Tk) | B26: ='Profit Share'!B25 -> 43713
A27: Total owed to you (Tk) | B27: ='Profit Share'!B26 -> 50525.004
A28: PROFIT / LOSS TO SHARE (Tk) | B28: ='Profit Share'!B7 -> -4656.4615
A29: Mukta Mama (Investor) Share — 50% (Tk) | B29: =IF('Profit Share'!B31="","",'Profit Share'!B31)
A30: Ratul Share (Tk) | B30: =IF('Profit Share'!B33="","",'Profit Share'!B33)
A31: Samin Share (Tk) | B31: =IF('Profit Share'!B34="","",'Profit Share'!B34)
A32: Nawroz Share (Tk) | B32: =IF('Profit Share'!B35="","",'Profit Share'!B35)
A34: FREE GIFTS & DISCOUNTS GIVEN AWAY | C34: Already counted in the profit above — shown so you can see it
A35: Free gifts — cost to you (Tk) | B35: ='Profit Share'!B38 -> 428.32671
A36: Free gifts — value at shop price (Tk) | B36: ='Profit Share'!B39 -> 880
A37: Discounts given on sales (Tk) | B37: ='Profit Share'!B40 -> 13504.989
A38: TOTAL GIVEN AWAY (Tk) | B38: ='Profit Share'!B41 -> 13933.316 | C38: ='Profit Share'!C41 -> That is 6.8 out of every Tk 100 of sales
A41: INVESTOR CASH POSITION
A42: Investor | B42: Invested (Tk) | C42: % of Capital | D42: Share of Purchases (Tk) | E42: Share of Expenses (Tk) | F42: Remaining Cash Share (Tk)
A43: {=IFERROR(INDEX(Investment!$B$5:$B$204,MATCH(ROW()-42,Investment!$F$5:$F$204,0)),"")} -> Mukta Mama | B43: =IF($A43="","",SUMIF(Investment!$B$5:$B$204,$A43,Investment!$C$5:$C$204)) -> 345000 | C43: =IF($A43="","",B43/$B$5) -> 1 | D43: =IF($A43="","",C43*$B$6) -> 370966.55 | E43: =IF($A43="","",C43*$B$7) -> 42722 | F43: =IF($A43="","",B43-D43-E43) -> -68688.55
A44: {=IFERROR(INDEX(Investment!$B$5:$B$204,MATCH(ROW()-42,Investment!$F$5:$F$204,0)),"")} | B44: =IF($A44="","",SUMIF(Investment!$B$5:$B$204,$A44,Investment!$C$5:$C$204)) | C44: =IF($A44="","",B44/$B$5) | D44: =IF($A44="","",C44*$B$6) | E44: =IF($A44="","",C44*$B$7) | F44: =IF($A44="","",B44-D44-E44)
A45: {=IFERROR(INDEX(Investment!$B$5:$B$204,MATCH(ROW()-42,Investment!$F$5:$F$204,0)),"")} | B45: =IF($A45="","",SUMIF(Investment!$B$5:$B$204,$A45,Investment!$C$5:$C$204)) | C45: =IF($A45="","",B45/$B$5) | D45: =IF($A45="","",C45*$B$6) | E45: =IF($A45="","",C45*$B$7) | F45: =IF($A45="","",B45-D45-E45)
A46: {=IFERROR(INDEX(Investment!$B$5:$B$204,MATCH(ROW()-42,Investment!$F$5:$F$204,0)),"")} | B46: =IF($A46="","",SUMIF(Investment!$B$5:$B$204,$A46,Investment!$C$5:$C$204)) | C46: =IF($A46="","",B46/$B$5) | D46: =IF($A46="","",C46*$B$6) | E46: =IF($A46="","",C46*$B$7) | F46: =IF($A46="","",B46-D46-E46)
A47: {=IFERROR(INDEX(Investment!$B$5:$B$204,MATCH(ROW()-42,Investment!$F$5:$F$204,0)),"")} | B47: =IF($A47="","",SUMIF(Investment!$B$5:$B$204,$A47,Investment!$C$5:$C$204)) | C47: =IF($A47="","",B47/$B$5) | D47: =IF($A47="","",C47*$B$6) | E47: =IF($A47="","",C47*$B$7) | F47: =IF($A47="","",B47-D47-E47)
A50: -
A59: *

Sheet Investment
A1: INVESTMENT LOG
A2: MONEY STILL IN THE BUSINESS | C2: =C3-C207 -> 345000 | D2: Invested minus withdrawn
A3: TOTAL INVESTED | C3: =SUM(Investment!$C$5:$C$204) -> 345000 | D3: Type on the first empty row — the list extends by itself
A4: Date | B4: Investor | C4: Amount (Tk) | D4: Note | F4: Helper - new investor no.
A5: 46209 | B5: Mukta Mama | C5: 100000 | D5: Capital investment - Tranche 1 | F5: =IF($B5="","",IF(COUNTIF($B$5:$B5,$B5)=1,MAX($F$4:F4)+1,"")) -> 1
A6: 46216 | B6: Mukta Mama | C6: 100000 | D6: Capital investment - Tranche 2 | F6: =IF($B6="","",IF(COUNTIF($B$5:$B6,$B6)=1,MAX($F$4:F5)+1,""))
A7: 46225 | B7: Mukta Mama | C7: 100000 | D7: Capital investment - Tranche 3 | F7: =IF($B7="","",IF(COUNTIF($B$5:$B7,$B7)=1,MAX($F$4:F6)+1,""))
A8: 46243 | B8: Mukta Mama | C8: 45000 | D8: Capital investment - Tranche 4 | F8: =IF($B8="","",IF(COUNTIF($B$5:$B8,$B8)=1,MAX($F$4:F7)+1,""))
F9: =IF($B9="","",IF(COUNTIF($B$5:$B9,$B9)=1,MAX($F$4:F8)+1,""))
F10: =IF($B10="","",IF(COUNTIF($B$5:$B10,$B10)=1,MAX($F$4:F9)+1,""))
F11: =IF($B11="","",IF(COUNTIF($B$5:$B11,$B11)=1,MAX($F$4:F10)+1,""))
F12: =IF($B12="","",IF(COUNTIF($B$5:$B12,$B12)=1,MAX($F$4:F11)+1,""))
F13: =IF($B13="","",IF(COUNTIF($B$5:$B13,$B13)=1,MAX($F$4:F12)+1,""))
F14: =IF($B14="","",IF(COUNTIF($B$5:$B14,$B14)=1,MAX($F$4:F13)+1,""))
F15: =IF($B15="","",IF(COUNTIF($B$5:$B15,$B15)=1,MAX($F$4:F14)+1,""))
F16: =IF($B16="","",IF(COUNTIF($B$5:$B16,$B16)=1,MAX($F$4:F15)+1,""))
F17: =IF($B17="","",IF(COUNTIF($B$5:$B17,$B17)=1,MAX($F$4:F16)+1,""))
F18: =IF($B18="","",IF(COUNTIF($B$5:$B18,$B18)=1,MAX($F$4:F17)+1,""))
F19: =IF($B19="","",IF(COUNTIF($B$5:$B19,$B19)=1,MAX($F$4:F18)+1,""))
F20: =IF($B20="","",IF(COUNTIF($B$5:$B20,$B20)=1,MAX($F$4:F19)+1,""))
... F204: =IF($B204="","",IF(COUNTIF($B$5:$B204,$B204)=1,MAX($F$4:F203)+1,""))
A206: WITHDRAWALS — money taken back out of the business
A207: TOTAL WITHDRAWN | C207: =SUM(Investment!$C$209:$C$408) -> 0
A208: Date | B208: Who took it | C208: Amount (Tk) | D208: Note

Sheet Expenses
A1: EXPENSES — Business Cash Out
A2: Log every cash expense here (rent, utilities, transport, salaries, etc.). This reduces Cash on Hand on the Dashboard.
A3: TOTALS → | D3: =SUM(Expenses!$D$5:$D$1004) -> 42722
A4: Date | B4: Category | C4: Description | D4: Amount (Tk) | E4: Notes
A5: 46216 | B5: Transport/Delivery | C5: Mirpur 11 AT Int. | D5: 180
A6: 46220 | B6: Bank/Mobile Transfer Fee | C6: Product Purchase | D6: 65
A7: 46216 | B7: Other | C7: For SmartHeart Delivery Man | D7: 100 | E7: For Bonus
A8: 46216 | B8: Other | C8: For DODO Delivery Man | D8: 50 | E8: For Bonus
A9: 46218 | B9: Transport/Delivery | C9: Product Purchase | D9: 350
A10: 46219 | B10: Transport/Delivery | C10: Product Purchase | D10: 250
A11: 46219 | B11: Maintenance | C11: Balance Sheet Khata | D11: 250
A12: 46219 | B12: Maintenance | C12: Money Box | D12: 100
A13: 46219 | B13: Marketing | C13: Facebook Boost | D13: 178
A14: 46222 | B14: Transport/Delivery | C14: Product Delivery | D14: 50 | E14: SmartHeart 2 Pc's
A15: 46222 | B15: Marketing | C15: Marketing cost | D15: 3040
A16: 46222 | B16: Transport/Delivery | C16: Transport Cost | D16: 60
A17: 46223 | B17: Marketing | C17: Banner | D17: 5000
A18: 46223 | B18: Transport/Delivery | C18: Traveling Cost for Marketing Work | D18: 20
A19: 46224 | B19: Transport/Delivery | C19: Traveling Cost for Marketing Work | D19: 40
A20: 46224 | B20: Marketing | C20: Facebook Ads | D20: 639
A21: 46224 | B21: Marketing | C21: Facebook Ads | D21: 724
A22: 46229 | B22: Transport/Delivery | C22: Transport Cost for Product Purchase | D22: 100
A23: 46229 | B23: Other | C23: For Pathao Pickup Boy | D23: 100
A24: 46229 | B24: Packaging | C24: Scotch Tape | D24: 60
A25: 46229 | B25: Maintenance | C25: Scotch Tape White | D25: 65
A26: 46229 | B26: Marketing | C26: FaceBook Marketing | D26: 125
... A55: 46252 | B55: Bank/Mobile Transfer Fee | C55: Bkash Cash Out | D55: 39

Sheet Purchases
A1: PURCHASES LOG
A2: All product purchases from suppliers. Add new rows below as you buy more.
A3: TOTALS → | G3: =SUM(Purchases!$G$5:$G$1004) -> 3031 | I3: =SUM(Purchases!$I$5:$I$1004) -> 370966.55 | K3: =SUM(Purchases!$K$5:$K$1004) -> 3031
A4: Date | B4: Type | C4: Supplier | D4: Item Code | E4: Product Description | F4: Category | G4: Qty | H4: Unit Cost (Tk) | I4: Total Cost (Tk) | J4: Website Updated | K4: Net Qty (stock calc) | L4: Helper - new item no.
A5: 46137 | B5: Purchase | C5: M.S Trading | D5: AC-PNC-LR-002 | E5: Pet Nail Clippers Large | F5: Cat Accessories | G5: 1 | H5: 190 | I5: =IF($B5="Return to Supplier",-G5*H5,G5*H5) -> 190 | J5: TRUE | K5: =IF($B5="Return to Supplier",-G5,G5) -> 1 | L5: =IF($D5="","",IF(COUNTIF($D$5:$D5,$D5)=1,MAX($L$4:L4)+1,"")) -> 1
A6: 46137 | B6: Purchase | C6: M.S Trading | D6: AC-CTOY-004 | E6: Cat Ball Robot Toy | F6: Cat Accessories | G6: 1 | H6: 95 | I6: =IF($B6="Return to Supplier",-G6*H6,G6*H6) -> 95 | J6: TRUE | K6: =IF($B6="Return to Supplier",-G6,G6) -> 1 | L6: =IF($D6="","",IF(COUNTIF($D$5:$D6,$D6)=1,MAX($L$4:L5)+1,"")) -> 2
A7: 46181 | B7: Purchase | C7: M.S Trading | D7: AC-CB-001 | E7: Cat Belt | F7: Cat Accessories | G7: 8 | H7: 27 | I7: =IF($B7="Return to Supplier",-G7*H7,G7*H7) -> 216 | J7: TRUE | K7: =IF($B7="Return to Supplier",-G7,G7) -> 8 | L7: =IF($D7="","",IF(COUNTIF($D$5:$D7,$D7)=1,MAX($L$4:L6)+1,"")) -> 3
A8: 46190 | B8: Purchase | C8: M.S Trading | D8: PO-WET-NK-70G-001 | E8: Nekko Pouch Tuna in Jelly | F8: Cat Pouch | G8: 10 | H8: 66 | I8: =IF($B8="Return to Supplier",-G8*H8,G8*H8) -> 660 | J8: TRUE | K8: =IF($B8="Return to Supplier",-G8,G8) -> 10 | L8: =IF($D8="","",IF(COUNTIF($D$5:$D8,$D8)=1,MAX($L$4:L7)+1,"")) -> 4
A9: 46190 | B9: Purchase | C9: AT International | D9: AC-CJ-AR-001 | E9: Cat Jersey Argentina Medium | F9: Cat Accessories | G9: 3 | H9: 140 | I9: =IF($B9="Return to Supplier",-G9*H9,G9*H9) -> 420 | J9: TRUE | K9: =IF($B9="Return to Supplier",-G9,G9) -> 3 | L9: =IF($D9="","",IF(COUNTIF($D$5:$D9,$D9)=1,MAX($L$4:L8)+1,"")) -> 5
A10: 46190 | B10: Purchase | C10: AT International | D10: AC-CJ-AR-002 | E10: Cat Jersey Argentina Large | F10: Cat Accessories | G10: 1 | H10: 140 | I10: =IF($B10="Return to Supplier",-G10*H10,G10*H10) -> 140 | J10: TRUE | K10: =IF($B10="Return to Supplier",-G10,G10) -> 1 | L10: =IF($D10="","",IF(COUNTIF($D$5:$D10,$D10)=1,MAX($L$4:L9)+1,"")) -> 6
A11: 46190 | B11: Purchase | C11: AT International | D11: AC-CJ-BR-002 | E11: Cat Jersey Brazil Large | F11: Cat Accessories | G11: 2 | H11: 140 | I11: =IF($B11="Return to Supplier",-G11*H11,G11*H11) -> 280 | J11: TRUE | K11: =IF($B11="Return to Supplier",-G11,G11) -> 2 | L11: =IF($D11="","",IF(COUNTIF($D$5:$D11,$D11)=1,MAX($L$4:L10)+1,"")) -> 7
A12: 46190 | B12: Purchase | C12: AT International | D12: AC-CJ-BR-001 | E12: Cat Jersey Brazil Medium | F12: Cat Accessories | G12: 3 | H12: 140 | I12: =IF($B12="Return to Supplier",-G12*H12,G12*H12) -> 420 | J12: TRUE | K12: =IF($B12="Return to Supplier",-G12,G12) -> 3 | L12: =IF($D12="","",IF(COUNTIF($D$5:$D12,$D12)=1,MAX($L$4:L11)+1,"")) -> 8
A13: 46190 | B13: Purchase | C13: AT International | D13: AC-SHAMP-002 | E13: Bengal Flea & Tick Shampoo | F13: Cat Accessories | G13: 0 | H13: 240 | I13: =IF($B13="Return to Supplier",-G13*H13,G13*H13) -> 0 | J13: TRUE | K13: =IF($B13="Return to Supplier",-G13,G13) -> 0 | L13: =IF($D13="","",IF(COUNTIF($D$5:$D13,$D13)=1,MAX($L$4:L12)+1,"")) -> 9
A14: 46190 | B14: Purchase | C14: AT International | D14: AC-SHAMP-003 | E14: Bengal Waterless Bath No-Rinse Shampoo | F14: Cat Accessories | G14: 1 | H14: 290 | I14: =IF($B14="Return to Supplier",-G14*H14,G14*H14) -> 290 | J14: TRUE | K14: =IF($B14="Return to Supplier",-G14,G14) -> 1 | L14: =IF($D14="","",IF(COUNTIF($D$5:$D14,$D14)=1,MAX($L$4:L13)+1,"")) -> 10
A15: 46190 | B15: Purchase | C15: AT International | D15: AC-LB-001 | E15: Cat Litter Box Large | F15: Cat Accessories | G15: 1 | H15: 400 | I15: =IF($B15="Return to Supplier",-G15*H15,G15*H15) -> 400 | J15: TRUE | K15: =IF($B15="Return to Supplier",-G15,G15) -> 1 | L15: =IF($D15="","",IF(COUNTIF($D$5:$D15,$D15)=1,MAX($L$4:L14)+1,"")) -> 11
A16: 46191 | B16: Purchase | C16: AT International | D16: AC-LB-002 | E16: Cat Litter Box Medium | F16: Cat Accessories | G16: 1 | H16: 300 | I16: =IF($B16="Return to Supplier",-G16*H16,G16*H16) -> 300 | J16: TRUE | K16: =IF($B16="Return to Supplier",-G16,G16) -> 1 | L16: =IF($D16="","",IF(COUNTIF($D$5:$D16,$D16)=1,MAX($L$4:L15)+1,"")) -> 12
... A151: 46249 | B151: Purchase | C151: M.S Trading | D151: FD-MX-0003 | E151: Drools, Meo & Cutie Mixed Food 100gm | F151: Cat Food | G151: 1 | H151: 31 | I151: =IF($B151="Return to Supplier",-G151*H151,G151*H151) -> 31 | J151: FALSE | K151: =IF($B151="Return to Supplier",-G151,G151) -> 1 | L151: =IF($D151="","",IF(COUNTIF($D$5:$D151,$D151)=1,MAX($L$4:L150)+1,"")) -> 121
A152: 46258 | B152: Purchase | C152: Nutrichemy Limited | D152: FD-DRY-CHNK-CHKN-1.5KG-001 | E152: Chonk All ages Tuna | F152: Cat Food | G152: 6 | H152: 400 | I152: =IF($B152="Return to Supplier",-G152*H152,G152*H152) -> 2400 | K152: =IF($B152="Return to Supplier",-G152,G152) -> 6 | L152: =IF($D152="","",IF(COUNTIF($D$5:$D152,$D152)=1,MAX($L$4:L151)+1,""))
A153: 46258 | B153: Purchase | C153: Nutrichemy Limited | D153: FD-DRY-CHNK-OCFCK-1.5KG-001 | E153: Chonk All ages Ocean Fish with Chicken | F153: Cat Food | G153: 2 | H153: 400 | I153: =IF($B153="Return to Supplier",-G153*H153,G153*H153) -> 800 | K153: =IF($B153="Return to Supplier",-G153,G153) -> 2 | L153: =IF($D153="","",IF(COUNTIF($D$5:$D153,$D153)=1,MAX($L$4:L152)+1,""))
A154: 46258 | B154: Purchase | C154: Nutrichemy Limited | D154: FD-DRY-CHNK-TN-1.5KG-001 | E154: Chonk All ages Tuna | F154: Cat Food | G154: 2 | H154: 400 | I154: =IF($B154="Return to Supplier",-G154*H154,G154*H154) -> 800 | K154: =IF($B154="Return to Supplier",-G154,G154) -> 2 | L154: =IF($D154="","",IF(COUNTIF($D$5:$D154,$D154)=1,MAX($L$4:L153)+1,""))
A155: 46260 | B155: Purchase | C155: Birds Palace | D155: FD-DRY-WP-1.5KG-001 | E155: Wanpy Grain Free Cat Food | F155: Cat Food | G155: 8 | H155: 990 | I155: =IF($B155="Return to Supplier",-G155*H155,G155*H155) -> 7920 | K155: =IF($B155="Return to Supplier",-G155,G155) -> 8 | L155: =IF($D155="","",IF(COUNTIF($D$5:$D155,$D155)=1,MAX($L$4:L154)+1,"")) -> 122
A156: 46260 | B156: Purchase | C156: Birds Palace | D156: FD-WET-WP-001 | E156: Wanpy Cat Treat Likable Tuna Mousse with Chicken 40gm | F156: Cat Wet Food | G156: 6 | H156: 80 | I156: =IF($B156="Return to Supplier",-G156*H156,G156*H156) -> 480 | K156: =IF($B156="Return to Supplier",-G156,G156) -> 6 | L156: =IF($D156="","",IF(COUNTIF($D$5:$D156,$D156)=1,MAX($L$4:L155)+1,"")) -> 123
A157: 46260 | B157: Purchase | C157: Birds Palace | D157: FD-DRY-KTCN-All-400G-001 | E157: Kitchen Flavour Grain Free Dry Cat Food All Life Stage 400gm | F157: Cat Food | G157: 16 | H157: 290 | I157: =IF($B157="Return to Supplier",-G157*H157,G157*H157) -> 4640 | K157: =IF($B157="Return to Supplier",-G157,G157) -> 16 | L157: =IF($D157="","",IF(COUNTIF($D$5:$D157,$D157)=1,MAX($L$4:L156)+1,"")) -> 124
A158: 46260 | B158: Purchase | C158: Birds Palace | D158: PO-WET-KTCN-HS-001 | E158: Kitchen Flavour Special Care Complete Cat Food Pouch Hair & Skin Care 70gm | F158: Cat Pouch | G158: 48 | H158: 75 | I158: =IF($B158="Return to Supplier",-G158*H158,G158*H158) -> 3600 | K158: =IF($B158="Return to Supplier",-G158,G158) -> 48 | L158: =IF($D158="","",IF(COUNTIF($D$5:$D158,$D158)=1,MAX($L$4:L157)+1,"")) -> 125
A159: 46260 | B159: Purchase | C159: Birds Palace | D159: PO-WET-KTCN-UR-001 | E159: Kitchen Flavour Special Care Complete Cat Food Pouch Urinary Care 70gm | F159: Cat Pouch | G159: 48 | H159: 75 | I159: =IF($B159="Return to Supplier",-G159*H159,G159*H159) -> 3600 | K159: =IF($B159="Return to Supplier",-G159,G159) -> 48 | L159: =IF($D159="","",IF(COUNTIF($D$5:$D159,$D159)=1,MAX($L$4:L158)+1,"")) -> 126
A160: 46260 | B160: Purchase | C160: Birds Palace | D160: PO-WET-KTCN-ID-001 | E160: Kitchen Flavour Special Care Complete Cat Food Pouch Indoor & Digestive Care 70gm | F160: Cat Pouch | G160: 48 | H160: 75 | I160: =IF($B160="Return to Supplier",-G160*H160,G160*H160) -> 3600 | K160: =IF($B160="Return to Supplier",-G160,G160) -> 48 | L160: =IF($D160="","",IF(COUNTIF($D$5:$D160,$D160)=1,MAX($L$4:L159)+1,"")) -> 127
A161: 46260 | B161: Purchase | C161: Birds Palace | D161: PO-WET-NB-KD-001 | E161: Nature Bridge Veterinary Exclusive Wet Cat Food for Kidney 190gm | F161: Cat Pouch | G161: 24 | H161: 290 | I161: =IF($B161="Return to Supplier",-G161*H161,G161*H161) -> 6960 | K161: =IF($B161="Return to Supplier",-G161,G161) -> 24 | L161: =IF($D161="","",IF(COUNTIF($D$5:$D161,$D161)=1,MAX($L$4:L160)+1,"")) -> 128
A162: 46260 | B162: Purchase | C162: Birds Palace | D162: PO-WET-NB-UR-001 | E162: Nature Bridge Veterinary Exclusive Wet Cat Food for Urinary Tract 190gm | F162: Cat Pouch | G162: 24 | H162: 290 | I162: =IF($B162="Return to Supplier",-G162*H162,G162*H162) -> 6960 | K162: =IF($B162="Return to Supplier",-G162,G162) -> 24 | L162: =IF($D162="","",IF(COUNTIF($D$5:$D162,$D162)=1,MAX($L$4:L161)+1,"")) -> 129
A163: 46260 | B163: Purchase | C163: Birds Palace | D163: FD-DRY-KT-H/P-1.5KG-001 | E163: Haisenpet Premium Kitten Dry Cat Food Chicken, Fish, Egg & Milk 1.2KG | F163: Cat Food | G163: 3 | H163: 500 | I163: =IF($B163="Return to Supplier",-G163*H163,G163*H163) -> 1500 | K163: =IF($B163="Return to Supplier",-G163,G163) -> 3 | L163: =IF($D163="","",IF(COUNTIF($D$5:$D163,$D163)=1,MAX($L$4:L162)+1,"")) -> 130
... A201: 46267 | B201: Purchase | C201: 3s Impex | D201: FD-DRY-BON-KT-0001 | E201: Bonacibo Super Premium Cat (Chicken, Rice with Anchovy) 1.5KG | F201: Cat Food | G201: 10 | H201: 800 | I201: =IF($B201="Return to Supplier",-G201*H201,G201*H201) -> 8000 | K201: =IF($B201="Return to Supplier",-G201,G201) -> 10 | L201: =IF($D201="","",IF(COUNTIF($D$5:$D201,$D201)=1,MAX($L$4:L200)+1,"")) -> 156
I202: =IF($B202="Return to Supplier",-G202*H202,G202*H202) -> 0 | K202: =IF($B202="Return to Supplier",-G202,G202) | L202: =IF($D202="","",IF(COUNTIF($D$5:$D202,$D202)=1,MAX($L$4:L201)+1,""))
I203: =IF($B203="Return to Supplier",-G203*H203,G203*H203) -> 0 | K203: =IF($B203="Return to Supplier",-G203,G203) | L203: =IF($D203="","",IF(COUNTIF($D$5:$D203,$D203)=1,MAX($L$4:L202)+1,""))
I204: =IF($B204="Return to Supplier",-G204*H204,G204*H204) -> 0 | K204: =IF($B204="Return to Supplier",-G204,G204) | L204: =IF($D204="","",IF(COUNTIF($D$5:$D204,$D204)=1,MAX($L$4:L203)+1,""))
I205: =IF($B205="Return to Supplier",-G205*H205,G205*H205) -> 0 | K205: =IF($B205="Return to Supplier",-G205,G205) | L205: =IF($D205="","",IF(COUNTIF($D$5:$D205,$D205)=1,MAX($L$4:L204)+1,""))
I206: =IF($B206="Return to Supplier",-G206*H206,G206*H206) -> 0 | K206: =IF($B206="Return to Supplier",-G206,G206) | L206: =IF($D206="","",IF(COUNTIF($D$5:$D206,$D206)=1,MAX($L$4:L205)+1,""))
I207: =IF($B207="Return to Supplier",-G207*H207,G207*H207) -> 0 | K207: =IF($B207="Return to Supplier",-G207,G207) | L207: =IF($D207="","",IF(COUNTIF($D$5:$D207,$D207)=1,MAX($L$4:L206)+1,""))
I208: =IF($B208="Return to Supplier",-G208*H208,G208*H208) -> 0 | K208: =IF($B208="Return to Supplier",-G208,G208) | L208: =IF($D208="","",IF(COUNTIF($D$5:$D208,$D208)=1,MAX($L$4:L207)+1,""))
I209: =IF($B209="Return to Supplier",-G209*H209,G209*H209) -> 0 | K209: =IF($B209="Return to Supplier",-G209,G209) | L209: =IF($D209="","",IF(COUNTIF($D$5:$D209,$D209)=1,MAX($L$4:L208)+1,""))
I210: =IF($B210="Return to Supplier",-G210*H210,G210*H210) -> 0 | K210: =IF($B210="Return to Supplier",-G210,G210) | L210: =IF($D210="","",IF(COUNTIF($D$5:$D210,$D210)=1,MAX($L$4:L209)+1,""))
I211: =IF($B211="Return to Supplier",-G211*H211,G211*H211) -> 0 | K211: =IF($B211="Return to Supplier",-G211,G211) | L211: =IF($D211="","",IF(COUNTIF($D$5:$D211,$D211)=1,MAX($L$4:L210)+1,""))
I212: =IF($B212="Return to Supplier",-G212*H212,G212*H212) -> 0 | K212: =IF($B212="Return to Supplier",-G212,G212) | L212: =IF($D212="","",IF(COUNTIF($D$5:$D212,$D212)=1,MAX($L$4:L211)+1,""))
I213: =IF($B213="Return to Supplier",-G213*H213,G213*H213) -> 0 | K213: =IF($B213="Return to Supplier",-G213,G213) | L213: =IF($D213="","",IF(COUNTIF($D$5:$D213,$D213)=1,MAX($L$4:L212)+1,""))
... I1004: =IF($B1004="Return to Supplier",-G1004*H1004,G1004*H1004) -> 0 | K1004: =IF($B1004="Return to Supplier",-G1004,G1004) | L1004: =IF($D1004="","",IF(COUNTIF($D$5:$D1004,$D1004)=1,MAX($L$4:L1003)+1,""))

Sheet Inventory
A1: INVENTORY / STOCK TRACKER
A2: Auto-populates from Purchases — just add new purchase rows in Purchases and the product appears here automatically. Fill in MRP (yellow) for any new product. | O2: Items with no MRP set: | P2: {=SUMPRODUCT(--($A$5:$A$604<>""),--(($K$5:$K$604="")+($K$5:$K$604=0)>0))} -> 0
A3: TOTALS → | D3: =SUM(Inventory!$D$5:$D$604) -> 3031 | E3: =SUM(Inventory!$E$5:$E$604) -> 1005 | F3: =SUM(Inventory!$F$5:$F$604) -> 1 | H3: =SUM(Inventory!$H$5:$H$604) -> 1569 | J3: =SUM(Inventory!$J$5:$J$604) -> 204214.08 | O3: Codes fill in by themselves from Purchases — just type the price in any yellow cell.
A4: Item Code | B4: Product Description | C4: Category | D4: Purchased Qty | E4: Sold Qty | F4: Returned Qty | G4: Given to Shops (Qty) | H4: Current Stock | I4: Avg Unit Cost (Tk) | J4: Stock Value (Tk) | K4: MRP (Tk) | L4: Profit Margin % (of MRP) | M4: Profit Markup % (on Cost) | N4: (spacer) | O4: MRP Master — Item Code (auto-fills) | P4: MRP (Tk) — type price here
A5: {=IFERROR(INDEX(Purchases!$D$5:$D$1004,MATCH(ROW()-4,Purchases!$L$5:$L$1004,0)),"")} -> AC-PNC-LR-002 | B5: =IFERROR(VLOOKUP(A5,Purchases!$D:$E,2,FALSE),"") -> Pet Nail Clippers Large | C5: =IFERROR(VLOOKUP(A5,Purchases!$D:$F,3,FALSE),"") -> Cat Accessories | D5: =IF(A5="","",SUMIF(Purchases!$D:$D,A5,Purchases!$K:$K)) -> 1 | E5: =IF(A5="","",SUMIFS(Sales!$H:$H,Sales!$F:$F,A5,Sales!$B:$B,"<>Return")) -> 0 | F5: =IF(A5="","",SUMIFS(Sales!$H:$H,Sales!$F:$F,A5,Sales!$B:$B,"Return")) -> 0 | G5: =IF($A5="","",SUMIF('Shop Ledger'!$C:$C,$A5,'Shop Ledger'!$F:$F)) -> 0 | H5: =IF(A5="","",D5-E5+F5-G5) -> 1 | I5: =IF(A5="","",IFERROR(SUMIF(Purchases!$D:$D,A5,Purchases!$I:$I)/D5,0)) -> 190 | J5: =IF(A5="","",H5*I5) -> 190 | K5: =IF($A5="","",IFERROR(VALUE(SUBSTITUTE(SUBSTITUTE(SUBSTITUTE(VLOOKUP($A5,Inventory!$O$5:$P$604,2,FALSE),"Tk","")," ",""),",","")),"")) -> 270 | L5: =IF(OR(I5="",K5="",K5=0),"",(K5-I5)/K5) -> 0.2962963 | M5: =IF(OR(I5="",K5="",K5=0,I5=0),"",(K5-I5)/I5) -> 0.42105263 | O5: =IF($A5="","",$A5) -> AC-PNC-LR-002 | P5: 270
A6: {=IFERROR(INDEX(Purchases!$D$5:$D$1004,MATCH(ROW()-4,Purchases!$L$5:$L$1004,0)),"")} -> AC-CTOY-004 | B6: =IFERROR(VLOOKUP(A6,Purchases!$D:$E,2,FALSE),"") -> Cat Ball Robot Toy | C6: =IFERROR(VLOOKUP(A6,Purchases!$D:$F,3,FALSE),"") -> Cat Accessories | D6: =IF(A6="","",SUMIF(Purchases!$D:$D,A6,Purchases!$K:$K)) -> 1 | E6: =IF(A6="","",SUMIFS(Sales!$H:$H,Sales!$F:$F,A6,Sales!$B:$B,"<>Return")) -> 0 | F6: =IF(A6="","",SUMIFS(Sales!$H:$H,Sales!$F:$F,A6,Sales!$B:$B,"Return")) -> 0 | G6: =IF($A6="","",SUMIF('Shop Ledger'!$C:$C,$A6,'Shop Ledger'!$F:$F)) -> 0 | H6: =IF(A6="","",D6-E6+F6-G6) -> 1 | I6: =IF(A6="","",IFERROR(SUMIF(Purchases!$D:$D,A6,Purchases!$I:$I)/D6,0)) -> 95 | J6: =IF(A6="","",H6*I6) -> 95 | K6: =IF($A6="","",IFERROR(VALUE(SUBSTITUTE(SUBSTITUTE(SUBSTITUTE(VLOOKUP($A6,Inventory!$O$5:$P$604,2,FALSE),"Tk","")," ",""),",","")),"")) -> 150 | L6: =IF(OR(I6="",K6="",K6=0),"",(K6-I6)/K6) -> 0.36666667 | M6: =IF(OR(I6="",K6="",K6=0,I6=0),"",(K6-I6)/I6) -> 0.57894737 | O6: =IF($A6="","",$A6) -> AC-CTOY-004 | P6: 150
A7: {=IFERROR(INDEX(Purchases!$D$5:$D$1004,MATCH(ROW()-4,Purchases!$L$5:$L$1004,0)),"")} -> AC-CB-001 | B7: =IFERROR(VLOOKUP(A7,Purchases!$D:$E,2,FALSE),"") -> Cat Belt | C7: =IFERROR(VLOOKUP(A7,Purchases!$D:$F,3,FALSE),"") -> Cat Accessories | D7: =IF(A7="","",SUMIF(Purchases!$D:$D,A7,Purchases!$K:$K)) -> 37 | E7: =IF(A7="","",SUMIFS(Sales!$H:$H,Sales!$F:$F,A7,Sales!$B:$B,"<>Return")) -> 11 | F7: =IF(A7="","",SUMIFS(Sales!$H:$H,Sales!$F:$F,A7,Sales!$B:$B,"Return")) -> 0 | G7: =IF($A7="","",SUMIF('Shop Ledger'!$C:$C,$A7,'Shop Ledger'!$F:$F)) -> 0 | H7: =IF(A7="","",D7-E7+F7-G7) -> 26 | I7: =IF(A7="","",IFERROR(SUMIF(Purchases!$D:$D,A7,Purchases!$I:$I)/D7,0)) -> 29.351351 | J7: =IF(A7="","",H7*I7) -> 763.13514 | K7: =IF($A7="","",IFERROR(VALUE(SUBSTITUTE(SUBSTITUTE(SUBSTITUTE(VLOOKUP($A7,Inventory!$O$5:$P$604,2,FALSE),"Tk","")," ",""),",","")),"")) -> 60 | L7: =IF(OR(I7="",K7="",K7=0),"",(K7-I7)/K7) -> 0.51081081 | M7: =IF(OR(I7="",K7="",K7=0,I7=0),"",(K7-I7)/I7) -> 1.0441989 | O7: =IF($A7="","",$A7) -> AC-CB-001 | P7: 60
A8: {=IFERROR(INDEX(Purchases!$D$5:$D$1004,MATCH(ROW()-4,Purchases!$L$5:$L$1004,0)),"")} -> PO-WET-NK-70G-001 | B8: =IFERROR(VLOOKUP(A8,Purchases!$D:$E,2,FALSE),"") -> Nekko Pouch Tuna in Jelly | C8: =IFERROR(VLOOKUP(A8,Purchases!$D:$F,3,FALSE),"") -> Cat Pouch | D8: =IF(A8="","",SUMIF(Purchases!$D:$D,A8,Purchases!$K:$K)) -> 58 | E8: =IF(A8="","",SUMIFS(Sales!$H:$H,Sales!$F:$F,A8,Sales!$B:$B,"<>Return")) -> 11 | F8: =IF(A8="","",SUMIFS(Sales!$H:$H,Sales!$F:$F,A8,Sales!$B:$B,"Return")) -> 0 | G8: =IF($A8="","",SUMIF('Shop Ledger'!$C:$C,$A8,'Shop Ledger'!$F:$F)) -> 12 | H8: =IF(A8="","",D8-E8+F8-G8) -> 35 | I8: =IF(A8="","",IFERROR(SUMIF(Purchases!$D:$D,A8,Purchases!$I:$I)/D8,0)) -> 65.172414 | J8: =IF(A8="","",H8*I8) -> 2281.0345 | K8: =IF($A8="","",IFERROR(VALUE(SUBSTITUTE(SUBSTITUTE(SUBSTITUTE(VLOOKUP($A8,Inventory!$O$5:$P$604,2,FALSE),"Tk","")," ",""),",","")),"")) -> 90 | L8: =IF(OR(I8="",K8="",K8=0),"",(K8-I8)/K8) -> 0.27586207 | M8: =IF(OR(I8="",K8="",K8=0,I8=0),"",(K8-I8)/I8) -> 0.38095238 | O8: =IF($A8="","",$A8) -> PO-WET-NK-70G-001 | P8: 90
A9: {=IFERROR(INDEX(Purchases!$D$5:$D$1004,MATCH(ROW()-4,Purchases!$L$5:$L$1004,0)),"")} -> AC-CJ-AR-001 | B9: =IFERROR(VLOOKUP(A9,Purchases!$D:$E,2,FALSE),"") -> Cat Jersey Argentina Medium | C9: =IFERROR(VLOOKUP(A9,Purchases!$D:$F,3,FALSE),"") -> Cat Accessories | D9: =IF(A9="","",SUMIF(Purchases!$D:$D,A9,Purchases!$K:$K)) -> 3 | E9: =IF(A9="","",SUMIFS(Sales!$H:$H,Sales!$F:$F,A9,Sales!$B:$B,"<>Return")) -> 2 | F9: =IF(A9="","",SUMIFS(Sales!$H:$H,Sales!$F:$F,A9,Sales!$B:$B,"Return")) -> 0 | G9: =IF($A9="","",SUMIF('Shop Ledger'!$C:$C,$A9,'Shop Ledger'!$F:$F)) -> 0 | H9: =IF(A9="","",D9-E9+F9-G9) -> 1 | I9: =IF(A9="","",IFERROR(SUMIF(Purchases!$D:$D,A9,Purchases!$I:$I)/D9,0)) -> 140 | J9: =IF(A9="","",H9*I9) -> 140 | K9: =IF($A9="","",IFERROR(VALUE(SUBSTITUTE(SUBSTITUTE(SUBSTITUTE(VLOOKUP($A9,Inventory!$O$5:$P$604,2,FALSE),"Tk","")," ",""),",","")),"")) -> 300 | L9: =IF(OR(I9="",K9="",K9=0),"",(K9-I9)/K9) -> 0.53333333 | M9: =IF(OR(I9="",K9="",K9=0,I9=0),"",(K9-I9)/I9) -> 1.1428571 | O9: =IF($A9="","",$A9) -> AC-CJ-AR-001 | P9: 300
A10: {=IFERROR(INDEX(Purchases!$D$5:$D$1004,MATCH(ROW()-4,Purchases!$L$5:$L$1004,0)),"")} -> AC-CJ-AR-002 | B10: =IFERROR(VLOOKUP(A10,Purchases!$D:$E,2,FALSE),"") -> Cat Jersey Argentina Large | C10: =IFERROR(VLOOKUP(A10,Purchases!$D:$F,3,FALSE),"") -> Cat Accessories | D10: =IF(A10="","",SUMIF(Purchases!$D:$D,A10,Purchases!$K:$K)) -> 1 | E10: =IF(A10="","",SUMIFS(Sales!$H:$H,Sales!$F:$F,A10,Sales!$B:$B,"<>Return")) -> 1 | F10: =IF(A10="","",SUMIFS(Sales!$H:$H,Sales!$F:$F,A10,Sales!$B:$B,"Return")) -> 0 | G10: =IF($A10="","",SUMIF('Shop Ledger'!$C:$C,$A10,'Shop Ledger'!$F:$F)) -> 0 | H10: =IF(A10="","",D10-E10+F10-G10) -> 0 | I10: =IF(A10="","",IFERROR(SUMIF(Purchases!$D:$D,A10,Purchases!$I:$I)/D10,0)) -> 140 | J10: =IF(A10="","",H10*I10) -> 0 | K10: =IF($A10="","",IFERROR(VALUE(SUBSTITUTE(SUBSTITUTE(SUBSTITUTE(VLOOKUP($A10,Inventory!$O$5:$P$604,2,FALSE),"Tk","")," ",""),",","")),"")) -> 300 | L10: =IF(OR(I10="",K10="",K10=0),"",(K10-I10)/K10) -> 0.53333333 | M10: =IF(OR(I10="",K10="",K10=0,I10=0),"",(K10-I10)/I10) -> 1.1428571 | O10: =IF($A10="","",$A10) -> AC-CJ-AR-002 | P10: 300
A11: {=IFERROR(INDEX(Purchases!$D$5:$D$1004,MATCH(ROW()-4,Purchases!$L$5:$L$1004,0)),"")} -> AC-CJ-BR-002 | B11: =IFERROR(VLOOKUP(A11,Purchases!$D:$E,2,FALSE),"") -> Cat Jersey Brazil Large | C11: =IFERROR(VLOOKUP(A11,Purchases!$D:$F,3,FALSE),"") -> Cat Accessories | D11: =IF(A11="","",SUMIF(Purchases!$D:$D,A11,Purchases!$K:$K)) -> 2 | E11: =IF(A11="","",SUMIFS(Sales!$H:$H,Sales!$F:$F,A11,Sales!$B:$B,"<>Return")) -> 0 | F11: =IF(A11="","",SUMIFS(Sales!$H:$H,Sales!$F:$F,A11,Sales!$B:$B,"Return")) -> 0 | G11: =IF($A11="","",SUMIF('Shop Ledger'!$C:$C,$A11,'Shop Ledger'!$F:$F)) -> 0 | H11: =IF(A11="","",D11-E11+F11-G11) -> 2 | I11: =IF(A11="","",IFERROR(SUMIF(Purchases!$D:$D,A11,Purchases!$I:$I)/D11,0)) -> 140 | J11: =IF(A11="","",H11*I11) -> 280 | K11: =IF($A11="","",IFERROR(VALUE(SUBSTITUTE(SUBSTITUTE(SUBSTITUTE(VLOOKUP($A11,Inventory!$O$5:$P$604,2,FALSE),"Tk","")," ",""),",","")),"")) -> 300 | L11: =IF(OR(I11="",K11="",K11=0),"",(K11-I11)/K11) -> 0.53333333 | M11: =IF(OR(I11="",K11="",K11=0,I11=0),"",(K11-I11)/I11) -> 1.1428571 | O11: =IF($A11="","",$A11) -> AC-CJ-BR-002 | P11: 300
A12: {=IFERROR(INDEX(Purchases!$D$5:$D$1004,MATCH(ROW()-4,Purchases!$L$5:$L$1004,0)),"")} -> AC-CJ-BR-001 | B12: =IFERROR(VLOOKUP(A12,Purchases!$D:$E,2,FALSE),"") -> Cat Jersey Brazil Medium | C12: =IFERROR(VLOOKUP(A12,Purchases!$D:$F,3,FALSE),"") -> Cat Accessories | D12: =IF(A12="","",SUMIF(Purchases!$D:$D,A12,Purchases!$K:$K)) -> 3 | E12: =IF(A12="","",SUMIFS(Sales!$H:$H,Sales!$F:$F,A12,Sales!$B:$B,"<>Return")) -> 0 | F12: =IF(A12="","",SUMIFS(Sales!$H:$H,Sales!$F:$F,A12,Sales!$B:$B,"Return")) -> 0 | G12: =IF($A12="","",SUMIF('Shop Ledger'!$C:$C,$A12,'Shop Ledger'!$F:$F)) -> 0 | H12: =IF(A12="","",D12-E12+F12-G12) -> 3 | I12: =IF(A12="","",IFERROR(SUMIF(Purchases!$D:$D,A12,Purchases!$I:$I)/D12,0)) -> 140 | J12: =IF(A12="","",H12*I12) -> 420 | K12: =IF($A12="","",IFERROR(VALUE(SUBSTITUTE(SUBSTITUTE(SUBSTITUTE(VLOOKUP($A12,Inventory!$O$5:$P$604,2,FALSE),"Tk","")," ",""),",","")),"")) -> 300 | L12: =IF(OR(I12="",K12="",K12=0),"",(K12-I12)/K12) -> 0.53333333 | M12: =IF(OR(I12="",K12="",K12=0,I12=0),"",(K12-I12)/I12) -> 1.1428571 | O12: =IF($A12="","",$A12) -> AC-CJ-BR-001 | P12: 300
A13: {=IFERROR(INDEX(Purchases!$D$5:$D$1004,MATCH(ROW()-4,Purchases!$L$5:$L$1004,0)),"")} -> AC-SHAMP-002 | B13: =IFERROR(VLOOKUP(A13,Purchases!$D:$E,2,FALSE),"") -> Bengal Flea & Tick Shampoo | C13: =IFERROR(VLOOKUP(A13,Purchases!$D:$F,3,FALSE),"") -> Cat Accessories | D13: =IF(A13="","",SUMIF(Purchases!$D:$D,A13,Purchases!$K:$K)) -> 9 | E13: =IF(A13="","",SUMIFS(Sales!$H:$H,Sales!$F:$F,A13,Sales!$B:$B,"<>Return")) -> 6 | F13: =IF(A13="","",SUMIFS(Sales!$H:$H,Sales!$F:$F,A13,Sales!$B:$B,"Return")) -> 0 | G13: =IF($A13="","",SUMIF('Shop Ledger'!$C:$C,$A13,'Shop Ledger'!$F:$F)) -> 1 | H13: =IF(A13="","",D13-E13+F13-G13) -> 2 | I13: =IF(A13="","",IFERROR(SUMIF(Purchases!$D:$D,A13,Purchases!$I:$I)/D13,0)) -> 240 | J13: =IF(A13="","",H13*I13) -> 480 | K13: =IF($A13="","",IFERROR(VALUE(SUBSTITUTE(SUBSTITUTE(SUBSTITUTE(VLOOKUP($A13,Inventory!$O$5:$P$604,2,FALSE),"Tk","")," ",""),",","")),"")) -> 400 | L13: =IF(OR(I13="",K13="",K13=0),"",(K13-I13)/K13) -> 0.4 | M13: =IF(OR(I13="",K13="",K13=0,I13=0),"",(K13-I13)/I13) -> 0.66666667 | O13: =IF($A13="","",$A13) -> AC-SHAMP-002 | P13: 400
A14: {=IFERROR(INDEX(Purchases!$D$5:$D$1004,MATCH(ROW()-4,Purchases!$L$5:$L$1004,0)),"")} -> AC-SHAMP-003 | B14: =IFERROR(VLOOKUP(A14,Purchases!$D:$E,2,FALSE),"") -> Bengal Waterless Bath No-Rinse Shampoo | C14: =IFERROR(VLOOKUP(A14,Purchases!$D:$F,3,FALSE),"") -> Cat Accessories | D14: =IF(A14="","",SUMIF(Purchases!$D:$D,A14,Purchases!$K:$K)) -> 1 | E14: =IF(A14="","",SUMIFS(Sales!$H:$H,Sales!$F:$F,A14,Sales!$B:$B,"<>Return")) -> 0 | F14: =IF(A14="","",SUMIFS(Sales!$H:$H,Sales!$F:$F,A14,Sales!$B:$B,"Return")) -> 0 | G14: =IF($A14="","",SUMIF('Shop Ledger'!$C:$C,$A14,'Shop Ledger'!$F:$F)) -> 0 | H14: =IF(A14="","",D14-E14+F14-G14) -> 1 | I14: =IF(A14="","",IFERROR(SUMIF(Purchases!$D:$D,A14,Purchases!$I:$I)/D14,0)) -> 290 | J14: =IF(A14="","",H14*I14) -> 290 | K14: =IF($A14="","",IFERROR(VALUE(SUBSTITUTE(SUBSTITUTE(SUBSTITUTE(VLOOKUP($A14,Inventory!$O$5:$P$604,2,FALSE),"Tk","")," ",""),",","")),"")) -> 450 | L14: =IF(OR(I14="",K14="",K14=0),"",(K14-I14)/K14) -> 0.35555556 | M14: =IF(OR(I14="",K14="",K14=0,I14=0),"",(K14-I14)/I14) -> 0.55172414 | O14: =IF($A14="","",$A14) -> AC-SHAMP-003 | P14: 450
A15: {=IFERROR(INDEX(Purchases!$D$5:$D$1004,MATCH(ROW()-4,Purchases!$L$5:$L$1004,0)),"")} -> AC-LB-001 | B15: =IFERROR(VLOOKUP(A15,Purchases!$D:$E,2,FALSE),"") -> Cat Litter Box Large | C15: =IFERROR(VLOOKUP(A15,Purchases!$D:$F,3,FALSE),"") -> Cat Accessories | D15: =IF(A15="","",SUMIF(Purchases!$D:$D,A15,Purchases!$K:$K)) -> 1 | E15: =IF(A15="","",SUMIFS(Sales!$H:$H,Sales!$F:$F,A15,Sales!$B:$B,"<>Return")) -> 1 | F15: =IF(A15="","",SUMIFS(Sales!$H:$H,Sales!$F:$F,A15,Sales!$B:$B,"Return")) -> 0 | G15: =IF($A15="","",SUMIF('Shop Ledger'!$C:$C,$A15,'Shop Ledger'!$F:$F)) -> 0 | H15: =IF(A15="","",D15-E15+F15-G15) -> 0 | I15: =IF(A15="","",IFERROR(SUMIF(Purchases!$D:$D,A15,Purchases!$I:$I)/D15,0)) -> 400 | J15: =IF(A15="","",H15*I15) -> 0 | K15: =IF($A15="","",IFERROR(VALUE(SUBSTITUTE(SUBSTITUTE(SUBSTITUTE(VLOOKUP($A15,Inventory!$O$5:$P$604,2,FALSE),"Tk","")," ",""),",","")),"")) -> 600 | L15: =IF(OR(I15="",K15="",K15=0),"",(K15-I15)/K15) -> 0.33333333 | M15: =IF(OR(I15="",K15="",K15=0,I15=0),"",(K15-I15)/I15) -> 0.5 | O15: =IF($A15="","",$A15) -> AC-LB-001 | P15: 600
A16: {=IFERROR(INDEX(Purchases!$D$5:$D$1004,MATCH(ROW()-4,Purchases!$L$5:$L$1004,0)),"")} -> AC-LB-002 | B16: =IFERROR(VLOOKUP(A16,Purchases!$D:$E,2,FALSE),"") -> Cat Litter Box Medium | C16: =IFERROR(VLOOKUP(A16,Purchases!$D:$F,3,FALSE),"") -> Cat Accessories | D16: =IF(A16="","",SUMIF(Purchases!$D:$D,A16,Purchases!$K:$K)) -> 6 | E16: =IF(A16="","",SUMIFS(Sales!$H:$H,Sales!$F:$F,A16,Sales!$B:$B,"<>Return")) -> 4 | F16: =IF(A16="","",SUMIFS(Sales!$H:$H,Sales!$F:$F,A16,Sales!$B:$B,"Return")) -> 0 | G16: =IF($A16="","",SUMIF('Shop Ledger'!$C:$C,$A16,'Shop Ledger'!$F:$F)) -> 0 | H16: =IF(A16="","",D16-E16+F16-G16) -> 2 | I16: =IF(A16="","",IFERROR(SUMIF(Purchases!$D:$D,A16,Purchases!$I:$I)/D16,0)) -> 300 | J16: =IF(A16="","",H16*I16) -> 600 | K16: =IF($A16="","",IFERROR(VALUE(SUBSTITUTE(SUBSTITUTE(SUBSTITUTE(VLOOKUP($A16,Inventory!$O$5:$P$604,2,FALSE),"Tk","")," ",""),",","")),"")) -> 500 | L16: =IF(OR(I16="",K16="",K16=0),"",(K16-I16)/K16) -> 0.4 | M16: =IF(OR(I16="",K16="",K16=0,I16=0),"",(K16-I16)/I16) -> 0.66666667 | O16: =IF($A16="","",$A16) -> AC-LB-002 | P16: 500
... A160: {=IFERROR(INDEX(Purchases!$D$5:$D$1004,MATCH(ROW()-4,Purchases!$L$5:$L$1004,0)),"")} -> FD-DRY-BON-KT-0001 | B160: =IFERROR(VLOOKUP(A160,Purchases!$D:$E,2,FALSE),"") -> Bonacibo Super Premium Cat (Chicken, Rice with Anchovy) 1.5KG | C160: =IFERROR(VLOOKUP(A160,Purchases!$D:$F,3,FALSE),"") -> Cat Food | D160: =IF(A160="","",SUMIF(Purchases!$D:$D,A160,Purchases!$K:$K)) -> 10 | E160: =IF(A160="","",SUMIFS(Sales!$H:$H,Sales!$F:$F,A160,Sales!$B:$B,"<>Return")) -> 0 | F160: =IF(A160="","",SUMIFS(Sales!$H:$H,Sales!$F:$F,A160,Sales!$B:$B,"Return")) -> 0 | G160: =IF($A160="","",SUMIF('Shop Ledger'!$C:$C,$A160,'Shop Ledger'!$F:$F)) -> 0 | H160: =IF(A160="","",D160-E160+F160-G160) -> 10 | I160: =IF(A160="","",IFERROR(SUMIF(Purchases!$D:$D,A160,Purchases!$I:$I)/D160,0)) -> 800 | J160: =IF(A160="","",H160*I160) -> 8000 | K160: =IF($A160="","",IFERROR(VALUE(SUBSTITUTE(SUBSTITUTE(SUBSTITUTE(VLOOKUP($A160,Inventory!$O$5:$P$604,2,FALSE),"Tk","")," ",""),",","")),"")) -> 1050 | L160: =IF(OR(I160="",K160="",K160=0),"",(K160-I160)/K160) -> 0.23809524 | M160: =IF(OR(I160="",K160="",K160=0,I160=0),"",(K160-I160)/I160) -> 0.3125 | O160: =IF($A160="","",$A160) -> FD-DRY-BON-KT-0001 | P160: 1050
A161: {=IFERROR(INDEX(Purchases!$D$5:$D$1004,MATCH(ROW()-4,Purchases!$L$5:$L$1004,0)),"")} | B161: =IFERROR(VLOOKUP(A161,Purchases!$D:$E,2,FALSE),"") | C161: =IFERROR(VLOOKUP(A161,Purchases!$D:$F,3,FALSE),"") | D161: =IF(A161="","",SUMIF(Purchases!$D:$D,A161,Purchases!$K:$K)) | E161: =IF(A161="","",SUMIFS(Sales!$H:$H,Sales!$F:$F,A161,Sales!$B:$B,"<>Return")) | F161: =IF(A161="","",SUMIFS(Sales!$H:$H,Sales!$F:$F,A161,Sales!$B:$B,"Return")) | G161: =IF($A161="","",SUMIF('Shop Ledger'!$C:$C,$A161,'Shop Ledger'!$F:$F)) | H161: =IF(A161="","",D161-E161+F161-G161) | I161: =IF(A161="","",IFERROR(SUMIF(Purchases!$D:$D,A161,Purchases!$I:$I)/D161,0)) | J161: =IF(A161="","",H161*I161) | K161: =IF($A161="","",IFERROR(VALUE(SUBSTITUTE(SUBSTITUTE(SUBSTITUTE(VLOOKUP($A161,Inventory!$O$5:$P$604,2,FALSE),"Tk","")," ",""),",","")),"")) | L161: =IF(OR(I161="",K161="",K161=0),"",(K161-I161)/K161) | M161: =IF(OR(I161="",K161="",K161=0,I161=0),"",(K161-I161)/I161) | O161: =IF($A161="","",$A161)
A162: {=IFERROR(INDEX(Purchases!$D$5:$D$1004,MATCH(ROW()-4,Purchases!$L$5:$L$1004,0)),"")} | B162: =IFERROR(VLOOKUP(A162,Purchases!$D:$E,2,FALSE),"") | C162: =IFERROR(VLOOKUP(A162,Purchases!$D:$F,3,FALSE),"") | D162: =IF(A162="","",SUMIF(Purchases!$D:$D,A162,Purchases!$K:$K)) | E162: =IF(A162="","",SUMIFS(Sales!$H:$H,Sales!$F:$F,A162,Sales!$B:$B,"<>Return")) | F162: =IF(A162="","",SUMIFS(Sales!$H:$H,Sales!$F:$F,A162,Sales!$B:$B,"Return")) | G162: =IF($A162="","",SUMIF('Shop Ledger'!$C:$C,$A162,'Shop Ledger'!$F:$F)) | H162: =IF(A162="","",D162-E162+F162-G162) | I162: =IF(A162="","",IFERROR(SUMIF(Purchases!$D:$D,A162,Purchases!$I:$I)/D162,0)) | J162: =IF(A162="","",H162*I162) | K162: =IF($A162="","",IFERROR(VALUE(SUBSTITUTE(SUBSTITUTE(SUBSTITUTE(VLOOKUP($A162,Inventory!$O$5:$P$604,2,FALSE),"Tk","")," ",""),",","")),"")) | L162: =IF(OR(I162="",K162="",K162=0),"",(K162-I162)/K162) | M162: =IF(OR(I162="",K162="",K162=0,I162=0),"",(K162-I162)/I162) | O162: =IF($A162="","",$A162)
A163: {=IFERROR(INDEX(Purchases!$D$5:$D$1004,MATCH(ROW()-4,Purchases!$L$5:$L$1004,0)),"")} | B163: =IFERROR(VLOOKUP(A163,Purchases!$D:$E,2,FALSE),"") | C163: =IFERROR(VLOOKUP(A163,Purchases!$D:$F,3,FALSE),"") | D163: =IF(A163="","",SUMIF(Purchases!$D:$D,A163,Purchases!$K:$K)) | E163: =IF(A163="","",SUMIFS(Sales!$H:$H,Sales!$F:$F,A163,Sales!$B:$B,"<>Return")) | F163: =IF(A163="","",SUMIFS(Sales!$H:$H,Sales!$F:$F,A163,Sales!$B:$B,"Return")) | G163: =IF($A163="","",SUMIF('Shop Ledger'!$C:$C,$A163,'Shop Ledger'!$F:$F)) | H163: =IF(A163="","",D163-E163+F163-G163) | I163: =IF(A163="","",IFERROR(SUMIF(Purchases!$D:$D,A163,Purchases!$I:$I)/D163,0)) | J163: =IF(A163="","",H163*I163) | K163: =IF($A163="","",IFERROR(VALUE(SUBSTITUTE(SUBSTITUTE(SUBSTITUTE(VLOOKUP($A163,Inventory!$O$5:$P$604,2,FALSE),"Tk","")," ",""),",","")),"")) | L163: =IF(OR(I163="",K163="",K163=0),"",(K163-I163)/K163) | M163: =IF(OR(I163="",K163="",K163=0,I163=0),"",(K163-I163)/I163) | O163: =IF($A163="","",$A163)
A164: {=IFERROR(INDEX(Purchases!$D$5:$D$1004,MATCH(ROW()-4,Purchases!$L$5:$L$1004,0)),"")} | B164: =IFERROR(VLOOKUP(A164,Purchases!$D:$E,2,FALSE),"") | C164: =IFERROR(VLOOKUP(A164,Purchases!$D:$F,3,FALSE),"") | D164: =IF(A164="","",SUMIF(Purchases!$D:$D,A164,Purchases!$K:$K)) | E164: =IF(A164="","",SUMIFS(Sales!$H:$H,Sales!$F:$F,A164,Sales!$B:$B,"<>Return")) | F164: =IF(A164="","",SUMIFS(Sales!$H:$H,Sales!$F:$F,A164,Sales!$B:$B,"Return")) | G164: =IF($A164="","",SUMIF('Shop Ledger'!$C:$C,$A164,'Shop Ledger'!$F:$F)) | H164: =IF(A164="","",D164-E164+F164-G164) | I164: =IF(A164="","",IFERROR(SUMIF(Purchases!$D:$D,A164,Purchases!$I:$I)/D164,0)) | J164: =IF(A164="","",H164*I164) | K164: =IF($A164="","",IFERROR(VALUE(SUBSTITUTE(SUBSTITUTE(SUBSTITUTE(VLOOKUP($A164,Inventory!$O$5:$P$604,2,FALSE),"Tk","")," ",""),",","")),"")) | L164: =IF(OR(I164="",K164="",K164=0),"",(K164-I164)/K164) | M164: =IF(OR(I164="",K164="",K164=0,I164=0),"",(K164-I164)/I164) | O164: =IF($A164="","",$A164)
A165: {=IFERROR(INDEX(Purchases!$D$5:$D$1004,MATCH(ROW()-4,Purchases!$L$5:$L$1004,0)),"")} | B165: =IFERROR(VLOOKUP(A165,Purchases!$D:$E,2,FALSE),"") | C165: =IFERROR(VLOOKUP(A165,Purchases!$D:$F,3,FALSE),"") | D165: =IF(A165="","",SUMIF(Purchases!$D:$D,A165,Purchases!$K:$K)) | E165: =IF(A165="","",SUMIFS(Sales!$H:$H,Sales!$F:$F,A165,Sales!$B:$B,"<>Return")) | F165: =IF(A165="","",SUMIFS(Sales!$H:$H,Sales!$F:$F,A165,Sales!$B:$B,"Return")) | G165: =IF($A165="","",SUMIF('Shop Ledger'!$C:$C,$A165,'Shop Ledger'!$F:$F)) | H165: =IF(A165="","",D165-E165+F165-G165) | I165: =IF(A165="","",IFERROR(SUMIF(Purchases!$D:$D,A165,Purchases!$I:$I)/D165,0)) | J165: =IF(A165="","",H165*I165) | K165: =IF($A165="","",IFERROR(VALUE(SUBSTITUTE(SUBSTITUTE(SUBSTITUTE(VLOOKUP($A165,Inventory!$O$5:$P$604,2,FALSE),"Tk","")," ",""),",","")),"")) | L165: =IF(OR(I165="",K165="",K165=0),"",(K165-I165)/K165) | M165: =IF(OR(I165="",K165="",K165=0,I165=0),"",(K165-I165)/I165) | O165: =IF($A165="","",$A165)
A166: {=IFERROR(INDEX(Purchases!$D$5:$D$1004,MATCH(ROW()-4,Purchases!$L$5:$L$1004,0)),"")} | B166: =IFERROR(VLOOKUP(A166,Purchases!$D:$E,2,FALSE),"") | C166: =IFERROR(VLOOKUP(A166,Purchases!$D:$F,3,FALSE),"") | D166: =IF(A166="","",SUMIF(Purchases!$D:$D,A166,Purchases!$K:$K)) | E166: =IF(A166="","",SUMIFS(Sales!$H:$H,Sales!$F:$F,A166,Sales!$B:$B,"<>Return")) | F166: =IF(A166="","",SUMIFS(Sales!$H:$H,Sales!$F:$F,A166,Sales!$B:$B,"Return")) | G166: =IF($A166="","",SUMIF('Shop Ledger'!$C:$C,$A166,'Shop Ledger'!$F:$F)) | H166: =IF(A166="","",D166-E166+F166-G166) | I166: =IF(A166="","",IFERROR(SUMIF(Purchases!$D:$D,A166,Purchases!$I:$I)/D166,0)) | J166: =IF(A166="","",H166*I166) | K166: =IF($A166="","",IFERROR(VALUE(SUBSTITUTE(SUBSTITUTE(SUBSTITUTE(VLOOKUP($A166,Inventory!$O$5:$P$604,2,FALSE),"Tk","")," ",""),",","")),"")) | L166: =IF(OR(I166="",K166="",K166=0),"",(K166-I166)/K166) | M166: =IF(OR(I166="",K166="",K166=0,I166=0),"",(K166-I166)/I166) | O166: =IF($A166="","",$A166)
A167: {=IFERROR(INDEX(Purchases!$D$5:$D$1004,MATCH(ROW()-4,Purchases!$L$5:$L$1004,0)),"")} | B167: =IFERROR(VLOOKUP(A167,Purchases!$D:$E,2,FALSE),"") | C167: =IFERROR(VLOOKUP(A167,Purchases!$D:$F,3,FALSE),"") | D167: =IF(A167="","",SUMIF(Purchases!$D:$D,A167,Purchases!$K:$K)) | E167: =IF(A167="","",SUMIFS(Sales!$H:$H,Sales!$F:$F,A167,Sales!$B:$B,"<>Return")) | F167: =IF(A167="","",SUMIFS(Sales!$H:$H,Sales!$F:$F,A167,Sales!$B:$B,"Return")) | G167: =IF($A167="","",SUMIF('Shop Ledger'!$C:$C,$A167,'Shop Ledger'!$F:$F)) | H167: =IF(A167="","",D167-E167+F167-G167) | I167: =IF(A167="","",IFERROR(SUMIF(Purchases!$D:$D,A167,Purchases!$I:$I)/D167,0)) | J167: =IF(A167="","",H167*I167) | K167: =IF($A167="","",IFERROR(VALUE(SUBSTITUTE(SUBSTITUTE(SUBSTITUTE(VLOOKUP($A167,Inventory!$O$5:$P$604,2,FALSE),"Tk","")," ",""),",","")),"")) | L167: =IF(OR(I167="",K167="",K167=0),"",(K167-I167)/K167) | M167: =IF(OR(I167="",K167="",K167=0,I167=0),"",(K167-I167)/I167) | O167: =IF($A167="","",$A167)
A168: {=IFERROR(INDEX(Purchases!$D$5:$D$1004,MATCH(ROW()-4,Purchases!$L$5:$L$1004,0)),"")} | B168: =IFERROR(VLOOKUP(A168,Purchases!$D:$E,2,FALSE),"") | C168: =IFERROR(VLOOKUP(A168,Purchases!$D:$F,3,FALSE),"") | D168: =IF(A168="","",SUMIF(Purchases!$D:$D,A168,Purchases!$K:$K)) | E168: =IF(A168="","",SUMIFS(Sales!$H:$H,Sales!$F:$F,A168,Sales!$B:$B,"<>Return")) | F168: =IF(A168="","",SUMIFS(Sales!$H:$H,Sales!$F:$F,A168,Sales!$B:$B,"Return")) | G168: =IF($A168="","",SUMIF('Shop Ledger'!$C:$C,$A168,'Shop Ledger'!$F:$F)) | H168: =IF(A168="","",D168-E168+F168-G168) | I168: =IF(A168="","",IFERROR(SUMIF(Purchases!$D:$D,A168,Purchases!$I:$I)/D168,0)) | J168: =IF(A168="","",H168*I168) | K168: =IF($A168="","",IFERROR(VALUE(SUBSTITUTE(SUBSTITUTE(SUBSTITUTE(VLOOKUP($A168,Inventory!$O$5:$P$604,2,FALSE),"Tk","")," ",""),",","")),"")) | L168: =IF(OR(I168="",K168="",K168=0),"",(K168-I168)/K168) | M168: =IF(OR(I168="",K168="",K168=0,I168=0),"",(K168-I168)/I168) | O168: =IF($A168="","",$A168)
A169: {=IFERROR(INDEX(Purchases!$D$5:$D$1004,MATCH(ROW()-4,Purchases!$L$5:$L$1004,0)),"")} | B169: =IFERROR(VLOOKUP(A169,Purchases!$D:$E,2,FALSE),"") | C169: =IFERROR(VLOOKUP(A169,Purchases!$D:$F,3,FALSE),"") | D169: =IF(A169="","",SUMIF(Purchases!$D:$D,A169,Purchases!$K:$K)) | E169: =IF(A169="","",SUMIFS(Sales!$H:$H,Sales!$F:$F,A169,Sales!$B:$B,"<>Return")) | F169: =IF(A169="","",SUMIFS(Sales!$H:$H,Sales!$F:$F,A169,Sales!$B:$B,"Return")) | G169: =IF($A169="","",SUMIF('Shop Ledger'!$C:$C,$A169,'Shop Ledger'!$F:$F)) | H169: =IF(A169="","",D169-E169+F169-G169) | I169: =IF(A169="","",IFERROR(SUMIF(Purchases!$D:$D,A169,Purchases!$I:$I)/D169,0)) | J169: =IF(A169="","",H169*I169) | K169: =IF($A169="","",IFERROR(VALUE(SUBSTITUTE(SUBSTITUTE(SUBSTITUTE(VLOOKUP($A169,Inventory!$O$5:$P$604,2,FALSE),"Tk","")," ",""),",","")),"")) | L169: =IF(OR(I169="",K169="",K169=0),"",(K169-I169)/K169) | M169: =IF(OR(I169="",K169="",K169=0,I169=0),"",(K169-I169)/I169) | O169: =IF($A169="","",$A169)
A170: {=IFERROR(INDEX(Purchases!$D$5:$D$1004,MATCH(ROW()-4,Purchases!$L$5:$L$1004,0)),"")} | B170: =IFERROR(VLOOKUP(A170,Purchases!$D:$E,2,FALSE),"") | C170: =IFERROR(VLOOKUP(A170,Purchases!$D:$F,3,FALSE),"") | D170: =IF(A170="","",SUMIF(Purchases!$D:$D,A170,Purchases!$K:$K)) | E170: =IF(A170="","",SUMIFS(Sales!$H:$H,Sales!$F:$F,A170,Sales!$B:$B,"<>Return")) | F170: =IF(A170="","",SUMIFS(Sales!$H:$H,Sales!$F:$F,A170,Sales!$B:$B,"Return")) | G170: =IF($A170="","",SUMIF('Shop Ledger'!$C:$C,$A170,'Shop Ledger'!$F:$F)) | H170: =IF(A170="","",D170-E170+F170-G170) | I170: =IF(A170="","",IFERROR(SUMIF(Purchases!$D:$D,A170,Purchases!$I:$I)/D170,0)) | J170: =IF(A170="","",H170*I170) | K170: =IF($A170="","",IFERROR(VALUE(SUBSTITUTE(SUBSTITUTE(SUBSTITUTE(VLOOKUP($A170,Inventory!$O$5:$P$604,2,FALSE),"Tk","")," ",""),",","")),"")) | L170: =IF(OR(I170="",K170="",K170=0),"",(K170-I170)/K170) | M170: =IF(OR(I170="",K170="",K170=0,I170=0),"",(K170-I170)/I170) | O170: =IF($A170="","",$A170)
A171: {=IFERROR(INDEX(Purchases!$D$5:$D$1004,MATCH(ROW()-4,Purchases!$L$5:$L$1004,0)),"")} | B171: =IFERROR(VLOOKUP(A171,Purchases!$D:$E,2,FALSE),"") | C171: =IFERROR(VLOOKUP(A171,Purchases!$D:$F,3,FALSE),"") | D171: =IF(A171="","",SUMIF(Purchases!$D:$D,A171,Purchases!$K:$K)) | E171: =IF(A171="","",SUMIFS(Sales!$H:$H,Sales!$F:$F,A171,Sales!$B:$B,"<>Return")) | F171: =IF(A171="","",SUMIFS(Sales!$H:$H,Sales!$F:$F,A171,Sales!$B:$B,"Return")) | G171: =IF($A171="","",SUMIF('Shop Ledger'!$C:$C,$A171,'Shop Ledger'!$F:$F)) | H171: =IF(A171="","",D171-E171+F171-G171) | I171: =IF(A171="","",IFERROR(SUMIF(Purchases!$D:$D,A171,Purchases!$I:$I)/D171,0)) | J171: =IF(A171="","",H171*I171) | K171: =IF($A171="","",IFERROR(VALUE(SUBSTITUTE(SUBSTITUTE(SUBSTITUTE(VLOOKUP($A171,Inventory!$O$5:$P$604,2,FALSE),"Tk","")," ",""),",","")),"")) | L171: =IF(OR(I171="",K171="",K171=0),"",(K171-I171)/K171) | M171: =IF(OR(I171="",K171="",K171=0,I171=0),"",(K171-I171)/I171) | O171: =IF($A171="","",$A171)
A172: {=IFERROR(INDEX(Purchases!$D$5:$D$1004,MATCH(ROW()-4,Purchases!$L$5:$L$1004,0)),"")} | B172: =IFERROR(VLOOKUP(A172,Purchases!$D:$E,2,FALSE),"") | C172: =IFERROR(VLOOKUP(A172,Purchases!$D:$F,3,FALSE),"") | D172: =IF(A172="","",SUMIF(Purchases!$D:$D,A172,Purchases!$K:$K)) | E172: =IF(A172="","",SUMIFS(Sales!$H:$H,Sales!$F:$F,A172,Sales!$B:$B,"<>Return")) | F172: =IF(A172="","",SUMIFS(Sales!$H:$H,Sales!$F:$F,A172,Sales!$B:$B,"Return")) | G172: =IF($A172="","",SUMIF('Shop Ledger'!$C:$C,$A172,'Shop Ledger'!$F:$F)) | H172: =IF(A172="","",D172-E172+F172-G172) | I172: =IF(A172="","",IFERROR(SUMIF(Purchases!$D:$D,A172,Purchases!$I:$I)/D172,0)) | J172: =IF(A172="","",H172*I172) | K172: =IF($A172="","",IFERROR(VALUE(SUBSTITUTE(SUBSTITUTE(SUBSTITUTE(VLOOKUP($A172,Inventory!$O$5:$P$604,2,FALSE),"Tk","")," ",""),",","")),"")) | L172: =IF(OR(I172="",K172="",K172=0),"",(K172-I172)/K172) | M172: =IF(OR(I172="",K172="",K172=0,I172=0),"",(K172-I172)/I172) | O172: =IF($A172="","",$A172)
... A604: {=IFERROR(INDEX(Purchases!$D$5:$D$1004,MATCH(ROW()-4,Purchases!$L$5:$L$1004,0)),"")} | B604: =IFERROR(VLOOKUP(A604,Purchases!$D:$E,2,FALSE),"") | C604: =IFERROR(VLOOKUP(A604,Purchases!$D:$F,3,FALSE),"") | D604: =IF(A604="","",SUMIF(Purchases!$D:$D,A604,Purchases!$K:$K)) | E604: =IF(A604="","",SUMIFS(Sales!$H:$H,Sales!$F:$F,A604,Sales!$B:$B,"<>Return")) | F604: =IF(A604="","",SUMIFS(Sales!$H:$H,Sales!$F:$F,A604,Sales!$B:$B,"Return")) | G604: =IF($A604="","",SUMIF('Shop Ledger'!$C:$C,$A604,'Shop Ledger'!$F:$F)) | H604: =IF(A604="","",D604-E604+F604-G604) | I604: =IF(A604="","",IFERROR(SUMIF(Purchases!$D:$D,A604,Purchases!$I:$I)/D604,0)) | J604: =IF(A604="","",H604*I604) | K604: =IF($A604="","",IFERROR(VALUE(SUBSTITUTE(SUBSTITUTE(SUBSTITUTE(VLOOKUP($A604,Inventory!$O$5:$P$604,2,FALSE),"Tk","")," ",""),",","")),"")) | L604: =IF(OR(I604="",K604="",K604=0),"",(K604-I604)/K604) | M604: =IF(OR(I604="",K604="",K604=0,I604=0),"",(K604-I604)/I604) | O604: =IF($A604="","",$A604)

Sheet Sales
A1: SALES LOG | K1: SALES SUMMARY | AC1: TEST 1 - typed list -> click AD1 | AF1: ALPHA | AG1: =IF(AF1="","",AF1) -> ALPHA
A2: Enter each sale or return here. Type = "Sale" or "Return". Description, Unit Cost, Total Cost & Profit auto-calculate. | K2: Total Sales | L2: =SUM(Sales!$L$7:$L$1506) -> 147710.01 | M2: Cost of Goods | N2: =SUM(Sales!$O$7:$O$1506) -> 114725.88 | O2: Product Profit | P2: =SUM(Sales!$P$7:$P$1506) -> 32984.131 | AC2: TEST 2 - static range -> click AD2 | AF2: BRAVO | AG2: =IF(AF2="","",AF2) -> BRAVO
K3: Delivery Charged | L3: =SUM(Sales!$R$7:$R$1506) -> 1890 | M3: Delivery You Paid | N3: =SUM(Sales!$S$7:$S$1506) -> 1995 | O3: REAL Profit | P3: =SUM(Sales!$T$7:$T$1506) -> 32731.095 | AC3: TEST 3 - formula range -> click AD3 | AF3: CHARLIE | AG3: =IF(AF3="","",AF3) -> CHARLIE
K4: Total Due | L4: =SUMIFS(Sales!$L$7:$L$1506,Sales!$M$7:$M$1506,"Due") -> 6812.004 | M4: Profit Collected | N4: =SUMIFS(Sales!$T$7:$T$1506,Sales!$M$7:$M$1506,"Paid") -> 30785.757 | O4: Profit Pending | P4: =SUMIFS(Sales!$T$7:$T$1506,Sales!$M$7:$M$1506,"Due") -> 1544.8463
A6: Date | B6: Type | C6: Channel | D6: Customer | E6: Invoice Number | F6: Item Code (click here ↓ for dropdown) | G6: Product Description (auto-fills) | H6: Qty | I6: Unit Price (Tk) | J6: MRP (Tk) | K6: Discount (Tk) | L6: Total Amount (Tk) | M6: Payment Status | N6: Unit Cost (Tk) | O6: Total Cost (Tk) | P6: Profit (Tk) | Q6: Notes | R6: Delivery Charged to Customer (auto from Orders) | S6: Delivery Cost You Paid (auto from Orders) | T6: REAL Profit incl. Delivery (Tk) | U6: Profit for WHOLE Invoice (Tk) | V6: Helper - online invoice order | W6: Helper - sorted position | X6: Helper - line no. within month | Y6: Helper - month key | AA6: Item code list (feeds the dropdown — do not type here)
A7: 46219 | B7: Sale | C7: Online | D7: Samreen islam | E7: PAWF-260715-04EAA | F7: FD-DRY-SMHRT-15KG-001 | G7: =IF($F7="","",IFERROR(VLOOKUP($F7,Inventory!$A:$B,2,FALSE),"")) -> Smart Heart Adult Cat Food Chicken & Tuna [15kg] | H7: 1 | I7: =IF($F7="","",IF($B7="Gift",0,J7-IF(K7="",0,K7))) -> 6400 | J7: =IF($F7="","",IFERROR(VLOOKUP($F7,Inventory!$A:$K,11,FALSE),0)) -> 6700 | K7: 300 | L7: =IF($F7="","",IF($B7="Return",-H7*I7,H7*I7)) -> 6400 | M7: Paid | N7: =IF($F7="","",IFERROR(VLOOKUP($F7,Inventory!$A:$I,9,FALSE),0)) -> 5700 | O7: =IF($F7="","",IF($B7="Return",-H7*N7,H7*N7)) -> 5700 | P7: =IF($F7="","",L7-O7) -> 700 | R7: =IF($E7="","",IF(COUNTIF($E$7:$E7,$E7)>1,"",IFERROR(VLOOKUP($E7,Orders!$A:$I,8,FALSE),""))) -> 200 | S7: =IF($E7="","",IF(COUNTIF($E$7:$E7,$E7)>1,"",IFERROR(VLOOKUP($E7,Orders!$A:$I,9,FALSE),""))) -> 200 | T7: =IF($F7="","",P7+IF(R7="",0,R7)-IF(S7="",0,S7)) -> 700 | U7: =IF($F7="","",IF($E7="",T7,SUMIF(Sales!$E$7:$E$1506,$E7,Sales!$T$7:$T$1506))) -> 1100 | V7: =IF(OR($C7<>"Online",$E7=""),"",IF(COUNTIF($E$7:$E7,$E7)>1,"",COUNT($V$6:V6)+1)) -> 1 | W7: {=IF($V7="","",SUMPRODUCT((Sales!$V$7:$V$1506<>"")*(Sales!$E$7:$E$1506<$E7))+1)} -> 2 | X7: =IF($A7="","",COUNTIFS($A$7:$A7,">="&EOMONTH($A7,-1)+1,$A$7:$A7,"<="&EOMONTH($A7,0))) -> 1 | Y7: =IF($A7="","",TEXT($A7,"yyyymm")&"-"&$X7) -> 202607-1 | AA7: =IF(Inventory!A5="","",Inventory!A5) -> AC-PNC-LR-002
A8: 46219 | B8: Sale | C8: Online | D8: Samreen islam | E8: PAWF-260715-04EAA | F8: FD-DRY-SMHRT-10KG-001 | G8: =IF($F8="","",IFERROR(VLOOKUP($F8,Inventory!$A:$B,2,FALSE),"")) -> Smart Heart 10KG Chicken & Tuna | H8: 2 | I8: =IF($F8="","",IF($B8="Gift",0,J8-IF(K8="",0,K8))) -> 4300 | J8: =IF($F8="","",IFERROR(VLOOKUP($F8,Inventory!$A:$K,11,FALSE),0)) -> 4700 | K8: 400 | L8: =IF($F8="","",IF($B8="Return",-H8*I8,H8*I8)) -> 8600 | M8: Paid | N8: =IF($F8="","",IFERROR(VLOOKUP($F8,Inventory!$A:$I,9,FALSE),0)) -> 4100 | O8: =IF($F8="","",IF($B8="Return",-H8*N8,H8*N8)) -> 8200 | P8: =IF($F8="","",L8-O8) -> 400 | R8: =IF($E8="","",IF(COUNTIF($E$7:$E8,$E8)>1,"",IFERROR(VLOOKUP($E8,Orders!$A:$I,8,FALSE),""))) | S8: =IF($E8="","",IF(COUNTIF($E$7:$E8,$E8)>1,"",IFERROR(VLOOKUP($E8,Orders!$A:$I,9,FALSE),""))) | T8: =IF($F8="","",P8+IF(R8="",0,R8)-IF(S8="",0,S8)) -> 400 | U8: =IF($F8="","",IF($E8="",T8,SUMIF(Sales!$E$7:$E$1506,$E8,Sales!$T$7:$T$1506))) -> 1100 | V8: =IF(OR($C8<>"Online",$E8=""),"",IF(COUNTIF($E$7:$E8,$E8)>1,"",COUNT($V$6:V7)+1)) | W8: {=IF($V8="","",SUMPRODUCT((Sales!$V$7:$V$1506<>"")*(Sales!$E$7:$E$1506<$E8))+1)} | X8: =IF($A8="","",COUNTIFS($A$7:$A8,">="&EOMONTH($A8,-1)+1,$A$7:$A8,"<="&EOMONTH($A8,0))) -> 2 | Y8: =IF($A8="","",TEXT($A8,"yyyymm")&"-"&$X8) -> 202607-2 | AA8: =IF(Inventory!A6="","",Inventory!A6) -> AC-CTOY-004
A9: 46216 | B9: Sale | C9: Online | D9: Johura Hoque | E9: PAWF-260713-BAADD | F9: AC-CJ-AR-001 | G9: =IF($F9="","",IFERROR(VLOOKUP($F9,Inventory!$A:$B,2,FALSE),"")) -> Cat Jersey Argentina Medium | H9: 2 | I9: =IF($F9="","",IF($B9="Gift",0,J9-IF(K9="",0,K9))) -> 282 | J9: =IF($F9="","",IFERROR(VLOOKUP($F9,Inventory!$A:$K,11,FALSE),0)) -> 300 | K9: 18 | L9: =IF($F9="","",IF($B9="Return",-H9*I9,H9*I9)) -> 564 | M9: Paid | N9: =IF($F9="","",IFERROR(VLOOKUP($F9,Inventory!$A:$I,9,FALSE),0)) -> 140 | O9: =IF($F9="","",IF($B9="Return",-H9*N9,H9*N9)) -> 280 | P9: =IF($F9="","",L9-O9) -> 284 | Q9: Bkash | R9: =IF($E9="","",IF(COUNTIF($E$7:$E9,$E9)>1,"",IFERROR(VLOOKUP($E9,Orders!$A:$I,8,FALSE),""))) -> 80 | S9: =IF($E9="","",IF(COUNTIF($E$7:$E9,$E9)>1,"",IFERROR(VLOOKUP($E9,Orders!$A:$I,9,FALSE),""))) -> 36 | T9: =IF($F9="","",P9+IF(R9="",0,R9)-IF(S9="",0,S9)) -> 328 | U9: =IF($F9="","",IF($E9="",T9,SUMIF(Sales!$E$7:$E$1506,$E9,Sales!$T$7:$T$1506))) -> 328 | V9: =IF(OR($C9<>"Online",$E9=""),"",IF(COUNTIF($E$7:$E9,$E9)>1,"",COUNT($V$6:V8)+1)) -> 2 | W9: {=IF($V9="","",SUMPRODUCT((Sales!$V$7:$V$1506<>"")*(Sales!$E$7:$E$1506<$E9))+1)} -> 1 | X9: =IF($A9="","",COUNTIFS($A$7:$A9,">="&EOMONTH($A9,-1)+1,$A$7:$A9,"<="&EOMONTH($A9,0))) -> 3 | Y9: =IF($A9="","",TEXT($A9,"yyyymm")&"-"&$X9) -> 202607-3 | AA9: =IF(Inventory!A7="","",Inventory!A7) -> AC-CB-001
A10: 46221 | B10: Sale | C10: Online | D10: Nadim | E10: PAWF-260718-8CA86 | F10: FD-DRY-SMHRT-15KG-001 | G10: =IF($F10="","",IFERROR(VLOOKUP($F10,Inventory!$A:$B,2,FALSE),"")) -> Smart Heart Adult Cat Food Chicken & Tuna [15kg] | H10: 1 | I10: =IF($F10="","",IF($B10="Gift",0,J10-IF(K10="",0,K10))) -> 6100 | J10: =IF($F10="","",IFERROR(VLOOKUP($F10,Inventory!$A:$K,11,FALSE),0)) -> 6700 | K10: 600 | L10: =IF($F10="","",IF($B10="Return",-H10*I10,H10*I10)) -> 6100 | M10: Paid | N10: =IF($F10="","",IFERROR(VLOOKUP($F10,Inventory!$A:$I,9,FALSE),0)) -> 5700 | O10: =IF($F10="","",IF($B10="Return",-H10*N10,H10*N10)) -> 5700 | P10: =IF($F10="","",L10-O10) -> 400 | R10: =IF($E10="","",IF(COUNTIF($E$7:$E10,$E10)>1,"",IFERROR(VLOOKUP($E10,Orders!$A:$I,8,FALSE),""))) -> 0 | S10: =IF($E10="","",IF(COUNTIF($E$7:$E10,$E10)>1,"",IFERROR(VLOOKUP($E10,Orders!$A:$I,9,FALSE),""))) -> 0 | T10: =IF($F10="","",P10+IF(R10="",0,R10)-IF(S10="",0,S10)) -> 400 | U10: =IF($F10="","",IF($E10="",T10,SUMIF(Sales!$E$7:$E$1506,$E10,Sales!$T$7:$T$1506))) -> 220 | V10: =IF(OR($C10<>"Online",$E10=""),"",IF(COUNTIF($E$7:$E10,$E10)>1,"",COUNT($V$6:V9)+1)) -> 3 | W10: {=IF($V10="","",SUMPRODUCT((Sales!$V$7:$V$1506<>"")*(Sales!$E$7:$E$1506<$E10))+1)} -> 3 | X10: =IF($A10="","",COUNTIFS($A$7:$A10,">="&EOMONTH($A10,-1)+1,$A$7:$A10,"<="&EOMONTH($A10,0))) -> 4 | Y10: =IF($A10="","",TEXT($A10,"yyyymm")&"-"&$X10) -> 202607-4 | AA10: =IF(Inventory!A8="","",Inventory!A8) -> PO-WET-NK-70G-001
A11: 46210 | B11: Sale | C11: Shop | D11: PawfectBD Shop | E11: PAWF-260719-979C1 | F11: TR-CRMY-15G-001 | G11: =IF($F11="","",IFERROR(VLOOKUP($F11,Inventory!$A:$B,2,FALSE),"")) -> Creamy Treat 15G (Purry & Hyper Paws) | H11: 40 | I11: =IF($F11="","",IF($B11="Gift",0,J11-IF(K11="",0,K11))) -> 19.5 | J11: =IF($F11="","",IFERROR(VLOOKUP($F11,Inventory!$A:$K,11,FALSE),0)) -> 20 | K11: 0.5 | L11: =IF($F11="","",IF($B11="Return",-H11*I11,H11*I11)) -> 780 | M11: Paid | N11: =IF($F11="","",IFERROR(VLOOKUP($F11,Inventory!$A:$I,9,FALSE),0)) -> 8.1474119 | O11: =IF($F11="","",IF($B11="Return",-H11*N11,H11*N11)) -> 325.89647 | P11: =IF($F11="","",L11-O11) -> 454.10353 | R11: =IF($E11="","",IF(COUNTIF($E$7:$E11,$E11)>1,"",IFERROR(VLOOKUP($E11,Orders!$A:$I,8,FALSE),""))) | S11: =IF($E11="","",IF(COUNTIF($E$7:$E11,$E11)>1,"",IFERROR(VLOOKUP($E11,Orders!$A:$I,9,FALSE),""))) | T11: =IF($F11="","",P11+IF(R11="",0,R11)-IF(S11="",0,S11)) -> 454.10353 | U11: =IF($F11="","",IF($E11="",T11,SUMIF(Sales!$E$7:$E$1506,$E11,Sales!$T$7:$T$1506))) -> 908.20705 | V11: =IF(OR($C11<>"Online",$E11=""),"",IF(COUNTIF($E$7:$E11,$E11)>1,"",COUNT($V$6:V10)+1)) | W11: {=IF($V11="","",SUMPRODUCT((Sales!$V$7:$V$1506<>"")*(Sales!$E$7:$E$1506<$E11))+1)} | X11: =IF($A11="","",COUNTIFS($A$7:$A11,">="&EOMONTH($A11,-1)+1,$A$7:$A11,"<="&EOMONTH($A11,0))) -> 5 | Y11: =IF($A11="","",TEXT($A11,"yyyymm")&"-"&$X11) -> 202607-5 | AA11: =IF(Inventory!A9="","",Inventory!A9) -> AC-CJ-AR-001
A12: 46211 | B12: Sale | C12: Shop | D12: PawfectBD Shop | E12: PAWF-260719-979C1 | F12: TR-CRMY-15G-001 | G12: =IF($F12="","",IFERROR(VLOOKUP($F12,Inventory!$A:$B,2,FALSE),"")) -> Creamy Treat 15G (Purry & Hyper Paws) | H12: 40 | I12: =IF($F12="","",IF($B12="Gift",0,J12-IF(K12="",0,K12))) -> 19.5 | J12: =IF($F12="","",IFERROR(VLOOKUP($F12,Inventory!$A:$K,11,FALSE),0)) -> 20 | K12: 0.5 | L12: =IF($F12="","",IF($B12="Return",-H12*I12,H12*I12)) -> 780 | M12: Paid | N12: =IF($F12="","",IFERROR(VLOOKUP($F12,Inventory!$A:$I,9,FALSE),0)) -> 8.1474119 | O12: =IF($F12="","",IF($B12="Return",-H12*N12,H12*N12)) -> 325.89647 | P12: =IF($F12="","",L12-O12) -> 454.10353 | R12: =IF($E12="","",IF(COUNTIF($E$7:$E12,$E12)>1,"",IFERROR(VLOOKUP($E12,Orders!$A:$I,8,FALSE),""))) | S12: =IF($E12="","",IF(COUNTIF($E$7:$E12,$E12)>1,"",IFERROR(VLOOKUP($E12,Orders!$A:$I,9,FALSE),""))) | T12: =IF($F12="","",P12+IF(R12="",0,R12)-IF(S12="",0,S12)) -> 454.10353 | U12: =IF($F12="","",IF($E12="",T12,SUMIF(Sales!$E$7:$E$1506,$E12,Sales!$T$7:$T$1506))) -> 908.20705 | V12: =IF(OR($C12<>"Online",$E12=""),"",IF(COUNTIF($E$7:$E12,$E12)>1,"",COUNT($V$6:V11)+1)) | W12: {=IF($V12="","",SUMPRODUCT((Sales!$V$7:$V$1506<>"")*(Sales!$E$7:$E$1506<$E12))+1)} | X12: =IF($A12="","",COUNTIFS($A$7:$A12,">="&EOMONTH($A12,-1)+1,$A$7:$A12,"<="&EOMONTH($A12,0))) -> 6 | Y12: =IF($A12="","",TEXT($A12,"yyyymm")&"-"&$X12) -> 202607-6 | AA12: =IF(Inventory!A10="","",Inventory!A10) -> AC-CJ-AR-002
A13: 46212 | B13: Sale | C13: Shop | D13: PawfectBD Shop | E13: PAWF-260719-FCE0C | F13: FD-DRY-CHNK-OCFCK-1.5KG-001 | G13: =IF($F13="","",IFERROR(VLOOKUP($F13,Inventory!$A:$B,2,FALSE),"")) -> Chonk All ages Ocean Fish with Chicken | H13: 1 | I13: =IF($F13="","",IF($B13="Gift",0,J13-IF(K13="",0,K13))) -> 500 | J13: =IF($F13="","",IFERROR(VLOOKUP($F13,Inventory!$A:$K,11,FALSE),0)) -> 500 | L13: =IF($F13="","",IF($B13="Return",-H13*I13,H13*I13)) -> 500 | M13: Paid | N13: =IF($F13="","",IFERROR(VLOOKUP($F13,Inventory!$A:$I,9,FALSE),0)) -> 400 | O13: =IF($F13="","",IF($B13="Return",-H13*N13,H13*N13)) -> 400 | P13: =IF($F13="","",L13-O13) -> 100 | R13: =IF($E13="","",IF(COUNTIF($E$7:$E13,$E13)>1,"",IFERROR(VLOOKUP($E13,Orders!$A:$I,8,FALSE),""))) | S13: =IF($E13="","",IF(COUNTIF($E$7:$E13,$E13)>1,"",IFERROR(VLOOKUP($E13,Orders!$A:$I,9,FALSE),""))) | T13: =IF($F13="","",P13+IF(R13="",0,R13)-IF(S13="",0,S13)) -> 100 | U13: =IF($F13="","",IF($E13="",T13,SUMIF(Sales!$E$7:$E$1506,$E13,Sales!$T$7:$T$1506))) -> 300 | V13: =IF(OR($C13<>"Online",$E13=""),"",IF(COUNTIF($E$7:$E13,$E13)>1,"",COUNT($V$6:V12)+1)) | W13: {=IF($V13="","",SUMPRODUCT((Sales!$V$7:$V$1506<>"")*(Sales!$E$7:$E$1506<$E13))+1)} | X13: =IF($A13="","",COUNTIFS($A$7:$A13,">="&EOMONTH($A13,-1)+1,$A$7:$A13,"<="&EOMONTH($A13,0))) -> 7 | Y13: =IF($A13="","",TEXT($A13,"yyyymm")&"-"&$X13) -> 202607-7 | AA13: =IF(Inventory!A11="","",Inventory!A11) -> AC-CJ-BR-002
A14: 46213 | B14: Sale | C14: Shop | D14: PawfectBD Shop | E14: PAWF-260719-FCE0C | F14: FD-DRY-CHNK-TN-1.5KG-001 | G14: =IF($F14="","",IFERROR(VLOOKUP($F14,Inventory!$A:$B,2,FALSE),"")) -> Chonk All ages Tuna | H14: 2 | I14: =IF($F14="","",IF($B14="Gift",0,J14-IF(K14="",0,K14))) -> 500 | J14: =IF($F14="","",IFERROR(VLOOKUP($F14,Inventory!$A:$K,11,FALSE),0)) -> 500 | L14: =IF($F14="","",IF($B14="Return",-H14*I14,H14*I14)) -> 1000 | M14: Paid | N14: =IF($F14="","",IFERROR(VLOOKUP($F14,Inventory!$A:$I,9,FALSE),0)) -> 400 | O14: =IF($F14="","",IF($B14="Return",-H14*N14,H14*N14)) -> 800 | P14: =IF($F14="","",L14-O14) -> 200 | R14: =IF($E14="","",IF(COUNTIF($E$7:$E14,$E14)>1,"",IFERROR(VLOOKUP($E14,Orders!$A:$I,8,FALSE),""))) | S14: =IF($E14="","",IF(COUNTIF($E$7:$E14,$E14)>1,"",IFERROR(VLOOKUP($E14,Orders!$A:$I,9,FALSE),""))) | T14: =IF($F14="","",P14+IF(R14="",0,R14)-IF(S14="",0,S14)) -> 200 | U14: =IF($F14="","",IF($E14="",T14,SUMIF(Sales!$E$7:$E$1506,$E14,Sales!$T$7:$T$1506))) -> 300 | V14: =IF(OR($C14<>"Online",$E14=""),"",IF(COUNTIF($E$7:$E14,$E14)>1,"",COUNT($V$6:V13)+1)) | W14: {=IF($V14="","",SUMPRODUCT((Sales!$V$7:$V$1506<>"")*(Sales!$E$7:$E$1506<$E14))+1)} | X14: =IF($A14="","",COUNTIFS($A$7:$A14,">="&EOMONTH($A14,-1)+1,$A$7:$A14,"<="&EOMONTH($A14,0))) -> 8 | Y14: =IF($A14="","",TEXT($A14,"yyyymm")&"-"&$X14) -> 202607-8 | AA14: =IF(Inventory!A12="","",Inventory!A12) -> AC-CJ-BR-001
A15: 46214 | B15: Sale | C15: Shop | D15: PawfectBD Shop | E15: PAWF-260719-0FD1A | F15: FD-DRY-TRL-1KG-001 | G15: =IF($F15="","",IFERROR(VLOOKUP($F15,Inventory!$A:$B,2,FALSE),"")) -> TRENDLINE Adult Chicken Cat Food 1-Kg | H15: 1 | I15: =IF($F15="","",IF($B15="Gift",0,J15-IF(K15="",0,K15))) -> 450 | J15: =IF($F15="","",IFERROR(VLOOKUP($F15,Inventory!$A:$K,11,FALSE),0)) -> 450 | L15: =IF($F15="","",IF($B15="Return",-H15*I15,H15*I15)) -> 450 | M15: Paid | N15: =IF($F15="","",IFERROR(VLOOKUP($F15,Inventory!$A:$I,9,FALSE),0)) -> 368 | O15: =IF($F15="","",IF($B15="Return",-H15*N15,H15*N15)) -> 368 | P15: =IF($F15="","",L15-O15) -> 82 | R15: =IF($E15="","",IF(COUNTIF($E$7:$E15,$E15)>1,"",IFERROR(VLOOKUP($E15,Orders!$A:$I,8,FALSE),""))) | S15: =IF($E15="","",IF(COUNTIF($E$7:$E15,$E15)>1,"",IFERROR(VLOOKUP($E15,Orders!$A:$I,9,FALSE),""))) | T15: =IF($F15="","",P15+IF(R15="",0,R15)-IF(S15="",0,S15)) -> 82 | U15: =IF($F15="","",IF($E15="",T15,SUMIF(Sales!$E$7:$E$1506,$E15,Sales!$T$7:$T$1506))) -> 82 | V15: =IF(OR($C15<>"Online",$E15=""),"",IF(COUNTIF($E$7:$E15,$E15)>1,"",COUNT($V$6:V14)+1)) | W15: {=IF($V15="","",SUMPRODUCT((Sales!$V$7:$V$1506<>"")*(Sales!$E$7:$E$1506<$E15))+1)} | X15: =IF($A15="","",COUNTIFS($A$7:$A15,">="&EOMONTH($A15,-1)+1,$A$7:$A15,"<="&EOMONTH($A15,0))) -> 9 | Y15: =IF($A15="","",TEXT($A15,"yyyymm")&"-"&$X15) -> 202607-9 | AA15: =IF(Inventory!A13="","",Inventory!A13) -> AC-SHAMP-002
A16: 46215 | B16: Sale | C16: Shop | D16: PawfectBD Shop | E16: PAWF-260719-25FF0 | F16: LT-LM-DD-5L-001 | G16: =IF($F16="","",IFERROR(VLOOKUP($F16,Inventory!$A:$B,2,FALSE),"")) -> Dodo Cat Litter 5L Lemon Flvor | H16: 1 | I16: =IF($F16="","",IF($B16="Gift",0,J16-IF(K16="",0,K16))) -> 280 | J16: =IF($F16="","",IFERROR(VLOOKUP($F16,Inventory!$A:$K,11,FALSE),0)) -> 320 | K16: 40 | L16: =IF($F16="","",IF($B16="Return",-H16*I16,H16*I16)) -> 280 | M16: Paid | N16: =IF($F16="","",IFERROR(VLOOKUP($F16,Inventory!$A:$I,9,FALSE),0)) -> 180 | O16: =IF($F16="","",IF($B16="Return",-H16*N16,H16*N16)) -> 180 | P16: =IF($F16="","",L16-O16) -> 100 | R16: =IF($E16="","",IF(COUNTIF($E$7:$E16,$E16)>1,"",IFERROR(VLOOKUP($E16,Orders!$A:$I,8,FALSE),""))) | S16: =IF($E16="","",IF(COUNTIF($E$7:$E16,$E16)>1,"",IFERROR(VLOOKUP($E16,Orders!$A:$I,9,FALSE),""))) | T16: =IF($F16="","",P16+IF(R16="",0,R16)-IF(S16="",0,S16)) -> 100 | U16: =IF($F16="","",IF($E16="",T16,SUMIF(Sales!$E$7:$E$1506,$E16,Sales!$T$7:$T$1506))) -> 100 | V16: =IF(OR($C16<>"Online",$E16=""),"",IF(COUNTIF($E$7:$E16,$E16)>1,"",COUNT($V$6:V15)+1)) | W16: {=IF($V16="","",SUMPRODUCT((Sales!$V$7:$V$1506<>"")*(Sales!$E$7:$E$1506<$E16))+1)} | X16: =IF($A16="","",COUNTIFS($A$7:$A16,">="&EOMONTH($A16,-1)+1,$A$7:$A16,"<="&EOMONTH($A16,0))) -> 10 | Y16: =IF($A16="","",TEXT($A16,"yyyymm")&"-"&$X16) -> 202607-10 | AA16: =IF(Inventory!A14="","",Inventory!A14) -> AC-SHAMP-003
A17: 46216 | B17: Sale | C17: Shop | D17: PawfectBD Shop | E17: PAWF-260719-74AA3 | F17: FD-DRY-ZOI-1KG-001 | G17: =IF($F17="","",IFERROR(VLOOKUP($F17,Inventory!$A:$B,2,FALSE),"")) -> Zoi Cat Food 1kg | H17: 1 | I17: =IF($F17="","",IF($B17="Gift",0,J17-IF(K17="",0,K17))) -> 315 | J17: =IF($F17="","",IFERROR(VLOOKUP($F17,Inventory!$A:$K,11,FALSE),0)) -> 380 | K17: 65 | L17: =IF($F17="","",IF($B17="Return",-H17*I17,H17*I17)) -> 315 | M17: Paid | N17: =IF($F17="","",IFERROR(VLOOKUP($F17,Inventory!$A:$I,9,FALSE),0)) -> 300 | O17: =IF($F17="","",IF($B17="Return",-H17*N17,H17*N17)) -> 300 | P17: =IF($F17="","",L17-O17) -> 15 | R17: =IF($E17="","",IF(COUNTIF($E$7:$E17,$E17)>1,"",IFERROR(VLOOKUP($E17,Orders!$A:$I,8,FALSE),""))) | S17: =IF($E17="","",IF(COUNTIF($E$7:$E17,$E17)>1,"",IFERROR(VLOOKUP($E17,Orders!$A:$I,9,FALSE),""))) | T17: =IF($F17="","",P17+IF(R17="",0,R17)-IF(S17="",0,S17)) -> 15 | U17: =IF($F17="","",IF($E17="",T17,SUMIF(Sales!$E$7:$E$1506,$E17,Sales!$T$7:$T$1506))) -> 8 | V17: =IF(OR($C17<>"Online",$E17=""),"",IF(COUNTIF($E$7:$E17,$E17)>1,"",COUNT($V$6:V16)+1)) | W17: {=IF($V17="","",SUMPRODUCT((Sales!$V$7:$V$1506<>"")*(Sales!$E$7:$E$1506<$E17))+1)} | X17: =IF($A17="","",COUNTIFS($A$7:$A17,">="&EOMONTH($A17,-1)+1,$A$7:$A17,"<="&EOMONTH($A17,0))) -> 11 | Y17: =IF($A17="","",TEXT($A17,"yyyymm")&"-"&$X17) -> 202607-11 | AA17: =IF(Inventory!A15="","",Inventory!A15) -> AC-LB-001
A18: 46217 | B18: Sale | C18: Shop | D18: PawfectBD Shop | E18: PAWF-260719-74AA3 | F18: FD-DRY-KVF-MV-500G-001 | G18: =IF($F18="","",IFERROR(VLOOKUP($F18,Inventory!$A:$B,2,FALSE),"")) -> Kaniva Fusion Multiviamins Chicken & Pumpkin 500gm | H18: 1 | I18: =IF($F18="","",IF($B18="Gift",0,J18-IF(K18="",0,K18))) -> 500 | J18: =IF($F18="","",IFERROR(VLOOKUP($F18,Inventory!$A:$K,11,FALSE),0)) -> 650 | K18: 150 | L18: =IF($F18="","",IF($B18="Return",-H18*I18,H18*I18)) -> 500 | M18: Paid | N18: =IF($F18="","",IFERROR(VLOOKUP($F18,Inventory!$A:$I,9,FALSE),0)) -> 507 | O18: =IF($F18="","",IF($B18="Return",-H18*N18,H18*N18)) -> 507 | P18: =IF($F18="","",L18-O18) -> -7 | R18: =IF($E18="","",IF(COUNTIF($E$7:$E18,$E18)>1,"",IFERROR(VLOOKUP($E18,Orders!$A:$I,8,FALSE),""))) | S18: =IF($E18="","",IF(COUNTIF($E$7:$E18,$E18)>1,"",IFERROR(VLOOKUP($E18,Orders!$A:$I,9,FALSE),""))) | T18: =IF($F18="","",P18+IF(R18="",0,R18)-IF(S18="",0,S18)) -> -7 | U18: =IF($F18="","",IF($E18="",T18,SUMIF(Sales!$E$7:$E$1506,$E18,Sales!$T$7:$T$1506))) -> 8 | V18: =IF(OR($C18<>"Online",$E18=""),"",IF(COUNTIF($E$7:$E18,$E18)>1,"",COUNT($V$6:V17)+1)) | W18: {=IF($V18="","",SUMPRODUCT((Sales!$V$7:$V$1506<>"")*(Sales!$E$7:$E$1506<$E18))+1)} | X18: =IF($A18="","",COUNTIFS($A$7:$A18,">="&EOMONTH($A18,-1)+1,$A$7:$A18,"<="&EOMONTH($A18,0))) -> 12 | Y18: =IF($A18="","",TEXT($A18,"yyyymm")&"-"&$X18) -> 202607-12 | AA18: =IF(Inventory!A16="","",Inventory!A16) -> AC-LB-002
A19: 46218 | B19: Sale | C19: Shop | D19: PawfectBD Shop | E19: PAWF-260719-C4018 | F19: FD-DRY-SMHRT-480G-002 | G19: =IF($F19="","",IFERROR(VLOOKUP($F19,Inventory!$A:$B,2,FALSE),"")) -> Smart Heart Adult Cat Food Chicken & Tuna [480G] | H19: 1 | I19: =IF($F19="","",IF($B19="Gift",0,J19-IF(K19="",0,K19))) -> 370 | J19: =IF($F19="","",IFERROR(VLOOKUP($F19,Inventory!$A:$K,11,FALSE),0)) -> 380 | K19: 10 | L19: =IF($F19="","",IF($B19="Return",-H19*I19,H19*I19)) -> 370 | M19: Paid | N19: =IF($F19="","",IFERROR(VLOOKUP($F19,Inventory!$A:$I,9,FALSE),0)) -> 290.26316 | O19: =IF($F19="","",IF($B19="Return",-H19*N19,H19*N19)) -> 290.26316 | P19: =IF($F19="","",L19-O19) -> 79.736842 | R19: =IF($E19="","",IF(COUNTIF($E$7:$E19,$E19)>1,"",IFERROR(VLOOKUP($E19,Orders!$A:$I,8,FALSE),""))) | S19: =IF($E19="","",IF(COUNTIF($E$7:$E19,$E19)>1,"",IFERROR(VLOOKUP($E19,Orders!$A:$I,9,FALSE),""))) | T19: =IF($F19="","",P19+IF(R19="",0,R19)-IF(S19="",0,S19)) -> 79.736842 | U19: =IF($F19="","",IF($E19="",T19,SUMIF(Sales!$E$7:$E$1506,$E19,Sales!$T$7:$T$1506))) -> 79.736842 | V19: =IF(OR($C19<>"Online",$E19=""),"",IF(COUNTIF($E$7:$E19,$E19)>1,"",COUNT($V$6:V18)+1)) | W19: {=IF($V19="","",SUMPRODUCT((Sales!$V$7:$V$1506<>"")*(Sales!$E$7:$E$1506<$E19))+1)} | X19: =IF($A19="","",COUNTIFS($A$7:$A19,">="&EOMONTH($A19,-1)+1,$A$7:$A19,"<="&EOMONTH($A19,0))) -> 13 | Y19: =IF($A19="","",TEXT($A19,"yyyymm")&"-"&$X19) -> 202607-13 | AA19: =IF(Inventory!A17="","",Inventory!A17) -> LT-LM-DD-5L-001
A20: 46219 | B20: Sale | C20: Shop | D20: PawfectBD Shop | E20: PAWF-260719-187F5 | F20: AC-CB-001 | G20: =IF($F20="","",IFERROR(VLOOKUP($F20,Inventory!$A:$B,2,FALSE),"")) -> Cat Belt | H20: 2 | I20: =IF($F20="","",IF($B20="Gift",0,J20-IF(K20="",0,K20))) -> 55 | J20: =IF($F20="","",IFERROR(VLOOKUP($F20,Inventory!$A:$K,11,FALSE),0)) -> 60 | K20: 5 | L20: =IF($F20="","",IF($B20="Return",-H20*I20,H20*I20)) -> 110 | M20: Paid | N20: =IF($F20="","",IFERROR(VLOOKUP($F20,Inventory!$A:$I,9,FALSE),0)) -> 29.351351 | O20: =IF($F20="","",IF($B20="Return",-H20*N20,H20*N20)) -> 58.702703 | P20: =IF($F20="","",L20-O20) -> 51.297297 | R20: =IF($E20="","",IF(COUNTIF($E$7:$E20,$E20)>1,"",IFERROR(VLOOKUP($E20,Orders!$A:$I,8,FALSE),""))) | S20: =IF($E20="","",IF(COUNTIF($E$7:$E20,$E20)>1,"",IFERROR(VLOOKUP($E20,Orders!$A:$I,9,FALSE),""))) | T20: =IF($F20="","",P20+IF(R20="",0,R20)-IF(S20="",0,S20)) -> 51.297297 | U20: =IF($F20="","",IF($E20="",T20,SUMIF(Sales!$E$7:$E$1506,$E20,Sales!$T$7:$T$1506))) -> 51.297297 | V20: =IF(OR($C20<>"Online",$E20=""),"",IF(COUNTIF($E$7:$E20,$E20)>1,"",COUNT($V$6:V19)+1)) | W20: {=IF($V20="","",SUMPRODUCT((Sales!$V$7:$V$1506<>"")*(Sales!$E$7:$E$1506<$E20))+1)} | X20: =IF($A20="","",COUNTIFS($A$7:$A20,">="&EOMONTH($A20,-1)+1,$A$7:$A20,"<="&EOMONTH($A20,0))) -> 14 | Y20: =IF($A20="","",TEXT($A20,"yyyymm")&"-"&$X20) -> 202607-14 | AA20: =IF(Inventory!A18="","",Inventory!A18) -> FD-DRY-CHNK-CHKN-1.5KG-001
A21: 46219 | B21: Gift | C21: Shop | D21: Nadim | E21: PAWF-260718-8CA86 | F21: LT-LM-DD-5L-001 | G21: =IF($F21="","",IFERROR(VLOOKUP($F21,Inventory!$A:$B,2,FALSE),"")) -> Dodo Cat Litter 5L Lemon Flvor | H21: 1 | I21: =IF($F21="","",IF($B21="Gift",0,J21-IF(K21="",0,K21))) -> 0 | J21: =IF($F21="","",IFERROR(VLOOKUP($F21,Inventory!$A:$K,11,FALSE),0)) -> 320 | K21: 320 | L21: =IF($F21="","",IF($B21="Return",-H21*I21,H21*I21)) -> 0 | M21: Paid | N21: =IF($F21="","",IFERROR(VLOOKUP($F21,Inventory!$A:$I,9,FALSE),0)) -> 180 | O21: =IF($F21="","",IF($B21="Return",-H21*N21,H21*N21)) -> 180 | P21: =IF($F21="","",L21-O21) -> -180 | Q21: Gift For Check Product Quality | R21: =IF($E21="","",IF(COUNTIF($E$7:$E21,$E21)>1,"",IFERROR(VLOOKUP($E21,Orders!$A:$I,8,FALSE),""))) | S21: =IF($E21="","",IF(COUNTIF($E$7:$E21,$E21)>1,"",IFERROR(VLOOKUP($E21,Orders!$A:$I,9,FALSE),""))) | T21: =IF($F21="","",P21+IF(R21="",0,R21)-IF(S21="",0,S21)) -> -180 | U21: =IF($F21="","",IF($E21="",T21,SUMIF(Sales!$E$7:$E$1506,$E21,Sales!$T$7:$T$1506))) -> 220 | V21: =IF(OR($C21<>"Online",$E21=""),"",IF(COUNTIF($E$7:$E21,$E21)>1,"",COUNT($V$6:V20)+1)) | W21: {=IF($V21="","",SUMPRODUCT((Sales!$V$7:$V$1506<>"")*(Sales!$E$7:$E$1506<$E21))+1)} | X21: =IF($A21="","",COUNTIFS($A$7:$A21,">="&EOMONTH($A21,-1)+1,$A$7:$A21,"<="&EOMONTH($A21,0))) -> 15 | Y21: =IF($A21="","",TEXT($A21,"yyyymm")&"-"&$X21) -> 202607-15 | AA21: =IF(Inventory!A19="","",Inventory!A19) -> FD-DRY-CHNK-OCFCK-1.5KG-001
A22: 46220 | B22: Sale | C22: Shop | D22: PawfectBD Shop | E22: PAWF-260718-9DC96 | F22: FD-DRY-KTCN-400G-001 | G22: =IF($F22="","",IFERROR(VLOOKUP($F22,Inventory!$A:$B,2,FALSE),"")) -> Kitchen Flavor Grain Free Kitten 400G | H22: 1 | I22: =IF($F22="","",IF($B22="Gift",0,J22-IF(K22="",0,K22))) -> 350 | J22: =IF($F22="","",IFERROR(VLOOKUP($F22,Inventory!$A:$K,11,FALSE),0)) -> 380 | K22: 30 | L22: =IF($F22="","",IF($B22="Return",-H22*I22,H22*I22)) -> 350 | M22: Paid | N22: =IF($F22="","",IFERROR(VLOOKUP($F22,Inventory!$A:$I,9,FALSE),0)) -> 290 | O22: =IF($F22="","",IF($B22="Return",-H22*N22,H22*N22)) -> 290 | P22: =IF($F22="","",L22-O22) -> 60 | R22: =IF($E22="","",IF(COUNTIF($E$7:$E22,$E22)>1,"",IFERROR(VLOOKUP($E22,Orders!$A:$I,8,FALSE),""))) | S22: =IF($E22="","",IF(COUNTIF($E$7:$E22,$E22)>1,"",IFERROR(VLOOKUP($E22,Orders!$A:$I,9,FALSE),""))) | T22: =IF($F22="","",P22+IF(R22="",0,R22)-IF(S22="",0,S22)) -> 60 | U22: =IF($F22="","",IF($E22="",T22,SUMIF(Sales!$E$7:$E$1506,$E22,Sales!$T$7:$T$1506))) -> 347.78882 | V22: =IF(OR($C22<>"Online",$E22=""),"",IF(COUNTIF($E$7:$E22,$E22)>1,"",COUNT($V$6:V21)+1)) | W22: {=IF($V22="","",SUMPRODUCT((Sales!$V$7:$V$1506<>"")*(Sales!$E$7:$E$1506<$E22))+1)} | X22: =IF($A22="","",COUNTIFS($A$7:$A22,">="&EOMONTH($A22,-1)+1,$A$7:$A22,"<="&EOMONTH($A22,0))) -> 16 | Y22: =IF($A22="","",TEXT($A22,"yyyymm")&"-"&$X22) -> 202607-16 | AA22: =IF(Inventory!A20="","",Inventory!A20) -> FD-DRY-CHNK-TN-1.5KG-001
A23: 46220 | B23: Sale | C23: Shop | D23: PawfectBD Shop | E23: PAWF-260718-9DC96 | F23: TR-CRMY-15G-001 | G23: =IF($F23="","",IFERROR(VLOOKUP($F23,Inventory!$A:$B,2,FALSE),"")) -> Creamy Treat 15G (Purry & Hyper Paws) | H23: 7 | I23: =IF($F23="","",IF($B23="Gift",0,J23-IF(K23="",0,K23))) -> 20 | J23: =IF($F23="","",IFERROR(VLOOKUP($F23,Inventory!$A:$K,11,FALSE),0)) -> 20 | L23: =IF($F23="","",IF($B23="Return",-H23*I23,H23*I23)) -> 140 | M23: Paid | N23: =IF($F23="","",IFERROR(VLOOKUP($F23,Inventory!$A:$I,9,FALSE),0)) -> 8.1474119 | O23: =IF($F23="","",IF($B23="Return",-H23*N23,H23*N23)) -> 57.031883 | P23: =IF($F23="","",L23-O23) -> 82.968117 | R23: =IF($E23="","",IF(COUNTIF($E$7:$E23,$E23)>1,"",IFERROR(VLOOKUP($E23,Orders!$A:$I,8,FALSE),""))) | S23: =IF($E23="","",IF(COUNTIF($E$7:$E23,$E23)>1,"",IFERROR(VLOOKUP($E23,Orders!$A:$I,9,FALSE),""))) | T23: =IF($F23="","",P23+IF(R23="",0,R23)-IF(S23="",0,S23)) -> 82.968117 | U23: =IF($F23="","",IF($E23="",T23,SUMIF(Sales!$E$7:$E$1506,$E23,Sales!$T$7:$T$1506))) -> 347.78882 | V23: =IF(OR($C23<>"Online",$E23=""),"",IF(COUNTIF($E$7:$E23,$E23)>1,"",COUNT($V$6:V22)+1)) | W23: {=IF($V23="","",SUMPRODUCT((Sales!$V$7:$V$1506<>"")*(Sales!$E$7:$E$1506<$E23))+1)} | X23: =IF($A23="","",COUNTIFS($A$7:$A23,">="&EOMONTH($A23,-1)+1,$A$7:$A23,"<="&EOMONTH($A23,0))) -> 17 | Y23: =IF($A23="","",TEXT($A23,"yyyymm")&"-"&$X23) -> 202607-17 | AA23: =IF(Inventory!A21="","",Inventory!A21) -> TR-CRMY-15G-001
A24: 46220 | B24: Sale | C24: Shop | D24: PawfectBD Shop | E24: PAWF-260718-9DC96 | F24: TR-CRMY-15G-001 | G24: =IF($F24="","",IFERROR(VLOOKUP($F24,Inventory!$A:$B,2,FALSE),"")) -> Creamy Treat 15G (Purry & Hyper Paws) | H24: 8 | I24: =IF($F24="","",IF($B24="Gift",0,J24-IF(K24="",0,K24))) -> 20 | J24: =IF($F24="","",IFERROR(VLOOKUP($F24,Inventory!$A:$K,11,FALSE),0)) -> 20 | L24: =IF($F24="","",IF($B24="Return",-H24*I24,H24*I24)) -> 160 | M24: Paid | N24: =IF($F24="","",IFERROR(VLOOKUP($F24,Inventory!$A:$I,9,FALSE),0)) -> 8.1474119 | O24: =IF($F24="","",IF($B24="Return",-H24*N24,H24*N24)) -> 65.179295 | P24: =IF($F24="","",L24-O24) -> 94.820705 | R24: =IF($E24="","",IF(COUNTIF($E$7:$E24,$E24)>1,"",IFERROR(VLOOKUP($E24,Orders!$A:$I,8,FALSE),""))) | S24: =IF($E24="","",IF(COUNTIF($E$7:$E24,$E24)>1,"",IFERROR(VLOOKUP($E24,Orders!$A:$I,9,FALSE),""))) | T24: =IF($F24="","",P24+IF(R24="",0,R24)-IF(S24="",0,S24)) -> 94.820705 | U24: =IF($F24="","",IF($E24="",T24,SUMIF(Sales!$E$7:$E$1506,$E24,Sales!$T$7:$T$1506))) -> 347.78882 | V24: =IF(OR($C24<>"Online",$E24=""),"",IF(COUNTIF($E$7:$E24,$E24)>1,"",COUNT($V$6:V23)+1)) | W24: {=IF($V24="","",SUMPRODUCT((Sales!$V$7:$V$1506<>"")*(Sales!$E$7:$E$1506<$E24))+1)} | X24: =IF($A24="","",COUNTIFS($A$7:$A24,">="&EOMONTH($A24,-1)+1,$A$7:$A24,"<="&EOMONTH($A24,0))) -> 18 | Y24: =IF($A24="","",TEXT($A24,"yyyymm")&"-"&$X24) -> 202607-18 | AA24: =IF(Inventory!A22="","",Inventory!A22) -> FD-DRY-SMHRT-450G-001
A25: 46220 | B25: Sale | C25: Shop | D25: PawfectBD Shop | E25: PAWF-260718-9DC96 | F25: LT-LM-CZE-5L-001 | G25: =IF($F25="","",IFERROR(VLOOKUP($F25,Inventory!$A:$B,2,FALSE),"")) -> Cozie Cat Litter Lemon 5L | H25: 1 | I25: =IF($F25="","",IF($B25="Gift",0,J25-IF(K25="",0,K25))) -> 340 | J25: =IF($F25="","",IFERROR(VLOOKUP($F25,Inventory!$A:$K,11,FALSE),0)) -> 370 | K25: 30 | L25: =IF($F25="","",IF($B25="Return",-H25*I25,H25*I25)) -> 340 | M25: Paid | N25: =IF($F25="","",IFERROR(VLOOKUP($F25,Inventory!$A:$I,9,FALSE),0)) -> 230 | O25: =IF($F25="","",IF($B25="Return",-H25*N25,H25*N25)) -> 230 | P25: =IF($F25="","",L25-O25) -> 110 | R25: =IF($E25="","",IF(COUNTIF($E$7:$E25,$E25)>1,"",IFERROR(VLOOKUP($E25,Orders!$A:$I,8,FALSE),""))) | S25: =IF($E25="","",IF(COUNTIF($E$7:$E25,$E25)>1,"",IFERROR(VLOOKUP($E25,Orders!$A:$I,9,FALSE),""))) | T25: =IF($F25="","",P25+IF(R25="",0,R25)-IF(S25="",0,S25)) -> 110 | U25: =IF($F25="","",IF($E25="",T25,SUMIF(Sales!$E$7:$E$1506,$E25,Sales!$T$7:$T$1506))) -> 347.78882 | V25: =IF(OR($C25<>"Online",$E25=""),"",IF(COUNTIF($E$7:$E25,$E25)>1,"",COUNT($V$6:V24)+1)) | W25: {=IF($V25="","",SUMPRODUCT((Sales!$V$7:$V$1506<>"")*(Sales!$E$7:$E$1506<$E25))+1)} | X25: =IF($A25="","",COUNTIFS($A$7:$A25,">="&EOMONTH($A25,-1)+1,$A$7:$A25,"<="&EOMONTH($A25,0))) -> 19 | Y25: =IF($A25="","",TEXT($A25,"yyyymm")&"-"&$X25) -> 202607-19 | AA25: =IF(Inventory!A23="","",Inventory!A23) -> FD-DRY-SMHRT-15KG-001
A26: 46221 | B26: Sale | C26: Shop | D26: PawfectBD Shop | E26: PAWF-260719-0AD9E | F26: AC-HM-MD-001 | G26: =IF($F26="","",IFERROR(VLOOKUP($F26,Inventory!$A:$B,2,FALSE),"")) -> Helminticide-L Deworming Tablet | H26: 1 | I26: =IF($F26="","",IF($B26="Gift",0,J26-IF(K26="",0,K26))) -> 50 | J26: =IF($F26="","",IFERROR(VLOOKUP($F26,Inventory!$A:$K,11,FALSE),0)) -> 50 | L26: =IF($F26="","",IF($B26="Return",-H26*I26,H26*I26)) -> 50 | M26: Paid | N26: =IF($F26="","",IFERROR(VLOOKUP($F26,Inventory!$A:$I,9,FALSE),0)) -> 28.636364 | O26: =IF($F26="","",IF($B26="Return",-H26*N26,H26*N26)) -> 28.636364 | P26: =IF($F26="","",L26-O26) -> 21.363636 | R26: =IF($E26="","",IF(COUNTIF($E$7:$E26,$E26)>1,"",IFERROR(VLOOKUP($E26,Orders!$A:$I,8,FALSE),""))) | S26: =IF($E26="","",IF(COUNTIF($E$7:$E26,$E26)>1,"",IFERROR(VLOOKUP($E26,Orders!$A:$I,9,FALSE),""))) | T26: =IF($F26="","",P26+IF(R26="",0,R26)-IF(S26="",0,S26)) -> 21.363636 | U26: =IF($F26="","",IF($E26="",T26,SUMIF(Sales!$E$7:$E$1506,$E26,Sales!$T$7:$T$1506))) -> 80.626577 | V26: =IF(OR($C26<>"Online",$E26=""),"",IF(COUNTIF($E$7:$E26,$E26)>1,"",COUNT($V$6:V25)+1)) | W26: {=IF($V26="","",SUMPRODUCT((Sales!$V$7:$V$1506<>"")*(Sales!$E$7:$E$1506<$E26))+1)} | X26: =IF($A26="","",COUNTIFS($A$7:$A26,">="&EOMONTH($A26,-1)+1,$A$7:$A26,"<="&EOMONTH($A26,0))) -> 20 | Y26: =IF($A26="","",TEXT($A26,"yyyymm")&"-"&$X26) -> 202607-20 | AA26: =IF(Inventory!A24="","",Inventory!A24) -> FD-BRD-MLT-YLW-25KG
A27: 46221 | B27: Sale | C27: Shop | D27: PawfectBD Shop | E27: PAWF-260719-0AD9E | F27: TR-CRMY-15G-001 | G27: =IF($F27="","",IFERROR(VLOOKUP($F27,Inventory!$A:$B,2,FALSE),"")) -> Creamy Treat 15G (Purry & Hyper Paws) | H27: 5 | I27: =IF($F27="","",IF($B27="Gift",0,J27-IF(K27="",0,K27))) -> 20 | J27: =IF($F27="","",IFERROR(VLOOKUP($F27,Inventory!$A:$K,11,FALSE),0)) -> 20 | L27: =IF($F27="","",IF($B27="Return",-H27*I27,H27*I27)) -> 100 | M27: Paid | N27: =IF($F27="","",IFERROR(VLOOKUP($F27,Inventory!$A:$I,9,FALSE),0)) -> 8.1474119 | O27: =IF($F27="","",IF($B27="Return",-H27*N27,H27*N27)) -> 40.737059 | P27: =IF($F27="","",L27-O27) -> 59.262941 | R27: =IF($E27="","",IF(COUNTIF($E$7:$E27,$E27)>1,"",IFERROR(VLOOKUP($E27,Orders!$A:$I,8,FALSE),""))) | S27: =IF($E27="","",IF(COUNTIF($E$7:$E27,$E27)>1,"",IFERROR(VLOOKUP($E27,Orders!$A:$I,9,FALSE),""))) | T27: =IF($F27="","",P27+IF(R27="",0,R27)-IF(S27="",0,S27)) -> 59.262941 | U27: =IF($F27="","",IF($E27="",T27,SUMIF(Sales!$E$7:$E$1506,$E27,Sales!$T$7:$T$1506))) -> 80.626577 | V27: =IF(OR($C27<>"Online",$E27=""),"",IF(COUNTIF($E$7:$E27,$E27)>1,"",COUNT($V$6:V26)+1)) | W27: {=IF($V27="","",SUMPRODUCT((Sales!$V$7:$V$1506<>"")*(Sales!$E$7:$E$1506<$E27))+1)} | X27: =IF($A27="","",COUNTIFS($A$7:$A27,">="&EOMONTH($A27,-1)+1,$A$7:$A27,"<="&EOMONTH($A27,0))) -> 21 | Y27: =IF($A27="","",TEXT($A27,"yyyymm")&"-"&$X27) -> 202607-21 | AA27: =IF(Inventory!A25="","",Inventory!A25) -> FD-DRY-KVF-MV-500G-001
A28: 46221 | B28: Sale | C28: Shop | D28: PawfectBD Shop | E28: PAWF-260718-0F82F | F28: LT-AP-DD-25L-002 | G28: =IF($F28="","",IFERROR(VLOOKUP($F28,Inventory!$A:$B,2,FALSE),"")) -> Dodo Cat Litter 25L Apple Flvor | H28: 1 | I28: =IF($F28="","",IF($B28="Gift",0,J28-IF(K28="",0,K28))) -> 1230 | J28: =IF($F28="","",IFERROR(VLOOKUP($F28,Inventory!$A:$K,11,FALSE),0)) -> 1450 | K28: 220 | L28: =IF($F28="","",IF($B28="Return",-H28*I28,H28*I28)) -> 1230 | M28: Paid | N28: =IF($F28="","",IFERROR(VLOOKUP($F28,Inventory!$A:$I,9,FALSE),0)) -> 850 | O28: =IF($F28="","",IF($B28="Return",-H28*N28,H28*N28)) -> 850 | P28: =IF($F28="","",L28-O28) -> 380 | R28: =IF($E28="","",IF(COUNTIF($E$7:$E28,$E28)>1,"",IFERROR(VLOOKUP($E28,Orders!$A:$I,8,FALSE),""))) | S28: =IF($E28="","",IF(COUNTIF($E$7:$E28,$E28)>1,"",IFERROR(VLOOKUP($E28,Orders!$A:$I,9,FALSE),""))) | T28: =IF($F28="","",P28+IF(R28="",0,R28)-IF(S28="",0,S28)) -> 380 | U28: =IF($F28="","",IF($E28="",T28,SUMIF(Sales!$E$7:$E$1506,$E28,Sales!$T$7:$T$1506))) -> 310 | V28: =IF(OR($C28<>"Online",$E28=""),"",IF(COUNTIF($E$7:$E28,$E28)>1,"",COUNT($V$6:V27)+1)) | W28: {=IF($V28="","",SUMPRODUCT((Sales!$V$7:$V$1506<>"")*(Sales!$E$7:$E$1506<$E28))+1)} | X28: =IF($A28="","",COUNTIFS($A$7:$A28,">="&EOMONTH($A28,-1)+1,$A$7:$A28,"<="&EOMONTH($A28,0))) -> 22 | Y28: =IF($A28="","",TEXT($A28,"yyyymm")&"-"&$X28) -> 202607-22 | AA28: =IF(Inventory!A26="","",Inventory!A26) -> FD-DRY-KVF-SKCO-500G-001
A29: 46221 | B29: Sale | C29: Shop | D29: PawfectBD Shop | E29: PAWF-260718-0F82F | F29: FD-WET-KTCN-001 | G29: =IF($F29="","",IFERROR(VLOOKUP($F29,Inventory!$A:$B,2,FALSE),"")) -> Kitchen Flavor Pate Delight | H29: 2 | I29: =IF($F29="","",IF($B29="Gift",0,J29-IF(K29="",0,K29))) -> 145 | J29: =IF($F29="","",IFERROR(VLOOKUP($F29,Inventory!$A:$K,11,FALSE),0)) -> 150 | K29: 5 | L29: =IF($F29="","",IF($B29="Return",-H29*I29,H29*I29)) -> 290 | M29: Paid | N29: =IF($F29="","",IFERROR(VLOOKUP($F29,Inventory!$A:$I,9,FALSE),0)) -> 110 | O29: =IF($F29="","",IF($B29="Return",-H29*N29,H29*N29)) -> 220 | P29: =IF($F29="","",L29-O29) -> 70 | R29: =IF($E29="","",IF(COUNTIF($E$7:$E29,$E29)>1,"",IFERROR(VLOOKUP($E29,Orders!$A:$I,8,FALSE),""))) | S29: =IF($E29="","",IF(COUNTIF($E$7:$E29,$E29)>1,"",IFERROR(VLOOKUP($E29,Orders!$A:$I,9,FALSE),""))) | T29: =IF($F29="","",P29+IF(R29="",0,R29)-IF(S29="",0,S29)) -> 70 | U29: =IF($F29="","",IF($E29="",T29,SUMIF(Sales!$E$7:$E$1506,$E29,Sales!$T$7:$T$1506))) -> 310 | V29: =IF(OR($C29<>"Online",$E29=""),"",IF(COUNTIF($E$7:$E29,$E29)>1,"",COUNT($V$6:V28)+1)) | W29: {=IF($V29="","",SUMPRODUCT((Sales!$V$7:$V$1506<>"")*(Sales!$E$7:$E$1506<$E29))+1)} | X29: =IF($A29="","",COUNTIFS($A$7:$A29,">="&EOMONTH($A29,-1)+1,$A$7:$A29,"<="&EOMONTH($A29,0))) -> 23 | Y29: =IF($A29="","",TEXT($A29,"yyyymm")&"-"&$X29) -> 202607-23 | AA29: =IF(Inventory!A27="","",Inventory!A27) -> LT-LM-CZE-5L-001
A30: 46221 | B30: Gift | C30: Shop | D30: PawfectBD Shop | E30: PAWF-260718-0F82F | F30: AC-CJ-AR-002 | G30: =IF($F30="","",IFERROR(VLOOKUP($F30,Inventory!$A:$B,2,FALSE),"")) -> Cat Jersey Argentina Large | H30: 1 | I30: =IF($F30="","",IF($B30="Gift",0,J30-IF(K30="",0,K30))) -> 0 | J30: =IF($F30="","",IFERROR(VLOOKUP($F30,Inventory!$A:$K,11,FALSE),0)) -> 300 | K30: 300 | L30: =IF($F30="","",IF($B30="Return",-H30*I30,H30*I30)) -> 0 | M30: Paid | N30: =IF($F30="","",IFERROR(VLOOKUP($F30,Inventory!$A:$I,9,FALSE),0)) -> 140 | O30: =IF($F30="","",IF($B30="Return",-H30*N30,H30*N30)) -> 140 | P30: =IF($F30="","",L30-O30) -> -140 | Q30: Gift from PawfectBD | R30: =IF($E30="","",IF(COUNTIF($E$7:$E30,$E30)>1,"",IFERROR(VLOOKUP($E30,Orders!$A:$I,8,FALSE),""))) | S30: =IF($E30="","",IF(COUNTIF($E$7:$E30,$E30)>1,"",IFERROR(VLOOKUP($E30,Orders!$A:$I,9,FALSE),""))) | T30: =IF($F30="","",P30+IF(R30="",0,R30)-IF(S30="",0,S30)) -> -140 | U30: =IF($F30="","",IF($E30="",T30,SUMIF(Sales!$E$7:$E$1506,$E30,Sales!$T$7:$T$1506))) -> 310 | V30: =IF(OR($C30<>"Online",$E30=""),"",IF(COUNTIF($E$7:$E30,$E30)>1,"",COUNT($V$6:V29)+1)) | W30: {=IF($V30="","",SUMPRODUCT((Sales!$V$7:$V$1506<>"")*(Sales!$E$7:$E$1506<$E30))+1)} | X30: =IF($A30="","",COUNTIFS($A$7:$A30,">="&EOMONTH($A30,-1)+1,$A$7:$A30,"<="&EOMONTH($A30,0))) -> 24 | Y30: =IF($A30="","",TEXT($A30,"yyyymm")&"-"&$X30) -> 202607-24 | AA30: =IF(Inventory!A28="","",Inventory!A28) -> LT-LM-CZE-10L-001
A31: 46221 | B31: Sale | C31: Shop | D31: PawfectBD Shop | E31: PAWF-260729-77F7C | F31: LT-CF-DD-25L-001 | G31: =IF($F31="","",IFERROR(VLOOKUP($F31,Inventory!$A:$B,2,FALSE),"")) -> L Favorite Cat Litter 25L Coffee Flvor | H31: 1 | I31: =IF($F31="","",IF($B31="Gift",0,J31-IF(K31="",0,K31))) -> 1445 | J31: =IF($F31="","",IFERROR(VLOOKUP($F31,Inventory!$A:$K,11,FALSE),0)) -> 1550 | K31: 105 | L31: =IF($F31="","",IF($B31="Return",-H31*I31,H31*I31)) -> 1445 | M31: Paid | N31: =IF($F31="","",IFERROR(VLOOKUP($F31,Inventory!$A:$I,9,FALSE),0)) -> 1000 | O31: =IF($F31="","",IF($B31="Return",-H31*N31,H31*N31)) -> 1000 | P31: =IF($F31="","",L31-O31) -> 445 | Q31: Bkash | R31: =IF($E31="","",IF(COUNTIF($E$7:$E31,$E31)>1,"",IFERROR(VLOOKUP($E31,Orders!$A:$I,8,FALSE),""))) | S31: =IF($E31="","",IF(COUNTIF($E$7:$E31,$E31)>1,"",IFERROR(VLOOKUP($E31,Orders!$A:$I,9,FALSE),""))) | T31: =IF($F31="","",P31+IF(R31="",0,R31)-IF(S31="",0,S31)) -> 445 | U31: =IF($F31="","",IF($E31="",T31,SUMIF(Sales!$E$7:$E$1506,$E31,Sales!$T$7:$T$1506))) -> 445 | V31: =IF(OR($C31<>"Online",$E31=""),"",IF(COUNTIF($E$7:$E31,$E31)>1,"",COUNT($V$6:V30)+1)) | W31: {=IF($V31="","",SUMPRODUCT((Sales!$V$7:$V$1506<>"")*(Sales!$E$7:$E$1506<$E31))+1)} | X31: =IF($A31="","",COUNTIFS($A$7:$A31,">="&EOMONTH($A31,-1)+1,$A$7:$A31,"<="&EOMONTH($A31,0))) -> 25 | Y31: =IF($A31="","",TEXT($A31,"yyyymm")&"-"&$X31) -> 202607-25 | AA31: =IF(Inventory!A29="","",Inventory!A29) -> LT-LV-CZE-5L-001
A32: 46219 | B32: Sale | C32: Shop | D32: PawfectBD Shop | E32: PAWF-260719-B6373 | F32: AC-LB-002 | G32: =IF($F32="","",IFERROR(VLOOKUP($F32,Inventory!$A:$B,2,FALSE),"")) -> Cat Litter Box Medium | H32: 1 | I32: =IF($F32="","",IF($B32="Gift",0,J32-IF(K32="",0,K32))) -> 400 | J32: =IF($F32="","",IFERROR(VLOOKUP($F32,Inventory!$A:$K,11,FALSE),0)) -> 500 | K32: 100 | L32: =IF($F32="","",IF($B32="Return",-H32*I32,H32*I32)) -> 400 | M32: Paid | N32: =IF($F32="","",IFERROR(VLOOKUP($F32,Inventory!$A:$I,9,FALSE),0)) -> 300 | O32: =IF($F32="","",IF($B32="Return",-H32*N32,H32*N32)) -> 300 | P32: =IF($F32="","",L32-O32) -> 100 | R32: =IF($E32="","",IF(COUNTIF($E$7:$E32,$E32)>1,"",IFERROR(VLOOKUP($E32,Orders!$A:$I,8,FALSE),""))) | S32: =IF($E32="","",IF(COUNTIF($E$7:$E32,$E32)>1,"",IFERROR(VLOOKUP($E32,Orders!$A:$I,9,FALSE),""))) | T32: =IF($F32="","",P32+IF(R32="",0,R32)-IF(S32="",0,S32)) -> 100 | U32: =IF($F32="","",IF($E32="",T32,SUMIF(Sales!$E$7:$E$1506,$E32,Sales!$T$7:$T$1506))) -> 100 | V32: =IF(OR($C32<>"Online",$E32=""),"",IF(COUNTIF($E$7:$E32,$E32)>1,"",COUNT($V$6:V31)+1)) | W32: {=IF($V32="","",SUMPRODUCT((Sales!$V$7:$V$1506<>"")*(Sales!$E$7:$E$1506<$E32))+1)} | X32: =IF($A32="","",COUNTIFS($A$7:$A32,">="&EOMONTH($A32,-1)+1,$A$7:$A32,"<="&EOMONTH($A32,0))) -> 26 | Y32: =IF($A32="","",TEXT($A32,"yyyymm")&"-"&$X32) -> 202607-26 | AA32: =IF(Inventory!A30="","",Inventory!A30) -> LT-LV-CZE-10L-001
A33: 46222 | B33: Sale | C33: Shop | D33: PawfectBD Shop | E33: PAWF-260726-FD0E4 | F33: PO-WET-SMHRT-TJ-85G-001 | G33: =IF($F33="","",IFERROR(VLOOKUP($F33,Inventory!$A:$B,2,FALSE),"")) -> Smart Heart Pouch Tuna in Jelly Kitten | H33: 2 | I33: =IF($F33="","",IF($B33="Gift",0,J33-IF(K33="",0,K33))) -> 90 | J33: =IF($F33="","",IFERROR(VLOOKUP($F33,Inventory!$A:$K,11,FALSE),0)) -> 95 | K33: 5 | L33: =IF($F33="","",IF($B33="Return",-H33*I33,H33*I33)) -> 180 | M33: Paid | N33: =IF($F33="","",IFERROR(VLOOKUP($F33,Inventory!$A:$I,9,FALSE),0)) -> 72 | O33: =IF($F33="","",IF($B33="Return",-H33*N33,H33*N33)) -> 144 | P33: =IF($F33="","",L33-O33) -> 36 | R33: =IF($E33="","",IF(COUNTIF($E$7:$E33,$E33)>1,"",IFERROR(VLOOKUP($E33,Orders!$A:$I,8,FALSE),""))) | S33: =IF($E33="","",IF(COUNTIF($E$7:$E33,$E33)>1,"",IFERROR(VLOOKUP($E33,Orders!$A:$I,9,FALSE),""))) | T33: =IF($F33="","",P33+IF(R33="",0,R33)-IF(S33="",0,S33)) -> 36 | U33: =IF($F33="","",IF($E33="",T33,SUMIF(Sales!$E$7:$E$1506,$E33,Sales!$T$7:$T$1506))) -> 52 | V33: =IF(OR($C33<>"Online",$E33=""),"",IF(COUNTIF($E$7:$E33,$E33)>1,"",COUNT($V$6:V32)+1)) | W33: {=IF($V33="","",SUMPRODUCT((Sales!$V$7:$V$1506<>"")*(Sales!$E$7:$E$1506<$E33))+1)} | X33: =IF($A33="","",COUNTIFS($A$7:$A33,">="&EOMONTH($A33,-1)+1,$A$7:$A33,"<="&EOMONTH($A33,0))) -> 27 | Y33: =IF($A33="","",TEXT($A33,"yyyymm")&"-"&$X33) -> 202607-27 | AA33: =IF(Inventory!A31="","",Inventory!A31) -> PO-WET-NK-70G-002
A34: 46222 | B34: Sale | C34: Shop | D34: PawfectBD Shop | E34: PAWF-260726-FD0E4 | F34: PO-WET-WK-80G-001-KT | G34: =IF($F34="","",IFERROR(VLOOKUP($F34,Inventory!$A:$B,2,FALSE),"")) -> Whiskas Junior Tuna Flavor | H34: 1 | I34: =IF($F34="","",IF($B34="Gift",0,J34-IF(K34="",0,K34))) -> 90 | J34: =IF($F34="","",IFERROR(VLOOKUP($F34,Inventory!$A:$K,11,FALSE),0)) -> 95 | K34: 5 | L34: =IF($F34="","",IF($B34="Return",-H34*I34,H34*I34)) -> 90 | M34: Paid | N34: =IF($F34="","",IFERROR(VLOOKUP($F34,Inventory!$A:$I,9,FALSE),0)) -> 74 | O34: =IF($F34="","",IF($B34="Return",-H34*N34,H34*N34)) -> 74 | P34: =IF($F34="","",L34-O34) -> 16 | R34: =IF($E34="","",IF(COUNTIF($E$7:$E34,$E34)>1,"",IFERROR(VLOOKUP($E34,Orders!$A:$I,8,FALSE),""))) | S34: =IF($E34="","",IF(COUNTIF($E$7:$E34,$E34)>1,"",IFERROR(VLOOKUP($E34,Orders!$A:$I,9,FALSE),""))) | T34: =IF($F34="","",P34+IF(R34="",0,R34)-IF(S34="",0,S34)) -> 16 | U34: =IF($F34="","",IF($E34="",T34,SUMIF(Sales!$E$7:$E$1506,$E34,Sales!$T$7:$T$1506))) -> 52 | V34: =IF(OR($C34<>"Online",$E34=""),"",IF(COUNTIF($E$7:$E34,$E34)>1,"",COUNT($V$6:V33)+1)) | W34: {=IF($V34="","",SUMPRODUCT((Sales!$V$7:$V$1506<>"")*(Sales!$E$7:$E$1506<$E34))+1)} | X34: =IF($A34="","",COUNTIFS($A$7:$A34,">="&EOMONTH($A34,-1)+1,$A$7:$A34,"<="&EOMONTH($A34,0))) -> 28 | Y34: =IF($A34="","",TEXT($A34,"yyyymm")&"-"&$X34) -> 202607-28 | AA34: =IF(Inventory!A32="","",Inventory!A32) -> PO-WET-NK-70G-003-KT
A35: 46222 | B35: Sale | C35: Shop | D35: PawfectBD Shop | E35: PAWF-260726-18C42 | F35: TR-CRMY-15G-001 | G35: =IF($F35="","",IFERROR(VLOOKUP($F35,Inventory!$A:$B,2,FALSE),"")) -> Creamy Treat 15G (Purry & Hyper Paws) | H35: 2 | I35: =IF($F35="","",IF($B35="Gift",0,J35-IF(K35="",0,K35))) -> 20 | J35: =IF($F35="","",IFERROR(VLOOKUP($F35,Inventory!$A:$K,11,FALSE),0)) -> 20 | L35: =IF($F35="","",IF($B35="Return",-H35*I35,H35*I35)) -> 40 | M35: Paid | N35: =IF($F35="","",IFERROR(VLOOKUP($F35,Inventory!$A:$I,9,FALSE),0)) -> 8.1474119 | O35: =IF($F35="","",IF($B35="Return",-H35*N35,H35*N35)) -> 16.294824 | P35: =IF($F35="","",L35-O35) -> 23.705176 | R35: =IF($E35="","",IF(COUNTIF($E$7:$E35,$E35)>1,"",IFERROR(VLOOKUP($E35,Orders!$A:$I,8,FALSE),""))) | S35: =IF($E35="","",IF(COUNTIF($E$7:$E35,$E35)>1,"",IFERROR(VLOOKUP($E35,Orders!$A:$I,9,FALSE),""))) | T35: =IF($F35="","",P35+IF(R35="",0,R35)-IF(S35="",0,S35)) -> 23.705176 | U35: =IF($F35="","",IF($E35="",T35,SUMIF(Sales!$E$7:$E$1506,$E35,Sales!$T$7:$T$1506))) -> 15.557764 | V35: =IF(OR($C35<>"Online",$E35=""),"",IF(COUNTIF($E$7:$E35,$E35)>1,"",COUNT($V$6:V34)+1)) | W35: {=IF($V35="","",SUMPRODUCT((Sales!$V$7:$V$1506<>"")*(Sales!$E$7:$E$1506<$E35))+1)} | X35: =IF($A35="","",COUNTIFS($A$7:$A35,">="&EOMONTH($A35,-1)+1,$A$7:$A35,"<="&EOMONTH($A35,0))) -> 29 | Y35: =IF($A35="","",TEXT($A35,"yyyymm")&"-"&$X35) -> 202607-29 | AA35: =IF(Inventory!A33="","",Inventory!A33) -> PO-WET-SMHRT-TJ-85G-001
A36: 46222 | B36: Gift | C36: Shop | D36: PawfectBD Shop | E36: PAWF-260726-18C42 | F36: TR-CRMY-15G-001 | G36: =IF($F36="","",IFERROR(VLOOKUP($F36,Inventory!$A:$B,2,FALSE),"")) -> Creamy Treat 15G (Purry & Hyper Paws) | H36: 1 | I36: =IF($F36="","",IF($B36="Gift",0,J36-IF(K36="",0,K36))) -> 0 | J36: =IF($F36="","",IFERROR(VLOOKUP($F36,Inventory!$A:$K,11,FALSE),0)) -> 20 | K36: 20 | L36: =IF($F36="","",IF($B36="Return",-H36*I36,H36*I36)) -> 0 | M36: Paid | N36: =IF($F36="","",IFERROR(VLOOKUP($F36,Inventory!$A:$I,9,FALSE),0)) -> 8.1474119 | O36: =IF($F36="","",IF($B36="Return",-H36*N36,H36*N36)) -> 8.1474119 | P36: =IF($F36="","",L36-O36) -> -8.1474119 | Q36: Gift from PawfectBD | R36: =IF($E36="","",IF(COUNTIF($E$7:$E36,$E36)>1,"",IFERROR(VLOOKUP($E36,Orders!$A:$I,8,FALSE),""))) | S36: =IF($E36="","",IF(COUNTIF($E$7:$E36,$E36)>1,"",IFERROR(VLOOKUP($E36,Orders!$A:$I,9,FALSE),""))) | T36: =IF($F36="","",P36+IF(R36="",0,R36)-IF(S36="",0,S36)) -> -8.1474119 | U36: =IF($F36="","",IF($E36="",T36,SUMIF(Sales!$E$7:$E$1506,$E36,Sales!$T$7:$T$1506))) -> 15.557764 | V36: =IF(OR($C36<>"Online",$E36=""),"",IF(COUNTIF($E$7:$E36,$E36)>1,"",COUNT($V$6:V35)+1)) | W36: {=IF($V36="","",SUMPRODUCT((Sales!$V$7:$V$1506<>"")*(Sales!$E$7:$E$1506<$E36))+1)} | X36: =IF($A36="","",COUNTIFS($A$7:$A36,">="&EOMONTH($A36,-1)+1,$A$7:$A36,"<="&EOMONTH($A36,0))) -> 30 | Y36: =IF($A36="","",TEXT($A36,"yyyymm")&"-"&$X36) -> 202607-30 | AA36: =IF(Inventory!A34="","",Inventory!A34) -> PO-WET-SMHRT-TWC-85G-001
A37: 46222 | B37: Sale | C37: Shop | D37: PawfectBD Shop | E37: PAWF-260726-65F27 | F37: LT-LM-CZE-5L-001 | G37: =IF($F37="","",IFERROR(VLOOKUP($F37,Inventory!$A:$B,2,FALSE),"")) -> Cozie Cat Litter Lemon 5L | H37: 1 | I37: =IF($F37="","",IF($B37="Gift",0,J37-IF(K37="",0,K37))) -> 350 | J37: =IF($F37="","",IFERROR(VLOOKUP($F37,Inventory!$A:$K,11,FALSE),0)) -> 370 | K37: 20 | L37: =IF($F37="","",IF($B37="Return",-H37*I37,H37*I37)) -> 350 | M37: Paid | N37: =IF($F37="","",IFERROR(VLOOKUP($F37,Inventory!$A:$I,9,FALSE),0)) -> 230 | O37: =IF($F37="","",IF($B37="Return",-H37*N37,H37*N37)) -> 230 | P37: =IF($F37="","",L37-O37) -> 120 | R37: =IF($E37="","",IF(COUNTIF($E$7:$E37,$E37)>1,"",IFERROR(VLOOKUP($E37,Orders!$A:$I,8,FALSE),""))) | S37: =IF($E37="","",IF(COUNTIF($E$7:$E37,$E37)>1,"",IFERROR(VLOOKUP($E37,Orders!$A:$I,9,FALSE),""))) | T37: =IF($F37="","",P37+IF(R37="",0,R37)-IF(S37="",0,S37)) -> 120 | U37: =IF($F37="","",IF($E37="",T37,SUMIF(Sales!$E$7:$E$1506,$E37,Sales!$T$7:$T$1506))) -> 170 | V37: =IF(OR($C37<>"Online",$E37=""),"",IF(COUNTIF($E$7:$E37,$E37)>1,"",COUNT($V$6:V36)+1)) | W37: {=IF($V37="","",SUMPRODUCT((Sales!$V$7:$V$1506<>"")*(Sales!$E$7:$E$1506<$E37))+1)} | X37: =IF($A37="","",COUNTIFS($A$7:$A37,">="&EOMONTH($A37,-1)+1,$A$7:$A37,"<="&EOMONTH($A37,0))) -> 31 | Y37: =IF($A37="","",TEXT($A37,"yyyymm")&"-"&$X37) -> 202607-31 | AA37: =IF(Inventory!A35="","",Inventory!A35) -> LT-CF-DD-25L-001
A38: 46222 | B38: Gift | C38: Shop | D38: PawfectBD Shop | E38: PAWF-260726-65F27 | F38: AC-CS-002 | G38: =IF($F38="","",IFERROR(VLOOKUP($F38,Inventory!$A:$B,2,FALSE),"")) -> Cat litter scooper | H38: 1 | I38: =IF($F38="","",IF($B38="Gift",0,J38-IF(K38="",0,K38))) -> 0 | J38: =IF($F38="","",IFERROR(VLOOKUP($F38,Inventory!$A:$K,11,FALSE),0)) -> 80 | K38: 80 | L38: =IF($F38="","",IF($B38="Return",-H38*I38,H38*I38)) -> 0 | M38: Paid | N38: =IF($F38="","",IFERROR(VLOOKUP($F38,Inventory!$A:$I,9,FALSE),0)) -> 35 | O38: =IF($F38="","",IF($B38="Return",-H38*N38,H38*N38)) -> 35 | P38: =IF($F38="","",L38-O38) -> -35 | Q38: Gift From PawfectBD | R38: =IF($E38="","",IF(COUNTIF($E$7:$E38,$E38)>1,"",IFERROR(VLOOKUP($E38,Orders!$A:$I,8,FALSE),""))) | S38: =IF($E38="","",IF(COUNTIF($E$7:$E38,$E38)>1,"",IFERROR(VLOOKUP($E38,Orders!$A:$I,9,FALSE),""))) | T38: =IF($F38="","",P38+IF(R38="",0,R38)-IF(S38="",0,S38)) -> -35 | U38: =IF($F38="","",IF($E38="",T38,SUMIF(Sales!$E$7:$E$1506,$E38,Sales!$T$7:$T$1506))) -> 170 | V38: =IF(OR($C38<>"Online",$E38=""),"",IF(COUNTIF($E$7:$E38,$E38)>1,"",COUNT($V$6:V37)+1)) | W38: {=IF($V38="","",SUMPRODUCT((Sales!$V$7:$V$1506<>"")*(Sales!$E$7:$E$1506<$E38))+1)} | X38: =IF($A38="","",COUNTIFS($A$7:$A38,">="&EOMONTH($A38,-1)+1,$A$7:$A38,"<="&EOMONTH($A38,0))) -> 32 | Y38: =IF($A38="","",TEXT($A38,"yyyymm")&"-"&$X38) -> 202607-32 | AA38: =IF(Inventory!A36="","",Inventory!A36) -> LT-AP-DD-25L-002
A39: 46222 | B39: Sale | C39: Shop | D39: PawfectBD Shop | E39: PAWF-260726-65F27 | F39: AC-CF-001 | G39: =IF($F39="","",IFERROR(VLOOKUP($F39,Inventory!$A:$B,2,FALSE),"")) -> China Flea | H39: 1 | I39: =IF($F39="","",IF($B39="Gift",0,J39-IF(K39="",0,K39))) -> 120 | J39: =IF($F39="","",IFERROR(VLOOKUP($F39,Inventory!$A:$K,11,FALSE),0)) -> 120 | L39: =IF($F39="","",IF($B39="Return",-H39*I39,H39*I39)) -> 120 | M39: Paid | N39: =IF($F39="","",IFERROR(VLOOKUP($F39,Inventory!$A:$I,9,FALSE),0)) -> 65 | O39: =IF($F39="","",IF($B39="Return",-H39*N39,H39*N39)) -> 65 | P39: =IF($F39="","",L39-O39) -> 55 | R39: =IF($E39="","",IF(COUNTIF($E$7:$E39,$E39)>1,"",IFERROR(VLOOKUP($E39,Orders!$A:$I,8,FALSE),""))) | S39: =IF($E39="","",IF(COUNTIF($E$7:$E39,$E39)>1,"",IFERROR(VLOOKUP($E39,Orders!$A:$I,9,FALSE),""))) | T39: =IF($F39="","",P39+IF(R39="",0,R39)-IF(S39="",0,S39)) -> 55 | U39: =IF($F39="","",IF($E39="",T39,SUMIF(Sales!$E$7:$E$1506,$E39,Sales!$T$7:$T$1506))) -> 170 | V39: =IF(OR($C39<>"Online",$E39=""),"",IF(COUNTIF($E$7:$E39,$E39)>1,"",COUNT($V$6:V38)+1)) | W39: {=IF($V39="","",SUMPRODUCT((Sales!$V$7:$V$1506<>"")*(Sales!$E$7:$E$1506<$E39))+1)} | X39: =IF($A39="","",COUNTIFS($A$7:$A39,">="&EOMONTH($A39,-1)+1,$A$7:$A39,"<="&EOMONTH($A39,0))) -> 33 | Y39: =IF($A39="","",TEXT($A39,"yyyymm")&"-"&$X39) -> 202607-33 | AA39: =IF(Inventory!A37="","",Inventory!A37) -> LT-AP-DD-10L-001
A40: 46222 | B40: Sale | C40: Shop | D40: PawfectBD Shop | E40: PAWF-260726-65F27 | F40: FD-DRY-SMHRT-450G-001 | G40: =IF($F40="","",IFERROR(VLOOKUP($F40,Inventory!$A:$B,2,FALSE),"")) -> Smart Heart Kitten Food Chicken, Fish, Egg & Milk 450gm | H40: 1 | I40: =IF($F40="","",IF($B40="Gift",0,J40-IF(K40="",0,K40))) -> 320 | J40: =IF($F40="","",IFERROR(VLOOKUP($F40,Inventory!$A:$K,11,FALSE),0)) -> 380 | K40: 60 | L40: =IF($F40="","",IF($B40="Return",-H40*I40,H40*I40)) -> 320 | M40: Paid | N40: =IF($F40="","",IFERROR(VLOOKUP($F40,Inventory!$A:$I,9,FALSE),0)) -> 290 | O40: =IF($F40="","",IF($B40="Return",-H40*N40,H40*N40)) -> 290 | P40: =IF($F40="","",L40-O40) -> 30 | R40: =IF($E40="","",IF(COUNTIF($E$7:$E40,$E40)>1,"",IFERROR(VLOOKUP($E40,Orders!$A:$I,8,FALSE),""))) | S40: =IF($E40="","",IF(COUNTIF($E$7:$E40,$E40)>1,"",IFERROR(VLOOKUP($E40,Orders!$A:$I,9,FALSE),""))) | T40: =IF($F40="","",P40+IF(R40="",0,R40)-IF(S40="",0,S40)) -> 30 | U40: =IF($F40="","",IF($E40="",T40,SUMIF(Sales!$E$7:$E$1506,$E40,Sales!$T$7:$T$1506))) -> 170 | V40: =IF(OR($C40<>"Online",$E40=""),"",IF(COUNTIF($E$7:$E40,$E40)>1,"",COUNT($V$6:V39)+1)) | W40: {=IF($V40="","",SUMPRODUCT((Sales!$V$7:$V$1506<>"")*(Sales!$E$7:$E$1506<$E40))+1)} | X40: =IF($A40="","",COUNTIFS($A$7:$A40,">="&EOMONTH($A40,-1)+1,$A$7:$A40,"<="&EOMONTH($A40,0))) -> 34 | Y40: =IF($A40="","",TEXT($A40,"yyyymm")&"-"&$X40) -> 202607-34 | AA40: =IF(Inventory!A38="","",Inventory!A38) -> AC-SHAMP-001
A41: 46223 | B41: Sale | C41: Shop | D41: PawfectBD Shop | E41: PAWF-260726-3B7D4 | F41: TR-CRMY-15G-001 | G41: =IF($F41="","",IFERROR(VLOOKUP($F41,Inventory!$A:$B,2,FALSE),"")) -> Creamy Treat 15G (Purry & Hyper Paws) | H41: 5 | I41: =IF($F41="","",IF($B41="Gift",0,J41-IF(K41="",0,K41))) -> 20 | J41: =IF($F41="","",IFERROR(VLOOKUP($F41,Inventory!$A:$K,11,FALSE),0)) -> 20 | L41: =IF($F41="","",IF($B41="Return",-H41*I41,H41*I41)) -> 100 | M41: Paid | N41: =IF($F41="","",IFERROR(VLOOKUP($F41,Inventory!$A:$I,9,FALSE),0)) -> 8.1474119 | O41: =IF($F41="","",IF($B41="Return",-H41*N41,H41*N41)) -> 40.737059 | P41: =IF($F41="","",L41-O41) -> 59.262941 | R41: =IF($E41="","",IF(COUNTIF($E$7:$E41,$E41)>1,"",IFERROR(VLOOKUP($E41,Orders!$A:$I,8,FALSE),""))) | S41: =IF($E41="","",IF(COUNTIF($E$7:$E41,$E41)>1,"",IFERROR(VLOOKUP($E41,Orders!$A:$I,9,FALSE),""))) | T41: =IF($F41="","",P41+IF(R41="",0,R41)-IF(S41="",0,S41)) -> 59.262941 | U41: =IF($F41="","",IF($E41="",T41,SUMIF(Sales!$E$7:$E$1506,$E41,Sales!$T$7:$T$1506))) -> 59.262941 | V41: =IF(OR($C41<>"Online",$E41=""),"",IF(COUNTIF($E$7:$E41,$E41)>1,"",COUNT($V$6:V40)+1)) | W41: {=IF($V41="","",SUMPRODUCT((Sales!$V$7:$V$1506<>"")*(Sales!$E$7:$E$1506<$E41))+1)} | X41: =IF($A41="","",COUNTIFS($A$7:$A41,">="&EOMONTH($A41,-1)+1,$A$7:$A41,"<="&EOMONTH($A41,0))) -> 35 | Y41: =IF($A41="","",TEXT($A41,"yyyymm")&"-"&$X41) -> 202607-35 | AA41: =IF(Inventory!A39="","",Inventory!A39) -> AC-BOWL-001
A42: 46224 | B42: Sale | C42: Shop | D42: PawfectBD Shop | E42: PAWF-260726-A9C27 | F42: FD-DRY-KTCN-400G-002 | G42: =IF($F42="","",IFERROR(VLOOKUP($F42,Inventory!$A:$B,2,FALSE),"")) -> Kitchen Flavor Grain Free Adult 400G | H42: 1 | I42: =IF($F42="","",IF($B42="Gift",0,J42-IF(K42="",0,K42))) -> 380 | J42: =IF($F42="","",IFERROR(VLOOKUP($F42,Inventory!$A:$K,11,FALSE),0)) -> 380 | L42: =IF($F42="","",IF($B42="Return",-H42*I42,H42*I42)) -> 380 | M42: Paid | N42: =IF($F42="","",IFERROR(VLOOKUP($F42,Inventory!$A:$I,9,FALSE),0)) -> 290 | O42: =IF($F42="","",IF($B42="Return",-H42*N42,H42*N42)) -> 290 | P42: =IF($F42="","",L42-O42) -> 90 | Q42: Bkash | R42: =IF($E42="","",IF(COUNTIF($E$7:$E42,$E42)>1,"",IFERROR(VLOOKUP($E42,Orders!$A:$I,8,FALSE),""))) | S42: =IF($E42="","",IF(COUNTIF($E$7:$E42,$E42)>1,"",IFERROR(VLOOKUP($E42,Orders!$A:$I,9,FALSE),""))) | T42: =IF($F42="","",P42+IF(R42="",0,R42)-IF(S42="",0,S42)) -> 90 | U42: =IF($F42="","",IF($E42="",T42,SUMIF(Sales!$E$7:$E$1506,$E42,Sales!$T$7:$T$1506))) -> 124.85259 | V42: =IF(OR($C42<>"Online",$E42=""),"",IF(COUNTIF($E$7:$E42,$E42)>1,"",COUNT($V$6:V41)+1)) | W42: {=IF($V42="","",SUMPRODUCT((Sales!$V$7:$V$1506<>"")*(Sales!$E$7:$E$1506<$E42))+1)} | X42: =IF($A42="","",COUNTIFS($A$7:$A42,">="&EOMONTH($A42,-1)+1,$A$7:$A42,"<="&EOMONTH($A42,0))) -> 36 | Y42: =IF($A42="","",TEXT($A42,"yyyymm")&"-"&$X42) -> 202607-36 | AA42: =IF(Inventory!A40="","",Inventory!A40) -> AC-CTOY-001
A43: 46224 | B43: Sale | C43: Shop | D43: PawfectBD Shop | E43: PAWF-260726-A9C27 | F43: TR-CRMY-15G-001 | G43: =IF($F43="","",IFERROR(VLOOKUP($F43,Inventory!$A:$B,2,FALSE),"")) -> Creamy Treat 15G (Purry & Hyper Paws) | H43: 1 | I43: =IF($F43="","",IF($B43="Gift",0,J43-IF(K43="",0,K43))) -> 20 | J43: =IF($F43="","",IFERROR(VLOOKUP($F43,Inventory!$A:$K,11,FALSE),0)) -> 20 | L43: =IF($F43="","",IF($B43="Return",-H43*I43,H43*I43)) -> 20 | M43: Paid | N43: =IF($F43="","",IFERROR(VLOOKUP($F43,Inventory!$A:$I,9,FALSE),0)) -> 8.1474119 | O43: =IF($F43="","",IF($B43="Return",-H43*N43,H43*N43)) -> 8.1474119 | P43: =IF($F43="","",L43-O43) -> 11.852588 | Q43: Bkash | R43: =IF($E43="","",IF(COUNTIF($E$7:$E43,$E43)>1,"",IFERROR(VLOOKUP($E43,Orders!$A:$I,8,FALSE),""))) | S43: =IF($E43="","",IF(COUNTIF($E$7:$E43,$E43)>1,"",IFERROR(VLOOKUP($E43,Orders!$A:$I,9,FALSE),""))) | T43: =IF($F43="","",P43+IF(R43="",0,R43)-IF(S43="",0,S43)) -> 11.852588 | U43: =IF($F43="","",IF($E43="",T43,SUMIF(Sales!$E$7:$E$1506,$E43,Sales!$T$7:$T$1506))) -> 124.85259 | V43: =IF(OR($C43<>"Online",$E43=""),"",IF(COUNTIF($E$7:$E43,$E43)>1,"",COUNT($V$6:V42)+1)) | W43: {=IF($V43="","",SUMPRODUCT((Sales!$V$7:$V$1506<>"")*(Sales!$E$7:$E$1506<$E43))+1)} | X43: =IF($A43="","",COUNTIFS($A$7:$A43,">="&EOMONTH($A43,-1)+1,$A$7:$A43,"<="&EOMONTH($A43,0))) -> 37 | Y43: =IF($A43="","",TEXT($A43,"yyyymm")&"-"&$X43) -> 202607-37 | AA43: =IF(Inventory!A41="","",Inventory!A41) -> AC-HM-MD-001
A44: 46224 | B44: Sale | C44: Shop | D44: PawfectBD Shop | E44: PAWF-260726-A9C27 | F44: PO-WET-SMHRT-TJ-85G-001 | G44: =IF($F44="","",IFERROR(VLOOKUP($F44,Inventory!$A:$B,2,FALSE),"")) -> Smart Heart Pouch Tuna in Jelly Kitten | H44: 1 | I44: =IF($F44="","",IF($B44="Gift",0,J44-IF(K44="",0,K44))) -> 95 | J44: =IF($F44="","",IFERROR(VLOOKUP($F44,Inventory!$A:$K,11,FALSE),0)) -> 95 | L44: =IF($F44="","",IF($B44="Return",-H44*I44,H44*I44)) -> 95 | M44: Paid | N44: =IF($F44="","",IFERROR(VLOOKUP($F44,Inventory!$A:$I,9,FALSE),0)) -> 72 | O44: =IF($F44="","",IF($B44="Return",-H44*N44,H44*N44)) -> 72 | P44: =IF($F44="","",L44-O44) -> 23 | R44: =IF($E44="","",IF(COUNTIF($E$7:$E44,$E44)>1,"",IFERROR(VLOOKUP($E44,Orders!$A:$I,8,FALSE),""))) | S44: =IF($E44="","",IF(COUNTIF($E$7:$E44,$E44)>1,"",IFERROR(VLOOKUP($E44,Orders!$A:$I,9,FALSE),""))) | T44: =IF($F44="","",P44+IF(R44="",0,R44)-IF(S44="",0,S44)) -> 23 | U44: =IF($F44="","",IF($E44="",T44,SUMIF(Sales!$E$7:$E$1506,$E44,Sales!$T$7:$T$1506))) -> 124.85259 | V44: =IF(OR($C44<>"Online",$E44=""),"",IF(COUNTIF($E$7:$E44,$E44)>1,"",COUNT($V$6:V43)+1)) | W44: {=IF($V44="","",SUMPRODUCT((Sales!$V$7:$V$1506<>"")*(Sales!$E$7:$E$1506<$E44))+1)} | X44: =IF($A44="","",COUNTIFS($A$7:$A44,">="&EOMONTH($A44,-1)+1,$A$7:$A44,"<="&EOMONTH($A44,0))) -> 38 | Y44: =IF($A44="","",TEXT($A44,"yyyymm")&"-"&$X44) -> 202607-38 | AA44: =IF(Inventory!A42="","",Inventory!A42) -> FD-DRY-SMHRT-480G-002
A45: 46203 | B45: Sale | C45: Shop | D45: PawfectBD Shop | F45: FD-DRY-SMHRT-1.2KG-002 | G45: =IF($F45="","",IFERROR(VLOOKUP($F45,Inventory!$A:$B,2,FALSE),"")) -> Smart Heart Adult Cat Food Chicken & Tuna 1.2KG | H45: 1 | I45: =IF($F45="","",IF($B45="Gift",0,J45-IF(K45="",0,K45))) -> 770 | J45: =IF($F45="","",IFERROR(VLOOKUP($F45,Inventory!$A:$K,11,FALSE),0)) -> 770 | L45: =IF($F45="","",IF($B45="Return",-H45*I45,H45*I45)) -> 770 | M45: Paid | N45: =IF($F45="","",IFERROR(VLOOKUP($F45,Inventory!$A:$I,9,FALSE),0)) -> 600 | O45: =IF($F45="","",IF($B45="Return",-H45*N45,H45*N45)) -> 600 | P45: =IF($F45="","",L45-O45) -> 170 | Q45: Original sale before July — exact date unknown, placeholder 30-Jun-2026. Customer later returned this and bought 1.2KG-003. | R45: =IF($E45="","",IF(COUNTIF($E$7:$E45,$E45)>1,"",IFERROR(VLOOKUP($E45,Orders!$A:$I,8,FALSE),""))) | S45: =IF($E45="","",IF(COUNTIF($E$7:$E45,$E45)>1,"",IFERROR(VLOOKUP($E45,Orders!$A:$I,9,FALSE),""))) | T45: =IF($F45="","",P45+IF(R45="",0,R45)-IF(S45="",0,S45)) -> 170 | U45: =IF($F45="","",IF($E45="",T45,SUMIF(Sales!$E$7:$E$1506,$E45,Sales!$T$7:$T$1506))) -> 170 | V45: =IF(OR($C45<>"Online",$E45=""),"",IF(COUNTIF($E$7:$E45,$E45)>1,"",COUNT($V$6:V44)+1)) | W45: {=IF($V45="","",SUMPRODUCT((Sales!$V$7:$V$1506<>"")*(Sales!$E$7:$E$1506<$E45))+1)} | X45: =IF($A45="","",COUNTIFS($A$7:$A45,">="&EOMONTH($A45,-1)+1,$A$7:$A45,"<="&EOMONTH($A45,0))) -> 1 | Y45: =IF($A45="","",TEXT($A45,"yyyymm")&"-"&$X45) -> 202606-1 | AA45: =IF(Inventory!A43="","",Inventory!A43) -> PO-WET-WK-80G-001-KT
A46: 46225 | B46: Return | C46: Shop | D46: PawfectBD Shop | F46: FD-DRY-SMHRT-1.2KG-002 | G46: =IF($F46="","",IFERROR(VLOOKUP($F46,Inventory!$A:$B,2,FALSE),"")) -> Smart Heart Adult Cat Food Chicken & Tuna 1.2KG | H46: 1 | I46: =IF($F46="","",IF($B46="Gift",0,J46-IF(K46="",0,K46))) -> 770 | J46: =IF($F46="","",IFERROR(VLOOKUP($F46,Inventory!$A:$K,11,FALSE),0)) -> 770 | L46: =IF($F46="","",IF($B46="Return",-H46*I46,H46*I46)) -> -770 | M46: Paid | N46: =IF($F46="","",IFERROR(VLOOKUP($F46,Inventory!$A:$I,9,FALSE),0)) -> 600 | O46: =IF($F46="","",IF($B46="Return",-H46*N46,H46*N46)) -> -600 | P46: =IF($F46="","",L46-O46) -> -170 | R46: =IF($E46="","",IF(COUNTIF($E$7:$E46,$E46)>1,"",IFERROR(VLOOKUP($E46,Orders!$A:$I,8,FALSE),""))) | S46: =IF($E46="","",IF(COUNTIF($E$7:$E46,$E46)>1,"",IFERROR(VLOOKUP($E46,Orders!$A:$I,9,FALSE),""))) | T46: =IF($F46="","",P46+IF(R46="",0,R46)-IF(S46="",0,S46)) -> -170 | U46: =IF($F46="","",IF($E46="",T46,SUMIF(Sales!$E$7:$E$1506,$E46,Sales!$T$7:$T$1506))) -> -170 | V46: =IF(OR($C46<>"Online",$E46=""),"",IF(COUNTIF($E$7:$E46,$E46)>1,"",COUNT($V$6:V45)+1)) | W46: {=IF($V46="","",SUMPRODUCT((Sales!$V$7:$V$1506<>"")*(Sales!$E$7:$E$1506<$E46))+1)} | X46: =IF($A46="","",COUNTIFS($A$7:$A46,">="&EOMONTH($A46,-1)+1,$A$7:$A46,"<="&EOMONTH($A46,0))) -> 39 | Y46: =IF($A46="","",TEXT($A46,"yyyymm")&"-"&$X46) -> 202607-39 | AA46: =IF(Inventory!A44="","",Inventory!A44) -> AC-CTOY-002
A47: 46225 | B47: Sale | C47: Shop | D47: PawfectBD Shop | F47: FD-DRY-SMHRT-1.2KG-003 | G47: =IF($F47="","",IFERROR(VLOOKUP($F47,Inventory!$A:$B,2,FALSE),"")) -> Smart Heart Kitten Cat Food Chicken & Tuna 1.2KG | H47: 1 | I47: =IF($F47="","",IF($B47="Gift",0,J47-IF(K47="",0,K47))) -> 820 | J47: =IF($F47="","",IFERROR(VLOOKUP($F47,Inventory!$A:$K,11,FALSE),0)) -> 820 | L47: =IF($F47="","",IF($B47="Return",-H47*I47,H47*I47)) -> 820 | M47: Paid | N47: =IF($F47="","",IFERROR(VLOOKUP($F47,Inventory!$A:$I,9,FALSE),0)) -> 635 | O47: =IF($F47="","",IF($B47="Return",-H47*N47,H47*N47)) -> 635 | P47: =IF($F47="","",L47-O47) -> 185 | R47: =IF($E47="","",IF(COUNTIF($E$7:$E47,$E47)>1,"",IFERROR(VLOOKUP($E47,Orders!$A:$I,8,FALSE),""))) | S47: =IF($E47="","",IF(COUNTIF($E$7:$E47,$E47)>1,"",IFERROR(VLOOKUP($E47,Orders!$A:$I,9,FALSE),""))) | T47: =IF($F47="","",P47+IF(R47="",0,R47)-IF(S47="",0,S47)) -> 185 | U47: =IF($F47="","",IF($E47="",T47,SUMIF(Sales!$E$7:$E$1506,$E47,Sales!$T$7:$T$1506))) -> 185 | V47: =IF(OR($C47<>"Online",$E47=""),"",IF(COUNTIF($E$7:$E47,$E47)>1,"",COUNT($V$6:V46)+1)) | W47: {=IF($V47="","",SUMPRODUCT((Sales!$V$7:$V$1506<>"")*(Sales!$E$7:$E$1506<$E47))+1)} | X47: =IF($A47="","",COUNTIFS($A$7:$A47,">="&EOMONTH($A47,-1)+1,$A$7:$A47,"<="&EOMONTH($A47,0))) -> 40 | Y47: =IF($A47="","",TEXT($A47,"yyyymm")&"-"&$X47) -> 202607-40 | AA47: =IF(Inventory!A45="","",Inventory!A45) -> AC-PNC-SM-001
A48: 46225 | B48: Sale | C48: Shop | D48: PawfectBD Shop | F48: AC-CF-001 | G48: =IF($F48="","",IFERROR(VLOOKUP($F48,Inventory!$A:$B,2,FALSE),"")) -> China Flea | H48: 1 | I48: =IF($F48="","",IF($B48="Gift",0,J48-IF(K48="",0,K48))) -> 90 | J48: =IF($F48="","",IFERROR(VLOOKUP($F48,Inventory!$A:$K,11,FALSE),0)) -> 120 | K48: 30 | L48: =IF($F48="","",IF($B48="Return",-H48*I48,H48*I48)) -> 90 | M48: Paid | N48: =IF($F48="","",IFERROR(VLOOKUP($F48,Inventory!$A:$I,9,FALSE),0)) -> 65 | O48: =IF($F48="","",IF($B48="Return",-H48*N48,H48*N48)) -> 65 | P48: =IF($F48="","",L48-O48) -> 25 | R48: =IF($E48="","",IF(COUNTIF($E$7:$E48,$E48)>1,"",IFERROR(VLOOKUP($E48,Orders!$A:$I,8,FALSE),""))) | S48: =IF($E48="","",IF(COUNTIF($E$7:$E48,$E48)>1,"",IFERROR(VLOOKUP($E48,Orders!$A:$I,9,FALSE),""))) | T48: =IF($F48="","",P48+IF(R48="",0,R48)-IF(S48="",0,S48)) -> 25 | U48: =IF($F48="","",IF($E48="",T48,SUMIF(Sales!$E$7:$E$1506,$E48,Sales!$T$7:$T$1506))) -> 25 | V48: =IF(OR($C48<>"Online",$E48=""),"",IF(COUNTIF($E$7:$E48,$E48)>1,"",COUNT($V$6:V47)+1)) | W48: {=IF($V48="","",SUMPRODUCT((Sales!$V$7:$V$1506<>"")*(Sales!$E$7:$E$1506<$E48))+1)} | X48: =IF($A48="","",COUNTIFS($A$7:$A48,">="&EOMONTH($A48,-1)+1,$A$7:$A48,"<="&EOMONTH($A48,0))) -> 41 | Y48: =IF($A48="","",TEXT($A48,"yyyymm")&"-"&$X48) -> 202607-41 | AA48: =IF(Inventory!A46="","",Inventory!A46) -> AC-CB-RD-001
A49: 46226 | B49: Sale | C49: Shop | D49: PawfectBD Shop | E49: PAWF-260729-5B3A8 | F49: TR-CRMY-15G-001 | G49: =IF($F49="","",IFERROR(VLOOKUP($F49,Inventory!$A:$B,2,FALSE),"")) -> Creamy Treat 15G (Purry & Hyper Paws) | H49: 2 | I49: =IF($F49="","",IF($B49="Gift",0,J49-IF(K49="",0,K49))) -> 20 | J49: =IF($F49="","",IFERROR(VLOOKUP($F49,Inventory!$A:$K,11,FALSE),0)) -> 20 | L49: =IF($F49="","",IF($B49="Return",-H49*I49,H49*I49)) -> 40 | M49: Paid | N49: =IF($F49="","",IFERROR(VLOOKUP($F49,Inventory!$A:$I,9,FALSE),0)) -> 8.1474119 | O49: =IF($F49="","",IF($B49="Return",-H49*N49,H49*N49)) -> 16.294824 | P49: =IF($F49="","",L49-O49) -> 23.705176 | R49: =IF($E49="","",IF(COUNTIF($E$7:$E49,$E49)>1,"",IFERROR(VLOOKUP($E49,Orders!$A:$I,8,FALSE),""))) | S49: =IF($E49="","",IF(COUNTIF($E$7:$E49,$E49)>1,"",IFERROR(VLOOKUP($E49,Orders!$A:$I,9,FALSE),""))) | T49: =IF($F49="","",P49+IF(R49="",0,R49)-IF(S49="",0,S49)) -> 23.705176 | U49: =IF($F49="","",IF($E49="",T49,SUMIF(Sales!$E$7:$E$1506,$E49,Sales!$T$7:$T$1506))) -> 519.16107 | V49: =IF(OR($C49<>"Online",$E49=""),"",IF(COUNTIF($E$7:$E49,$E49)>1,"",COUNT($V$6:V48)+1)) | W49: {=IF($V49="","",SUMPRODUCT((Sales!$V$7:$V$1506<>"")*(Sales!$E$7:$E$1506<$E49))+1)} | X49: =IF($A49="","",COUNTIFS($A$7:$A49,">="&EOMONTH($A49,-1)+1,$A$7:$A49,"<="&EOMONTH($A49,0))) -> 42 | Y49: =IF($A49="","",TEXT($A49,"yyyymm")&"-"&$X49) -> 202607-42 | AA49: =IF(Inventory!A47="","",Inventory!A47) -> AC-CB-BW-001
A50: 46226 | B50: Sale | C50: Shop | D50: PawfectBD Shop | E50: PAWF-260729-5B3A8 | F50: LT-MX-DCLP-5L-002 | G50: =IF($F50="","",IFERROR(VLOOKUP($F50,Inventory!$A:$B,2,FALSE),"")) -> Cat Litter Mix Flavor 5L DR. Clump | H50: 1 | I50: =IF($F50="","",IF($B50="Gift",0,J50-IF(K50="",0,K50))) -> 300 | J50: =IF($F50="","",IFERROR(VLOOKUP($F50,Inventory!$A:$K,11,FALSE),0)) -> 320 | K50: 20 | L50: =IF($F50="","",IF($B50="Return",-H50*I50,H50*I50)) -> 300 | M50: Paid | N50: =IF($F50="","",IFERROR(VLOOKUP($F50,Inventory!$A:$I,9,FALSE),0)) -> 220 | O50: =IF($F50="","",IF($B50="Return",-H50*N50,H50*N50)) -> 220 | P50: =IF($F50="","",L50-O50) -> 80 | R50: =IF($E50="","",IF(COUNTIF($E$7:$E50,$E50)>1,"",IFERROR(VLOOKUP($E50,Orders!$A:$I,8,FALSE),""))) | S50: =IF($E50="","",IF(COUNTIF($E$7:$E50,$E50)>1,"",IFERROR(VLOOKUP($E50,Orders!$A:$I,9,FALSE),""))) | T50: =IF($F50="","",P50+IF(R50="",0,R50)-IF(S50="",0,S50)) -> 80 | U50: =IF($F50="","",IF($E50="",T50,SUMIF(Sales!$E$7:$E$1506,$E50,Sales!$T$7:$T$1506))) -> 519.16107 | V50: =IF(OR($C50<>"Online",$E50=""),"",IF(COUNTIF($E$7:$E50,$E50)>1,"",COUNT($V$6:V49)+1)) | W50: {=IF($V50="","",SUMPRODUCT((Sales!$V$7:$V$1506<>"")*(Sales!$E$7:$E$1506<$E50))+1)} | X50: =IF($A50="","",COUNTIFS($A$7:$A50,">="&EOMONTH($A50,-1)+1,$A$7:$A50,"<="&EOMONTH($A50,0))) -> 43 | Y50: =IF($A50="","",TEXT($A50,"yyyymm")&"-"&$X50) -> 202607-43 | AA50: =IF(Inventory!A48="","",Inventory!A48) -> AC-CB-FC-001
A51: 46226 | B51: Sale | C51: Shop | D51: PawfectBD Shop | E51: PAWF-260729-5B3A8 | F51: PO-WET-SMHRT-TWC-85G-001 | G51: =IF($F51="","",IFERROR(VLOOKUP($F51,Inventory!$A:$B,2,FALSE),"")) -> Smart Heart Pouch Tuna With Chicken in Jelly | H51: 2 | I51: =IF($F51="","",IF($B51="Gift",0,J51-IF(K51="",0,K51))) -> 95 | J51: =IF($F51="","",IFERROR(VLOOKUP($F51,Inventory!$A:$K,11,FALSE),0)) -> 95 | L51: =IF($F51="","",IF($B51="Return",-H51*I51,H51*I51)) -> 190 | M51: Paid | N51: =IF($F51="","",IFERROR(VLOOKUP($F51,Inventory!$A:$I,9,FALSE),0)) -> 71.904762 | O51: =IF($F51="","",IF($B51="Return",-H51*N51,H51*N51)) -> 143.80952 | P51: =IF($F51="","",L51-O51) -> 46.190476 | R51: =IF($E51="","",IF(COUNTIF($E$7:$E51,$E51)>1,"",IFERROR(VLOOKUP($E51,Orders!$A:$I,8,FALSE),""))) | S51: =IF($E51="","",IF(COUNTIF($E$7:$E51,$E51)>1,"",IFERROR(VLOOKUP($E51,Orders!$A:$I,9,FALSE),""))) | T51: =IF($F51="","",P51+IF(R51="",0,R51)-IF(S51="",0,S51)) -> 46.190476 | U51: =IF($F51="","",IF($E51="",T51,SUMIF(Sales!$E$7:$E$1506,$E51,Sales!$T$7:$T$1506))) -> 519.16107 | V51: =IF(OR($C51<>"Online",$E51=""),"",IF(COUNTIF($E$7:$E51,$E51)>1,"",COUNT($V$6:V50)+1)) | W51: {=IF($V51="","",SUMPRODUCT((Sales!$V$7:$V$1506<>"")*(Sales!$E$7:$E$1506<$E51))+1)} | X51: =IF($A51="","",COUNTIFS($A$7:$A51,">="&EOMONTH($A51,-1)+1,$A$7:$A51,"<="&EOMONTH($A51,0))) -> 44 | Y51: =IF($A51="","",TEXT($A51,"yyyymm")&"-"&$X51) -> 202607-44 | AA51: =IF(Inventory!A49="","",Inventory!A49) -> AC-CTOY-003
A52: 46226 | B52: Sale | C52: Shop | D52: PawfectBD Shop | E52: PAWF-260729-5B3A8 | F52: TR-CRMY-15G-001 | G52: =IF($F52="","",IFERROR(VLOOKUP($F52,Inventory!$A:$B,2,FALSE),"")) -> Creamy Treat 15G (Purry & Hyper Paws) | H52: 1 | I52: =IF($F52="","",IF($B52="Gift",0,J52-IF(K52="",0,K52))) -> 20 | J52: =IF($F52="","",IFERROR(VLOOKUP($F52,Inventory!$A:$K,11,FALSE),0)) -> 20 | L52: =IF($F52="","",IF($B52="Return",-H52*I52,H52*I52)) -> 20 | M52: Paid | N52: =IF($F52="","",IFERROR(VLOOKUP($F52,Inventory!$A:$I,9,FALSE),0)) -> 8.1474119 | O52: =IF($F52="","",IF($B52="Return",-H52*N52,H52*N52)) -> 8.1474119 | P52: =IF($F52="","",L52-O52) -> 11.852588 | R52: =IF($E52="","",IF(COUNTIF($E$7:$E52,$E52)>1,"",IFERROR(VLOOKUP($E52,Orders!$A:$I,8,FALSE),""))) | S52: =IF($E52="","",IF(COUNTIF($E$7:$E52,$E52)>1,"",IFERROR(VLOOKUP($E52,Orders!$A:$I,9,FALSE),""))) | T52: =IF($F52="","",P52+IF(R52="",0,R52)-IF(S52="",0,S52)) -> 11.852588 | U52: =IF($F52="","",IF($E52="",T52,SUMIF(Sales!$E$7:$E$1506,$E52,Sales!$T$7:$T$1506))) -> 519.16107 | V52: =IF(OR($C52<>"Online",$E52=""),"",IF(COUNTIF($E$7:$E52,$E52)>1,"",COUNT($V$6:V51)+1)) | W52: {=IF($V52="","",SUMPRODUCT((Sales!$V$7:$V$1506<>"")*(Sales!$E$7:$E$1506<$E52))+1)} | X52: =IF($A52="","",COUNTIFS($A$7:$A52,">="&EOMONTH($A52,-1)+1,$A$7:$A52,"<="&EOMONTH($A52,0))) -> 45 | Y52: =IF($A52="","",TEXT($A52,"yyyymm")&"-"&$X52) -> 202607-45 | AA52: =IF(Inventory!A50="","",Inventory!A50) -> LT-MX-DCLP-5L-002
A53: 46226 | B53: Sale | C53: Shop | D53: PawfectBD Shop | E53: PAWF-260729-5B3A8 | F53: AC-CB-001 | G53: =IF($F53="","",IFERROR(VLOOKUP($F53,Inventory!$A:$B,2,FALSE),"")) -> Cat Belt | H53: 2 | I53: =IF($F53="","",IF($B53="Gift",0,J53-IF(K53="",0,K53))) -> 50 | J53: =IF($F53="","",IFERROR(VLOOKUP($F53,Inventory!$A:$K,11,FALSE),0)) -> 60 | K53: 10 | L53: =IF($F53="","",IF($B53="Return",-H53*I53,H53*I53)) -> 100 | M53: Paid | N53: =IF($F53="","",IFERROR(VLOOKUP($F53,Inventory!$A:$I,9,FALSE),0)) -> 29.351351 | O53: =IF($F53="","",IF($B53="Return",-H53*N53,H53*N53)) -> 58.702703 | P53: =IF($F53="","",L53-O53) -> 41.297297 | R53: =IF($E53="","",IF(COUNTIF($E$7:$E53,$E53)>1,"",IFERROR(VLOOKUP($E53,Orders!$A:$I,8,FALSE),""))) | S53: =IF($E53="","",IF(COUNTIF($E$7:$E53,$E53)>1,"",IFERROR(VLOOKUP($E53,Orders!$A:$I,9,FALSE),""))) | T53: =IF($F53="","",P53+IF(R53="",0,R53)-IF(S53="",0,S53)) -> 41.297297 | U53: =IF($F53="","",IF($E53="",T53,SUMIF(Sales!$E$7:$E$1506,$E53,Sales!$T$7:$T$1506))) -> 519.16107 | V53: =IF(OR($C53<>"Online",$E53=""),"",IF(COUNTIF($E$7:$E53,$E53)>1,"",COUNT($V$6:V52)+1)) | W53: {=IF($V53="","",SUMPRODUCT((Sales!$V$7:$V$1506<>"")*(Sales!$E$7:$E$1506<$E53))+1)} | X53: =IF($A53="","",COUNTIFS($A$7:$A53,">="&EOMONTH($A53,-1)+1,$A$7:$A53,"<="&EOMONTH($A53,0))) -> 46 | Y53: =IF($A53="","",TEXT($A53,"yyyymm")&"-"&$X53) -> 202607-46 | AA53: =IF(Inventory!A51="","",Inventory!A51) -> LT-MX-DCLP-10L-001
A54: 46226 | B54: Sale | C54: Shop | D54: PawfectBD Shop | E54: PAWF-260729-5B3A8 | F54: TR-CRMY-15G-001 | G54: =IF($F54="","",IFERROR(VLOOKUP($F54,Inventory!$A:$B,2,FALSE),"")) -> Creamy Treat 15G (Purry & Hyper Paws) | H54: 5 | I54: =IF($F54="","",IF($B54="Gift",0,J54-IF(K54="",0,K54))) -> 20 | J54: =IF($F54="","",IFERROR(VLOOKUP($F54,Inventory!$A:$K,11,FALSE),0)) -> 20 | L54: =IF($F54="","",IF($B54="Return",-H54*I54,H54*I54)) -> 100 | M54: Paid | N54: =IF($F54="","",IFERROR(VLOOKUP($F54,Inventory!$A:$I,9,FALSE),0)) -> 8.1474119 | O54: =IF($F54="","",IF($B54="Return",-H54*N54,H54*N54)) -> 40.737059 | P54: =IF($F54="","",L54-O54) -> 59.262941 | R54: =IF($E54="","",IF(COUNTIF($E$7:$E54,$E54)>1,"",IFERROR(VLOOKUP($E54,Orders!$A:$I,8,FALSE),""))) | S54: =IF($E54="","",IF(COUNTIF($E$7:$E54,$E54)>1,"",IFERROR(VLOOKUP($E54,Orders!$A:$I,9,FALSE),""))) | T54: =IF($F54="","",P54+IF(R54="",0,R54)-IF(S54="",0,S54)) -> 59.262941 | U54: =IF($F54="","",IF($E54="",T54,SUMIF(Sales!$E$7:$E$1506,$E54,Sales!$T$7:$T$1506))) -> 519.16107 | V54: =IF(OR($C54<>"Online",$E54=""),"",IF(COUNTIF($E$7:$E54,$E54)>1,"",COUNT($V$6:V53)+1)) | W54: {=IF($V54="","",SUMPRODUCT((Sales!$V$7:$V$1506<>"")*(Sales!$E$7:$E$1506<$E54))+1)} | X54: =IF($A54="","",COUNTIFS($A$7:$A54,">="&EOMONTH($A54,-1)+1,$A$7:$A54,"<="&EOMONTH($A54,0))) -> 47 | Y54: =IF($A54="","",TEXT($A54,"yyyymm")&"-"&$X54) -> 202607-47 | AA54: =IF(Inventory!A52="","",Inventory!A52) -> TR-CKN-SMHRT-70G-001
A55: 46226 | B55: Sale | C55: Shop | D55: PawfectBD Shop | E55: PAWF-260729-5B3A8 | F55: FD-DRY-ZOI-1KG-001 | G55: =IF($F55="","",IFERROR(VLOOKUP($F55,Inventory!$A:$B,2,FALSE),"")) -> Zoi Cat Food 1kg | H55: 1 | I55: =IF($F55="","",IF($B55="Gift",0,J55-IF(K55="",0,K55))) -> 360 | J55: =IF($F55="","",IFERROR(VLOOKUP($F55,Inventory!$A:$K,11,FALSE),0)) -> 380 | K55: 20 | L55: =IF($F55="","",IF($B55="Return",-H55*I55,H55*I55)) -> 360 | M55: Paid | N55: =IF($F55="","",IFERROR(VLOOKUP($F55,Inventory!$A:$I,9,FALSE),0)) -> 300 | O55: =IF($F55="","",IF($B55="Return",-H55*N55,H55*N55)) -> 300 | P55: =IF($F55="","",L55-O55) -> 60 | R55: =IF($E55="","",IF(COUNTIF($E$7:$E55,$E55)>1,"",IFERROR(VLOOKUP($E55,Orders!$A:$I,8,FALSE),""))) | S55: =IF($E55="","",IF(COUNTIF($E$7:$E55,$E55)>1,"",IFERROR(VLOOKUP($E55,Orders!$A:$I,9,FALSE),""))) | T55: =IF($F55="","",P55+IF(R55="",0,R55)-IF(S55="",0,S55)) -> 60 | U55: =IF($F55="","",IF($E55="",T55,SUMIF(Sales!$E$7:$E$1506,$E55,Sales!$T$7:$T$1506))) -> 519.16107 | V55: =IF(OR($C55<>"Online",$E55=""),"",IF(COUNTIF($E$7:$E55,$E55)>1,"",COUNT($V$6:V54)+1)) | W55: {=IF($V55="","",SUMPRODUCT((Sales!$V$7:$V$1506<>"")*(Sales!$E$7:$E$1506<$E55))+1)} | X55: =IF($A55="","",COUNTIFS($A$7:$A55,">="&EOMONTH($A55,-1)+1,$A$7:$A55,"<="&EOMONTH($A55,0))) -> 48 | Y55: =IF($A55="","",TEXT($A55,"yyyymm")&"-"&$X55) -> 202607-48 | AA55: =IF(Inventory!A53="","",Inventory!A53) -> FD-DRY-KTCN-400G-001
A56: 46226 | B56: Sale | C56: Shop | D56: PawfectBD Shop | E56: PAWF-260729-5B3A8 | F56: FD-DRY-KTCN-400G-002 | G56: =IF($F56="","",IFERROR(VLOOKUP($F56,Inventory!$A:$B,2,FALSE),"")) -> Kitchen Flavor Grain Free Adult 400G | H56: 1 | I56: =IF($F56="","",IF($B56="Gift",0,J56-IF(K56="",0,K56))) -> 360 | J56: =IF($F56="","",IFERROR(VLOOKUP($F56,Inventory!$A:$K,11,FALSE),0)) -> 380 | K56: 20 | L56: =IF($F56="","",IF($B56="Return",-H56*I56,H56*I56)) -> 360 | M56: Paid | N56: =IF($F56="","",IFERROR(VLOOKUP($F56,Inventory!$A:$I,9,FALSE),0)) -> 290 | O56: =IF($F56="","",IF($B56="Return",-H56*N56,H56*N56)) -> 290 | P56: =IF($F56="","",L56-O56) -> 70 | R56: =IF($E56="","",IF(COUNTIF($E$7:$E56,$E56)>1,"",IFERROR(VLOOKUP($E56,Orders!$A:$I,8,FALSE),""))) | S56: =IF($E56="","",IF(COUNTIF($E$7:$E56,$E56)>1,"",IFERROR(VLOOKUP($E56,Orders!$A:$I,9,FALSE),""))) | T56: =IF($F56="","",P56+IF(R56="",0,R56)-IF(S56="",0,S56)) -> 70 | U56: =IF($F56="","",IF($E56="",T56,SUMIF(Sales!$E$7:$E$1506,$E56,Sales!$T$7:$T$1506))) -> 519.16107 | V56: =IF(OR($C56<>"Online",$E56=""),"",IF(COUNTIF($E$7:$E56,$E56)>1,"",COUNT($V$6:V55)+1)) | W56: {=IF($V56="","",SUMPRODUCT((Sales!$V$7:$V$1506<>"")*(Sales!$E$7:$E$1506<$E56))+1)} | X56: =IF($A56="","",COUNTIFS($A$7:$A56,">="&EOMONTH($A56,-1)+1,$A$7:$A56,"<="&EOMONTH($A56,0))) -> 49 | Y56: =IF($A56="","",TEXT($A56,"yyyymm")&"-"&$X56) -> 202607-49 | AA56: =IF(Inventory!A54="","",Inventory!A54) -> FD-DRY-KTCN-400G-002
A57: 46226 | B57: Sale | C57: Shop | D57: PawfectBD Shop | E57: PAWF-260729-5B3A8 | F57: AC-CTOY-002 | G57: =IF($F57="","",IFERROR(VLOOKUP($F57,Inventory!$A:$B,2,FALSE),"")) -> Cat Toy Rainbow Ball Spring | H57: 1 | I57: =IF($F57="","",IF($B57="Gift",0,J57-IF(K57="",0,K57))) -> 110 | J57: =IF($F57="","",IFERROR(VLOOKUP($F57,Inventory!$A:$K,11,FALSE),0)) -> 130 | K57: 20 | L57: =IF($F57="","",IF($B57="Return",-H57*I57,H57*I57)) -> 110 | M57: Paid | N57: =IF($F57="","",IFERROR(VLOOKUP($F57,Inventory!$A:$I,9,FALSE),0)) -> 80 | O57: =IF($F57="","",IF($B57="Return",-H57*N57,H57*N57)) -> 80 | P57: =IF($F57="","",L57-O57) -> 30 | R57: =IF($E57="","",IF(COUNTIF($E$7:$E57,$E57)>1,"",IFERROR(VLOOKUP($E57,Orders!$A:$I,8,FALSE),""))) | S57: =IF($E57="","",IF(COUNTIF($E$7:$E57,$E57)>1,"",IFERROR(VLOOKUP($E57,Orders!$A:$I,9,FALSE),""))) | T57: =IF($F57="","",P57+IF(R57="",0,R57)-IF(S57="",0,S57)) -> 30 | U57: =IF($F57="","",IF($E57="",T57,SUMIF(Sales!$E$7:$E$1506,$E57,Sales!$T$7:$T$1506))) -> 519.16107 | V57: =IF(OR($C57<>"Online",$E57=""),"",IF(COUNTIF($E$7:$E57,$E57)>1,"",COUNT($V$6:V56)+1)) | W57: {=IF($V57="","",SUMPRODUCT((Sales!$V$7:$V$1506<>"")*(Sales!$E$7:$E$1506<$E57))+1)} | X57: =IF($A57="","",COUNTIFS($A$7:$A57,">="&EOMONTH($A57,-1)+1,$A$7:$A57,"<="&EOMONTH($A57,0))) -> 50 | Y57: =IF($A57="","",TEXT($A57,"yyyymm")&"-"&$X57) -> 202607-50 | AA57: =IF(Inventory!A55="","",Inventory!A55) -> FD-DRY-KTCN-1.5G-001
A58: 46226 | B58: Sale | C58: Shop | D58: PawfectBD Shop | E58: PAWF-260729-5B3A8 | F58: TR-CKN-SMHRT-70G-001 | G58: =IF($F58="","",IFERROR(VLOOKUP($F58,Inventory!$A:$B,2,FALSE),"")) -> Smart Heart Chicken Treat | H58: 2 | I58: =IF($F58="","",IF($B58="Gift",0,J58-IF(K58="",0,K58))) -> 60 | J58: =IF($F58="","",IFERROR(VLOOKUP($F58,Inventory!$A:$K,11,FALSE),0)) -> 65 | K58: 5 | L58: =IF($F58="","",IF($B58="Return",-H58*I58,H58*I58)) -> 120 | M58: Paid | N58: =IF($F58="","",IFERROR(VLOOKUP($F58,Inventory!$A:$I,9,FALSE),0)) -> 47.5 | O58: =IF($F58="","",IF($B58="Return",-H58*N58,H58*N58)) -> 95 | P58: =IF($F58="","",L58-O58) -> 25 | R58: =IF($E58="","",IF(COUNTIF($E$7:$E58,$E58)>1,"",IFERROR(VLOOKUP($E58,Orders!$A:$I,8,FALSE),""))) | S58: =IF($E58="","",IF(COUNTIF($E$7:$E58,$E58)>1,"",IFERROR(VLOOKUP($E58,Orders!$A:$I,9,FALSE),""))) | T58: =IF($F58="","",P58+IF(R58="",0,R58)-IF(S58="",0,S58)) -> 25 | U58: =IF($F58="","",IF($E58="",T58,SUMIF(Sales!$E$7:$E$1506,$E58,Sales!$T$7:$T$1506))) -> 519.16107 | V58: =IF(OR($C58<>"Online",$E58=""),"",IF(COUNTIF($E$7:$E58,$E58)>1,"",COUNT($V$6:V57)+1)) | W58: {=IF($V58="","",SUMPRODUCT((Sales!$V$7:$V$1506<>"")*(Sales!$E$7:$E$1506<$E58))+1)} | X58: =IF($A58="","",COUNTIFS($A$7:$A58,">="&EOMONTH($A58,-1)+1,$A$7:$A58,"<="&EOMONTH($A58,0))) -> 51 | Y58: =IF($A58="","",TEXT($A58,"yyyymm")&"-"&$X58) -> 202607-51 | AA58: =IF(Inventory!A56="","",Inventory!A56) -> FD-WET-KTCN-001
A59: 46226 | B59: Sale | C59: Shop | D59: PawfectBD Shop | E59: PAWF-260729-5B3A8 | F59: TR-CRMY-15G-001 | G59: =IF($F59="","",IFERROR(VLOOKUP($F59,Inventory!$A:$B,2,FALSE),"")) -> Creamy Treat 15G (Purry & Hyper Paws) | H59: 1 | I59: =IF($F59="","",IF($B59="Gift",0,J59-IF(K59="",0,K59))) -> 20 | J59: =IF($F59="","",IFERROR(VLOOKUP($F59,Inventory!$A:$K,11,FALSE),0)) -> 20 | L59: =IF($F59="","",IF($B59="Return",-H59*I59,H59*I59)) -> 20 | M59: Paid | N59: =IF($F59="","",IFERROR(VLOOKUP($F59,Inventory!$A:$I,9,FALSE),0)) -> 8.1474119 | O59: =IF($F59="","",IF($B59="Return",-H59*N59,H59*N59)) -> 8.1474119 | P59: =IF($F59="","",L59-O59) -> 11.852588 | R59: =IF($E59="","",IF(COUNTIF($E$7:$E59,$E59)>1,"",IFERROR(VLOOKUP($E59,Orders!$A:$I,8,FALSE),""))) | S59: =IF($E59="","",IF(COUNTIF($E$7:$E59,$E59)>1,"",IFERROR(VLOOKUP($E59,Orders!$A:$I,9,FALSE),""))) | T59: =IF($F59="","",P59+IF(R59="",0,R59)-IF(S59="",0,S59)) -> 11.852588 | U59: =IF($F59="","",IF($E59="",T59,SUMIF(Sales!$E$7:$E$1506,$E59,Sales!$T$7:$T$1506))) -> 519.16107 | V59: =IF(OR($C59<>"Online",$E59=""),"",IF(COUNTIF($E$7:$E59,$E59)>1,"",COUNT($V$6:V58)+1)) | W59: {=IF($V59="","",SUMPRODUCT((Sales!$V$7:$V$1506<>"")*(Sales!$E$7:$E$1506<$E59))+1)} | X59: =IF($A59="","",COUNTIFS($A$7:$A59,">="&EOMONTH($A59,-1)+1,$A$7:$A59,"<="&EOMONTH($A59,0))) -> 52 | Y59: =IF($A59="","",TEXT($A59,"yyyymm")&"-"&$X59) -> 202607-52 | AA59: =IF(Inventory!A57="","",Inventory!A57) -> FD-DRY-KTCN-1.5G-002
A60: 46226 | B60: Sale | C60: Shop | D60: PawfectBD Shop | E60: PAWF-260729-5B3A8 | F60: LT-MX-DCLP-5L-002 | G60: =IF($F60="","",IFERROR(VLOOKUP($F60,Inventory!$A:$B,2,FALSE),"")) -> Cat Litter Mix Flavor 5L DR. Clump | H60: 1 | I60: =IF($F60="","",IF($B60="Gift",0,J60-IF(K60="",0,K60))) -> 280 | J60: =IF($F60="","",IFERROR(VLOOKUP($F60,Inventory!$A:$K,11,FALSE),0)) -> 320 | K60: 40 | L60: =IF($F60="","",IF($B60="Return",-H60*I60,H60*I60)) -> 280 | M60: Paid | N60: =IF($F60="","",IFERROR(VLOOKUP($F60,Inventory!$A:$I,9,FALSE),0)) -> 220 | O60: =IF($F60="","",IF($B60="Return",-H60*N60,H60*N60)) -> 220 | P60: =IF($F60="","",L60-O60) -> 60 | R60: =IF($E60="","",IF(COUNTIF($E$7:$E60,$E60)>1,"",IFERROR(VLOOKUP($E60,Orders!$A:$I,8,FALSE),""))) | S60: =IF($E60="","",IF(COUNTIF($E$7:$E60,$E60)>1,"",IFERROR(VLOOKUP($E60,Orders!$A:$I,9,FALSE),""))) | T60: =IF($F60="","",P60+IF(R60="",0,R60)-IF(S60="",0,S60)) -> 60 | U60: =IF($F60="","",IF($E60="",T60,SUMIF(Sales!$E$7:$E$1506,$E60,Sales!$T$7:$T$1506))) -> 519.16107 | V60: =IF(OR($C60<>"Online",$E60=""),"",IF(COUNTIF($E$7:$E60,$E60)>1,"",COUNT($V$6:V59)+1)) | W60: {=IF($V60="","",SUMPRODUCT((Sales!$V$7:$V$1506<>"")*(Sales!$E$7:$E$1506<$E60))+1)} | X60: =IF($A60="","",COUNTIFS($A$7:$A60,">="&EOMONTH($A60,-1)+1,$A$7:$A60,"<="&EOMONTH($A60,0))) -> 53 | Y60: =IF($A60="","",TEXT($A60,"yyyymm")&"-"&$X60) -> 202607-53 | AA60: =IF(Inventory!A58="","",Inventory!A58) -> FD-DRY-SMHRT-1.2KG-002
A61: 46227 | B61: Sale | C61: Shop | D61: PawfectBD Shop | F61: AC-CMB-001 | G61: =IF($F61="","",IFERROR(VLOOKUP($F61,Inventory!$A:$B,2,FALSE),"")) -> Pet Comb One Side | H61: 1 | I61: =IF($F61="","",IF($B61="Gift",0,J61-IF(K61="",0,K61))) -> 180 | J61: =IF($F61="","",IFERROR(VLOOKUP($F61,Inventory!$A:$K,11,FALSE),0)) -> 200 | K61: 20 | L61: =IF($F61="","",IF($B61="Return",-H61*I61,H61*I61)) -> 180 | M61: Paid | N61: =IF($F61="","",IFERROR(VLOOKUP($F61,Inventory!$A:$I,9,FALSE),0)) -> 130 | O61: =IF($F61="","",IF($B61="Return",-H61*N61,H61*N61)) -> 130 | P61: =IF($F61="","",L61-O61) -> 50 | R61: =IF($E61="","",IF(COUNTIF($E$7:$E61,$E61)>1,"",IFERROR(VLOOKUP($E61,Orders!$A:$I,8,FALSE),""))) | S61: =IF($E61="","",IF(COUNTIF($E$7:$E61,$E61)>1,"",IFERROR(VLOOKUP($E61,Orders!$A:$I,9,FALSE),""))) | T61: =IF($F61="","",P61+IF(R61="",0,R61)-IF(S61="",0,S61)) -> 50 | U61: =IF($F61="","",IF($E61="",T61,SUMIF(Sales!$E$7:$E$1506,$E61,Sales!$T$7:$T$1506))) -> 50 | V61: =IF(OR($C61<>"Online",$E61=""),"",IF(COUNTIF($E$7:$E61,$E61)>1,"",COUNT($V$6:V60)+1)) | W61: {=IF($V61="","",SUMPRODUCT((Sales!$V$7:$V$1506<>"")*(Sales!$E$7:$E$1506<$E61))+1)} | X61: =IF($A61="","",COUNTIFS($A$7:$A61,">="&EOMONTH($A61,-1)+1,$A$7:$A61,"<="&EOMONTH($A61,0))) -> 54 | Y61: =IF($A61="","",TEXT($A61,"yyyymm")&"-"&$X61) -> 202607-54 | AA61: =IF(Inventory!A59="","",Inventory!A59) -> AC-CF-001
A62: 46227 | B62: Sale | C62: Shop | D62: PawfectBD Shop | F62: TR-CRMY-15G-001 | G62: =IF($F62="","",IFERROR(VLOOKUP($F62,Inventory!$A:$B,2,FALSE),"")) -> Creamy Treat 15G (Purry & Hyper Paws) | H62: 1 | I62: =IF($F62="","",IF($B62="Gift",0,J62-IF(K62="",0,K62))) -> 20 | J62: =IF($F62="","",IFERROR(VLOOKUP($F62,Inventory!$A:$K,11,FALSE),0)) -> 20 | L62: =IF($F62="","",IF($B62="Return",-H62*I62,H62*I62)) -> 20 | M62: Paid | N62: =IF($F62="","",IFERROR(VLOOKUP($F62,Inventory!$A:$I,9,FALSE),0)) -> 8.1474119 | O62: =IF($F62="","",IF($B62="Return",-H62*N62,H62*N62)) -> 8.1474119 | P62: =IF($F62="","",L62-O62) -> 11.852588 | R62: =IF($E62="","",IF(COUNTIF($E$7:$E62,$E62)>1,"",IFERROR(VLOOKUP($E62,Orders!$A:$I,8,FALSE),""))) | S62: =IF($E62="","",IF(COUNTIF($E$7:$E62,$E62)>1,"",IFERROR(VLOOKUP($E62,Orders!$A:$I,9,FALSE),""))) | T62: =IF($F62="","",P62+IF(R62="",0,R62)-IF(S62="",0,S62)) -> 11.852588 | U62: =IF($F62="","",IF($E62="",T62,SUMIF(Sales!$E$7:$E$1506,$E62,Sales!$T$7:$T$1506))) -> 11.852588 | V62: =IF(OR($C62<>"Online",$E62=""),"",IF(COUNTIF($E$7:$E62,$E62)>1,"",COUNT($V$6:V61)+1)) | W62: {=IF($V62="","",SUMPRODUCT((Sales!$V$7:$V$1506<>"")*(Sales!$E$7:$E$1506<$E62))+1)} | X62: =IF($A62="","",COUNTIFS($A$7:$A62,">="&EOMONTH($A62,-1)+1,$A$7:$A62,"<="&EOMONTH($A62,0))) -> 55 | Y62: =IF($A62="","",TEXT($A62,"yyyymm")&"-"&$X62) -> 202607-55 | AA62: =IF(Inventory!A60="","",Inventory!A60) -> AC-CS-002
A63: 46227 | B63: Gift | C63: Shop | D63: PawfectBD Shop | F63: TR-CRMY-15G-001 | G63: =IF($F63="","",IFERROR(VLOOKUP($F63,Inventory!$A:$B,2,FALSE),"")) -> Creamy Treat 15G (Purry & Hyper Paws) | H63: 2 | I63: =IF($F63="","",IF($B63="Gift",0,J63-IF(K63="",0,K63))) -> 0 | J63: =IF($F63="","",IFERROR(VLOOKUP($F63,Inventory!$A:$K,11,FALSE),0)) -> 20 | K63: 20 | L63: =IF($F63="","",IF($B63="Return",-H63*I63,H63*I63)) -> 0 | M63: Paid | N63: =IF($F63="","",IFERROR(VLOOKUP($F63,Inventory!$A:$I,9,FALSE),0)) -> 8.1474119 | O63: =IF($F63="","",IF($B63="Return",-H63*N63,H63*N63)) -> 16.294824 | P63: =IF($F63="","",L63-O63) -> -16.294824 | R63: =IF($E63="","",IF(COUNTIF($E$7:$E63,$E63)>1,"",IFERROR(VLOOKUP($E63,Orders!$A:$I,8,FALSE),""))) | S63: =IF($E63="","",IF(COUNTIF($E$7:$E63,$E63)>1,"",IFERROR(VLOOKUP($E63,Orders!$A:$I,9,FALSE),""))) | T63: =IF($F63="","",P63+IF(R63="",0,R63)-IF(S63="",0,S63)) -> -16.294824 | U63: =IF($F63="","",IF($E63="",T63,SUMIF(Sales!$E$7:$E$1506,$E63,Sales!$T$7:$T$1506))) -> -16.294824 | V63: =IF(OR($C63<>"Online",$E63=""),"",IF(COUNTIF($E$7:$E63,$E63)>1,"",COUNT($V$6:V62)+1)) | W63: {=IF($V63="","",SUMPRODUCT((Sales!$V$7:$V$1506<>"")*(Sales!$E$7:$E$1506<$E63))+1)} | X63: =IF($A63="","",COUNTIFS($A$7:$A63,">="&EOMONTH($A63,-1)+1,$A$7:$A63,"<="&EOMONTH($A63,0))) -> 56 | Y63: =IF($A63="","",TEXT($A63,"yyyymm")&"-"&$X63) -> 202607-56 | AA63: =IF(Inventory!A61="","",Inventory!A61) -> FD-DRY-ZOI-1KG-001
A64: 46227 | B64: Sale | C64: Shop | D64: PawfectBD Shop | F64: FD-DRY-SMHRT-480G-002 | G64: =IF($F64="","",IFERROR(VLOOKUP($F64,Inventory!$A:$B,2,FALSE),"")) -> Smart Heart Adult Cat Food Chicken & Tuna [480G] | H64: 1 | I64: =IF($F64="","",IF($B64="Gift",0,J64-IF(K64="",0,K64))) -> 350 | J64: =IF($F64="","",IFERROR(VLOOKUP($F64,Inventory!$A:$K,11,FALSE),0)) -> 380 | K64: 30 | L64: =IF($F64="","",IF($B64="Return",-H64*I64,H64*I64)) -> 350 | M64: Paid | N64: =IF($F64="","",IFERROR(VLOOKUP($F64,Inventory!$A:$I,9,FALSE),0)) -> 290.26316 | O64: =IF($F64="","",IF($B64="Return",-H64*N64,H64*N64)) -> 290.26316 | P64: =IF($F64="","",L64-O64) -> 59.736842 | R64: =IF($E64="","",IF(COUNTIF($E$7:$E64,$E64)>1,"",IFERROR(VLOOKUP($E64,Orders!$A:$I,8,FALSE),""))) | S64: =IF($E64="","",IF(COUNTIF($E$7:$E64,$E64)>1,"",IFERROR(VLOOKUP($E64,Orders!$A:$I,9,FALSE),""))) | T64: =IF($F64="","",P64+IF(R64="",0,R64)-IF(S64="",0,S64)) -> 59.736842 | U64: =IF($F64="","",IF($E64="",T64,SUMIF(Sales!$E$7:$E$1506,$E64,Sales!$T$7:$T$1506))) -> 59.736842 | V64: =IF(OR($C64<>"Online",$E64=""),"",IF(COUNTIF($E$7:$E64,$E64)>1,"",COUNT($V$6:V63)+1)) | W64: {=IF($V64="","",SUMPRODUCT((Sales!$V$7:$V$1506<>"")*(Sales!$E$7:$E$1506<$E64))+1)} | X64: =IF($A64="","",COUNTIFS($A$7:$A64,">="&EOMONTH($A64,-1)+1,$A$7:$A64,"<="&EOMONTH($A64,0))) -> 57 | Y64: =IF($A64="","",TEXT($A64,"yyyymm")&"-"&$X64) -> 202607-57 | AA64: =IF(Inventory!A62="","",Inventory!A62) -> PO-WET-NK-70G-004
A65: 46227 | B65: Sale | C65: Shop | D65: PawfectBD Shop | F65: PO-WET-SMHRT-TWC-85G-001 | G65: =IF($F65="","",IFERROR(VLOOKUP($F65,Inventory!$A:$B,2,FALSE),"")) -> Smart Heart Pouch Tuna With Chicken in Jelly | H65: 5 | I65: =IF($F65="","",IF($B65="Gift",0,J65-IF(K65="",0,K65))) -> 90 | J65: =IF($F65="","",IFERROR(VLOOKUP($F65,Inventory!$A:$K,11,FALSE),0)) -> 95 | K65: 5 | L65: =IF($F65="","",IF($B65="Return",-H65*I65,H65*I65)) -> 450 | M65: Paid | N65: =IF($F65="","",IFERROR(VLOOKUP($F65,Inventory!$A:$I,9,FALSE),0)) -> 71.904762 | O65: =IF($F65="","",IF($B65="Return",-H65*N65,H65*N65)) -> 359.52381 | P65: =IF($F65="","",L65-O65) -> 90.47619 | R65: =IF($E65="","",IF(COUNTIF($E$7:$E65,$E65)>1,"",IFERROR(VLOOKUP($E65,Orders!$A:$I,8,FALSE),""))) | S65: =IF($E65="","",IF(COUNTIF($E$7:$E65,$E65)>1,"",IFERROR(VLOOKUP($E65,Orders!$A:$I,9,FALSE),""))) | T65: =IF($F65="","",P65+IF(R65="",0,R65)-IF(S65="",0,S65)) -> 90.47619 | U65: =IF($F65="","",IF($E65="",T65,SUMIF(Sales!$E$7:$E$1506,$E65,Sales!$T$7:$T$1506))) -> 90.47619 | V65: =IF(OR($C65<>"Online",$E65=""),"",IF(COUNTIF($E$7:$E65,$E65)>1,"",COUNT($V$6:V64)+1)) | W65: {=IF($V65="","",SUMPRODUCT((Sales!$V$7:$V$1506<>"")*(Sales!$E$7:$E$1506<$E65))+1)} | X65: =IF($A65="","",COUNTIFS($A$7:$A65,">="&EOMONTH($A65,-1)+1,$A$7:$A65,"<="&EOMONTH($A65,0))) -> 58 | Y65: =IF($A65="","",TEXT($A65,"yyyymm")&"-"&$X65) -> 202607-58 | AA65: =IF(Inventory!A63="","",Inventory!A63) -> FD-DRY-TRL-1KG-001
A66: 46227 | B66: Sale | C66: Shop | D66: PawfectBD Shop | F66: PO-TP-70G-001 | G66: =IF($F66="","",IFERROR(VLOOKUP($F66,Inventory!$A:$B,2,FALSE),"")) -> Taipet Chicken Tuna in Jelly | H66: 1 | I66: =IF($F66="","",IF($B66="Gift",0,J66-IF(K66="",0,K66))) -> 75 | J66: =IF($F66="","",IFERROR(VLOOKUP($F66,Inventory!$A:$K,11,FALSE),0)) -> 75 | L66: =IF($F66="","",IF($B66="Return",-H66*I66,H66*I66)) -> 75 | M66: Paid | N66: =IF($F66="","",IFERROR(VLOOKUP($F66,Inventory!$A:$I,9,FALSE),0)) -> 52 | O66: =IF($F66="","",IF($B66="Return",-H66*N66,H66*N66)) -> 52 | P66: =IF($F66="","",L66-O66) -> 23 | R66: =IF($E66="","",IF(COUNTIF($E$7:$E66,$E66)>1,"",IFERROR(VLOOKUP($E66,Orders!$A:$I,8,FALSE),""))) | S66: =IF($E66="","",IF(COUNTIF($E$7:$E66,$E66)>1,"",IFERROR(VLOOKUP($E66,Orders!$A:$I,9,FALSE),""))) | T66: =IF($F66="","",P66+IF(R66="",0,R66)-IF(S66="",0,S66)) -> 23 | U66: =IF($F66="","",IF($E66="",T66,SUMIF(Sales!$E$7:$E$1506,$E66,Sales!$T$7:$T$1506))) -> 23 | V66: =IF(OR($C66<>"Online",$E66=""),"",IF(COUNTIF($E$7:$E66,$E66)>1,"",COUNT($V$6:V65)+1)) | W66: {=IF($V66="","",SUMPRODUCT((Sales!$V$7:$V$1506<>"")*(Sales!$E$7:$E$1506<$E66))+1)} | X66: =IF($A66="","",COUNTIFS($A$7:$A66,">="&EOMONTH($A66,-1)+1,$A$7:$A66,"<="&EOMONTH($A66,0))) -> 59 | Y66: =IF($A66="","",TEXT($A66,"yyyymm")&"-"&$X66) -> 202607-59 | AA66: =IF(Inventory!A64="","",Inventory!A64) -> FD-DRY-SMHRT-10KG-001
A67: 46227 | B67: Sale | C67: Shop | D67: PawfectBD Shop | F67: AC-CB-001 | G67: =IF($F67="","",IFERROR(VLOOKUP($F67,Inventory!$A:$B,2,FALSE),"")) -> Cat Belt | H67: 1 | I67: =IF($F67="","",IF($B67="Gift",0,J67-IF(K67="",0,K67))) -> 60 | J67: =IF($F67="","",IFERROR(VLOOKUP($F67,Inventory!$A:$K,11,FALSE),0)) -> 60 | L67: =IF($F67="","",IF($B67="Return",-H67*I67,H67*I67)) -> 60 | M67: Paid | N67: =IF($F67="","",IFERROR(VLOOKUP($F67,Inventory!$A:$I,9,FALSE),0)) -> 29.351351 | O67: =IF($F67="","",IF($B67="Return",-H67*N67,H67*N67)) -> 29.351351 | P67: =IF($F67="","",L67-O67) -> 30.648649 | R67: =IF($E67="","",IF(COUNTIF($E$7:$E67,$E67)>1,"",IFERROR(VLOOKUP($E67,Orders!$A:$I,8,FALSE),""))) | S67: =IF($E67="","",IF(COUNTIF($E$7:$E67,$E67)>1,"",IFERROR(VLOOKUP($E67,Orders!$A:$I,9,FALSE),""))) | T67: =IF($F67="","",P67+IF(R67="",0,R67)-IF(S67="",0,S67)) -> 30.648649 | U67: =IF($F67="","",IF($E67="",T67,SUMIF(Sales!$E$7:$E$1506,$E67,Sales!$T$7:$T$1506))) -> 30.648649 | V67: =IF(OR($C67<>"Online",$E67=""),"",IF(COUNTIF($E$7:$E67,$E67)>1,"",COUNT($V$6:V66)+1)) | W67: {=IF($V67="","",SUMPRODUCT((Sales!$V$7:$V$1506<>"")*(Sales!$E$7:$E$1506<$E67))+1)} | X67: =IF($A67="","",COUNTIFS($A$7:$A67,">="&EOMONTH($A67,-1)+1,$A$7:$A67,"<="&EOMONTH($A67,0))) -> 60 | Y67: =IF($A67="","",TEXT($A67,"yyyymm")&"-"&$X67) -> 202607-60 | AA67: =IF(Inventory!A65="","",Inventory!A65) -> AC-CB-HRNS-001
A68: 46227 | B68: Sale | C68: Shop | D68: PawfectBD Shop | F68: FD-DRY-KVF-MV-500G-001 | G68: =IF($F68="","",IFERROR(VLOOKUP($F68,Inventory!$A:$B,2,FALSE),"")) -> Kaniva Fusion Multiviamins Chicken & Pumpkin 500gm | H68: 1 | I68: =IF($F68="","",IF($B68="Gift",0,J68-IF(K68="",0,K68))) -> 620 | J68: =IF($F68="","",IFERROR(VLOOKUP($F68,Inventory!$A:$K,11,FALSE),0)) -> 650 | K68: 30 | L68: =IF($F68="","",IF($B68="Return",-H68*I68,H68*I68)) -> 620 | M68: Paid | N68: =IF($F68="","",IFERROR(VLOOKUP($F68,Inventory!$A:$I,9,FALSE),0)) -> 507 | O68: =IF($F68="","",IF($B68="Return",-H68*N68,H68*N68)) -> 507 | P68: =IF($F68="","",L68-O68) -> 113 | R68: =IF($E68="","",IF(COUNTIF($E$7:$E68,$E68)>1,"",IFERROR(VLOOKUP($E68,Orders!$A:$I,8,FALSE),""))) | S68: =IF($E68="","",IF(COUNTIF($E$7:$E68,$E68)>1,"",IFERROR(VLOOKUP($E68,Orders!$A:$I,9,FALSE),""))) | T68: =IF($F68="","",P68+IF(R68="",0,R68)-IF(S68="",0,S68)) -> 113 | U68: =IF($F68="","",IF($E68="",T68,SUMIF(Sales!$E$7:$E$1506,$E68,Sales!$T$7:$T$1506))) -> 113 | V68: =IF(OR($C68<>"Online",$E68=""),"",IF(COUNTIF($E$7:$E68,$E68)>1,"",COUNT($V$6:V67)+1)) | W68: {=IF($V68="","",SUMPRODUCT((Sales!$V$7:$V$1506<>"")*(Sales!$E$7:$E$1506<$E68))+1)} | X68: =IF($A68="","",COUNTIFS($A$7:$A68,">="&EOMONTH($A68,-1)+1,$A$7:$A68,"<="&EOMONTH($A68,0))) -> 61 | Y68: =IF($A68="","",TEXT($A68,"yyyymm")&"-"&$X68) -> 202607-61 | AA68: =IF(Inventory!A66="","",Inventory!A66) -> AC-CB-HRNS-002
A69: 46227 | B69: Sale | C69: Shop | D69: PawfectBD Shop | F69: LT-MX-DCLP-5L-002 | G69: =IF($F69="","",IFERROR(VLOOKUP($F69,Inventory!$A:$B,2,FALSE),"")) -> Cat Litter Mix Flavor 5L DR. Clump | H69: 1 | I69: =IF($F69="","",IF($B69="Gift",0,J69-IF(K69="",0,K69))) -> 300 | J69: =IF($F69="","",IFERROR(VLOOKUP($F69,Inventory!$A:$K,11,FALSE),0)) -> 320 | K69: 20 | L69: =IF($F69="","",IF($B69="Return",-H69*I69,H69*I69)) -> 300 | M69: Paid | N69: =IF($F69="","",IFERROR(VLOOKUP($F69,Inventory!$A:$I,9,FALSE),0)) -> 220 | O69: =IF($F69="","",IF($B69="Return",-H69*N69,H69*N69)) -> 220 | P69: =IF($F69="","",L69-O69) -> 80 | R69: =IF($E69="","",IF(COUNTIF($E$7:$E69,$E69)>1,"",IFERROR(VLOOKUP($E69,Orders!$A:$I,8,FALSE),""))) | S69: =IF($E69="","",IF(COUNTIF($E$7:$E69,$E69)>1,"",IFERROR(VLOOKUP($E69,Orders!$A:$I,9,FALSE),""))) | T69: =IF($F69="","",P69+IF(R69="",0,R69)-IF(S69="",0,S69)) -> 80 | U69: =IF($F69="","",IF($E69="",T69,SUMIF(Sales!$E$7:$E$1506,$E69,Sales!$T$7:$T$1506))) -> 80 | V69: =IF(OR($C69<>"Online",$E69=""),"",IF(COUNTIF($E$7:$E69,$E69)>1,"",COUNT($V$6:V68)+1)) | W69: {=IF($V69="","",SUMPRODUCT((Sales!$V$7:$V$1506<>"")*(Sales!$E$7:$E$1506<$E69))+1)} | X69: =IF($A69="","",COUNTIFS($A$7:$A69,">="&EOMONTH($A69,-1)+1,$A$7:$A69,"<="&EOMONTH($A69,0))) -> 62 | Y69: =IF($A69="","",TEXT($A69,"yyyymm")&"-"&$X69) -> 202607-62 | AA69: =IF(Inventory!A67="","",Inventory!A67) -> AC-CMB-001
A70: 46227 | B70: Sale | C70: Shop | D70: PawfectBD Shop | F70: PO-WET-NK-70G-001 | G70: =IF($F70="","",IFERROR(VLOOKUP($F70,Inventory!$A:$B,2,FALSE),"")) -> Nekko Pouch Tuna in Jelly | H70: 2 | I70: =IF($F70="","",IF($B70="Gift",0,J70-IF(K70="",0,K70))) -> 82.5 | J70: =IF($F70="","",IFERROR(VLOOKUP($F70,Inventory!$A:$K,11,FALSE),0)) -> 90 | K70: 7.5 | L70: =IF($F70="","",IF($B70="Return",-H70*I70,H70*I70)) -> 165 | M70: Paid | N70: =IF($F70="","",IFERROR(VLOOKUP($F70,Inventory!$A:$I,9,FALSE),0)) -> 65.172414 | O70: =IF($F70="","",IF($B70="Return",-H70*N70,H70*N70)) -> 130.34483 | P70: =IF($F70="","",L70-O70) -> 34.655172 | R70: =IF($E70="","",IF(COUNTIF($E$7:$E70,$E70)>1,"",IFERROR(VLOOKUP($E70,Orders!$A:$I,8,FALSE),""))) | S70: =IF($E70="","",IF(COUNTIF($E$7:$E70,$E70)>1,"",IFERROR(VLOOKUP($E70,Orders!$A:$I,9,FALSE),""))) | T70: =IF($F70="","",P70+IF(R70="",0,R70)-IF(S70="",0,S70)) -> 34.655172 | U70: =IF($F70="","",IF($E70="",T70,SUMIF(Sales!$E$7:$E$1506,$E70,Sales!$T$7:$T$1506))) -> 34.655172 | V70: =IF(OR($C70<>"Online",$E70=""),"",IF(COUNTIF($E$7:$E70,$E70)>1,"",COUNT($V$6:V69)+1)) | W70: {=IF($V70="","",SUMPRODUCT((Sales!$V$7:$V$1506<>"")*(Sales!$E$7:$E$1506<$E70))+1)} | X70: =IF($A70="","",COUNTIFS($A$7:$A70,">="&EOMONTH($A70,-1)+1,$A$7:$A70,"<="&EOMONTH($A70,0))) -> 63 | Y70: =IF($A70="","",TEXT($A70,"yyyymm")&"-"&$X70) -> 202607-63 | AA70: =IF(Inventory!A68="","",Inventory!A68) -> FD-DRY-SMHRT-1.2KG-003
A71: 46228 | B71: Sale | C71: Online | D71: From Facebook | E71: PAWF-260725-A2D5A | F71: FD-DRY-CHNK-OCFCK-1.5KG-001 | G71: =IF($F71="","",IFERROR(VLOOKUP($F71,Inventory!$A:$B,2,FALSE),"")) -> Chonk All ages Ocean Fish with Chicken | H71: 1 | I71: =IF($F71="","",IF($B71="Gift",0,J71-IF(K71="",0,K71))) -> 493 | J71: =IF($F71="","",IFERROR(VLOOKUP($F71,Inventory!$A:$K,11,FALSE),0)) -> 500 | K71: 7 | L71: =IF($F71="","",IF($B71="Return",-H71*I71,H71*I71)) -> 493 | M71: Paid | N71: =IF($F71="","",IFERROR(VLOOKUP($F71,Inventory!$A:$I,9,FALSE),0)) -> 400 | O71: =IF($F71="","",IF($B71="Return",-H71*N71,H71*N71)) -> 400 | P71: =IF($F71="","",L71-O71) -> 93 | R71: =IF($E71="","",IF(COUNTIF($E$7:$E71,$E71)>1,"",IFERROR(VLOOKUP($E71,Orders!$A:$I,8,FALSE),""))) -> 120 | S71: =IF($E71="","",IF(COUNTIF($E$7:$E71,$E71)>1,"",IFERROR(VLOOKUP($E71,Orders!$A:$I,9,FALSE),""))) -> 125 | T71: =IF($F71="","",P71+IF(R71="",0,R71)-IF(S71="",0,S71)) -> 88 | U71: =IF($F71="","",IF($E71="",T71,SUMIF(Sales!$E$7:$E$1506,$E71,Sales!$T$7:$T$1506))) -> 435 | V71: =IF(OR($C71<>"Online",$E71=""),"",IF(COUNTIF($E$7:$E71,$E71)>1,"",COUNT($V$6:V70)+1)) -> 4 | W71: {=IF($V71="","",SUMPRODUCT((Sales!$V$7:$V$1506<>"")*(Sales!$E$7:$E$1506<$E71))+1)} -> 5 | X71: =IF($A71="","",COUNTIFS($A$7:$A71,">="&EOMONTH($A71,-1)+1,$A$7:$A71,"<="&EOMONTH($A71,0))) -> 64 | Y71: =IF($A71="","",TEXT($A71,"yyyymm")&"-"&$X71) -> 202607-64 | AA71: =IF(Inventory!A69="","",Inventory!A69) -> FD-DRY-DR-DOG-3-0001
A72: 46228 | B72: Sale | C72: Online | D72: From Facebook | E72: PAWF-260725-A2D5A | F72: FD-DRY-CHNK-CHKN-1.5KG-001 | G72: =IF($F72="","",IFERROR(VLOOKUP($F72,Inventory!$A:$B,2,FALSE),"")) -> Chonk All ages Chicken | H72: 2 | I72: =IF($F72="","",IF($B72="Gift",0,J72-IF(K72="",0,K72))) -> 496.5 | J72: =IF($F72="","",IFERROR(VLOOKUP($F72,Inventory!$A:$K,11,FALSE),0)) -> 500 | K72: 3.5 | L72: =IF($F72="","",IF($B72="Return",-H72*I72,H72*I72)) -> 993 | M72: Paid | N72: =IF($F72="","",IFERROR(VLOOKUP($F72,Inventory!$A:$I,9,FALSE),0)) -> 400 | O72: =IF($F72="","",IF($B72="Return",-H72*N72,H72*N72)) -> 800 | P72: =IF($F72="","",L72-O72) -> 193 | R72: =IF($E72="","",IF(COUNTIF($E$7:$E72,$E72)>1,"",IFERROR(VLOOKUP($E72,Orders!$A:$I,8,FALSE),""))) | S72: =IF($E72="","",IF(COUNTIF($E$7:$E72,$E72)>1,"",IFERROR(VLOOKUP($E72,Orders!$A:$I,9,FALSE),""))) | T72: =IF($F72="","",P72+IF(R72="",0,R72)-IF(S72="",0,S72)) -> 193 | U72: =IF($F72="","",IF($E72="",T72,SUMIF(Sales!$E$7:$E$1506,$E72,Sales!$T$7:$T$1506))) -> 435 | V72: =IF(OR($C72<>"Online",$E72=""),"",IF(COUNTIF($E$7:$E72,$E72)>1,"",COUNT($V$6:V71)+1)) | W72: {=IF($V72="","",SUMPRODUCT((Sales!$V$7:$V$1506<>"")*(Sales!$E$7:$E$1506<$E72))+1)} | X72: =IF($A72="","",COUNTIFS($A$7:$A72,">="&EOMONTH($A72,-1)+1,$A$7:$A72,"<="&EOMONTH($A72,0))) -> 65 | Y72: =IF($A72="","",TEXT($A72,"yyyymm")&"-"&$X72) -> 202607-65 | AA72: =IF(Inventory!A70="","",Inventory!A70) -> AC-CS-BAG-001
A73: 46228 | B73: Sale | C73: Online | D73: From Facebook | E73: PAWF-260725-A2D5A | F73: AC-SHAMP-002 | G73: =IF($F73="","",IFERROR(VLOOKUP($F73,Inventory!$A:$B,2,FALSE),"")) -> Bengal Flea & Tick Shampoo | H73: 1 | I73: =IF($F73="","",IF($B73="Gift",0,J73-IF(K73="",0,K73))) -> 394 | J73: =IF($F73="","",IFERROR(VLOOKUP($F73,Inventory!$A:$K,11,FALSE),0)) -> 400 | K73: 6 | L73: =IF($F73="","",IF($B73="Return",-H73*I73,H73*I73)) -> 394 | M73: Paid | N73: =IF($F73="","",IFERROR(VLOOKUP($F73,Inventory!$A:$I,9,FALSE),0)) -> 240 | O73: =IF($F73="","",IF($B73="Return",-H73*N73,H73*N73)) -> 240 | P73: =IF($F73="","",L73-O73) -> 154 | R73: =IF($E73="","",IF(COUNTIF($E$7:$E73,$E73)>1,"",IFERROR(VLOOKUP($E73,Orders!$A:$I,8,FALSE),""))) | S73: =IF($E73="","",IF(COUNTIF($E$7:$E73,$E73)>1,"",IFERROR(VLOOKUP($E73,Orders!$A:$I,9,FALSE),""))) | T73: =IF($F73="","",P73+IF(R73="",0,R73)-IF(S73="",0,S73)) -> 154 | U73: =IF($F73="","",IF($E73="",T73,SUMIF(Sales!$E$7:$E$1506,$E73,Sales!$T$7:$T$1506))) -> 435 | V73: =IF(OR($C73<>"Online",$E73=""),"",IF(COUNTIF($E$7:$E73,$E73)>1,"",COUNT($V$6:V72)+1)) | W73: {=IF($V73="","",SUMPRODUCT((Sales!$V$7:$V$1506<>"")*(Sales!$E$7:$E$1506<$E73))+1)} | X73: =IF($A73="","",COUNTIFS($A$7:$A73,">="&EOMONTH($A73,-1)+1,$A$7:$A73,"<="&EOMONTH($A73,0))) -> 66 | Y73: =IF($A73="","",TEXT($A73,"yyyymm")&"-"&$X73) -> 202607-66 | AA73: =IF(Inventory!A71="","",Inventory!A71) -> PO-TP-70G-001
A74: 46228 | B74: Sale | C74: Online | D74: From Facebook | E74: PAWF-260723-EC10A | F74: FD-DRY-CHNK-CHKN-1.5KG-001 | G74: =IF($F74="","",IFERROR(VLOOKUP($F74,Inventory!$A:$B,2,FALSE),"")) -> Chonk All ages Chicken | H74: 1 | I74: =IF($F74="","",IF($B74="Gift",0,J74-IF(K74="",0,K74))) -> 499 | J74: =IF($F74="","",IFERROR(VLOOKUP($F74,Inventory!$A:$K,11,FALSE),0)) -> 500 | K74: 1 | L74: =IF($F74="","",IF($B74="Return",-H74*I74,H74*I74)) -> 499 | M74: Paid | N74: =IF($F74="","",IFERROR(VLOOKUP($F74,Inventory!$A:$I,9,FALSE),0)) -> 400 | O74: =IF($F74="","",IF($B74="Return",-H74*N74,H74*N74)) -> 400 | P74: =IF($F74="","",L74-O74) -> 99 | R74: =IF($E74="","",IF(COUNTIF($E$7:$E74,$E74)>1,"",IFERROR(VLOOKUP($E74,Orders!$A:$I,8,FALSE),""))) -> 150 | S74: =IF($E74="","",IF(COUNTIF($E$7:$E74,$E74)>1,"",IFERROR(VLOOKUP($E74,Orders!$A:$I,9,FALSE),""))) -> 310 | T74: =IF($F74="","",P74+IF(R74="",0,R74)-IF(S74="",0,S74)) -> -61 | U74: =IF($F74="","",IF($E74="",T74,SUMIF(Sales!$E$7:$E$1506,$E74,Sales!$T$7:$T$1506))) -> 208 | V74: =IF(OR($C74<>"Online",$E74=""),"",IF(COUNTIF($E$7:$E74,$E74)>1,"",COUNT($V$6:V73)+1)) -> 5 | W74: {=IF($V74="","",SUMPRODUCT((Sales!$V$7:$V$1506<>"")*(Sales!$E$7:$E$1506<$E74))+1)} -> 4 | X74: =IF($A74="","",COUNTIFS($A$7:$A74,">="&EOMONTH($A74,-1)+1,$A$7:$A74,"<="&EOMONTH($A74,0))) -> 67 | Y74: =IF($A74="","",TEXT($A74,"yyyymm")&"-"&$X74) -> 202607-67 | AA74: =IF(Inventory!A72="","",Inventory!A72) -> PO-TP-70G-002
A75: 46228 | B75: Sale | C75: Online | D75: From Facebook | E75: PAWF-260723-EC10A | F75: AC-PNC-SM-001 | G75: =IF($F75="","",IFERROR(VLOOKUP($F75,Inventory!$A:$B,2,FALSE),"")) -> Pet Nail Clippers Small | H75: 1 | I75: =IF($F75="","",IF($B75="Gift",0,J75-IF(K75="",0,K75))) -> 160 | J75: =IF($F75="","",IFERROR(VLOOKUP($F75,Inventory!$A:$K,11,FALSE),0)) -> 180 | K75: 20 | L75: =IF($F75="","",IF($B75="Return",-H75*I75,H75*I75)) -> 160 | M75: Paid | N75: =IF($F75="","",IFERROR(VLOOKUP($F75,Inventory!$A:$I,9,FALSE),0)) -> 120 | O75: =IF($F75="","",IF($B75="Return",-H75*N75,H75*N75)) -> 120 | P75: =IF($F75="","",L75-O75) -> 40 | R75: =IF($E75="","",IF(COUNTIF($E$7:$E75,$E75)>1,"",IFERROR(VLOOKUP($E75,Orders!$A:$I,8,FALSE),""))) | S75: =IF($E75="","",IF(COUNTIF($E$7:$E75,$E75)>1,"",IFERROR(VLOOKUP($E75,Orders!$A:$I,9,FALSE),""))) | T75: =IF($F75="","",P75+IF(R75="",0,R75)-IF(S75="",0,S75)) -> 40 | U75: =IF($F75="","",IF($E75="",T75,SUMIF(Sales!$E$7:$E$1506,$E75,Sales!$T$7:$T$1506))) -> 208 | V75: =IF(OR($C75<>"Online",$E75=""),"",IF(COUNTIF($E$7:$E75,$E75)>1,"",COUNT($V$6:V74)+1)) | W75: {=IF($V75="","",SUMPRODUCT((Sales!$V$7:$V$1506<>"")*(Sales!$E$7:$E$1506<$E75))+1)} | X75: =IF($A75="","",COUNTIFS($A$7:$A75,">="&EOMONTH($A75,-1)+1,$A$7:$A75,"<="&EOMONTH($A75,0))) -> 68 | Y75: =IF($A75="","",TEXT($A75,"yyyymm")&"-"&$X75) -> 202607-68 | AA75: =IF(Inventory!A73="","",Inventory!A73) -> AC-BCR-001
A76: 46228 | B76: Sale | C76: Online | D76: From Facebook | E76: PAWF-260723-EC10A | F76: LT-LV-CZE-10L-001 | G76: =IF($F76="","",IFERROR(VLOOKUP($F76,Inventory!$A:$B,2,FALSE),"")) -> Cozie Cat Litter Lavender 10L | H76: 1 | I76: =IF($F76="","",IF($B76="Gift",0,J76-IF(K76="",0,K76))) -> 679 | J76: =IF($F76="","",IFERROR(VLOOKUP($F76,Inventory!$A:$K,11,FALSE),0)) -> 700 | K76: 21 | L76: =IF($F76="","",IF($B76="Return",-H76*I76,H76*I76)) -> 679 | M76: Paid | N76: =IF($F76="","",IFERROR(VLOOKUP($F76,Inventory!$A:$I,9,FALSE),0)) -> 450 | O76: =IF($F76="","",IF($B76="Return",-H76*N76,H76*N76)) -> 450 | P76: =IF($F76="","",L76-O76) -> 229 | R76: =IF($E76="","",IF(COUNTIF($E$7:$E76,$E76)>1,"",IFERROR(VLOOKUP($E76,Orders!$A:$I,8,FALSE),""))) | S76: =IF($E76="","",IF(COUNTIF($E$7:$E76,$E76)>1,"",IFERROR(VLOOKUP($E76,Orders!$A:$I,9,FALSE),""))) | T76: =IF($F76="","",P76+IF(R76="",0,R76)-IF(S76="",0,S76)) -> 229 | U76: =IF($F76="","",IF($E76="",T76,SUMIF(Sales!$E$7:$E$1506,$E76,Sales!$T$7:$T$1506))) -> 208 | V76: =IF(OR($C76<>"Online",$E76=""),"",IF(COUNTIF($E$7:$E76,$E76)>1,"",COUNT($V$6:V75)+1)) | W76: {=IF($V76="","",SUMPRODUCT((Sales!$V$7:$V$1506<>"")*(Sales!$E$7:$E$1506<$E76))+1)} | X76: =IF($A76="","",COUNTIFS($A$7:$A76,">="&EOMONTH($A76,-1)+1,$A$7:$A76,"<="&EOMONTH($A76,0))) -> 69 | Y76: =IF($A76="","",TEXT($A76,"yyyymm")&"-"&$X76) -> 202607-69 | AA76: =IF(Inventory!A74="","",Inventory!A74) -> CN-WAN-375G-001
A77: 46228 | B77: Sale | C77: Online | D77: From Facebook | F77: FD-DRY-SMHRT-450G-001 | G77: =IF($F77="","",IFERROR(VLOOKUP($F77,Inventory!$A:$B,2,FALSE),"")) -> Smart Heart Kitten Food Chicken, Fish, Egg & Milk 450gm | H77: 1 | I77: =IF($F77="","",IF($B77="Gift",0,J77-IF(K77="",0,K77))) -> 360 | J77: =IF($F77="","",IFERROR(VLOOKUP($F77,Inventory!$A:$K,11,FALSE),0)) -> 380 | K77: 20 | L77: =IF($F77="","",IF($B77="Return",-H77*I77,H77*I77)) -> 360 | M77: Paid | N77: =IF($F77="","",IFERROR(VLOOKUP($F77,Inventory!$A:$I,9,FALSE),0)) -> 290 | O77: =IF($F77="","",IF($B77="Return",-H77*N77,H77*N77)) -> 290 | P77: =IF($F77="","",L77-O77) -> 70 | R77: =IF($E77="","",IF(COUNTIF($E$7:$E77,$E77)>1,"",IFERROR(VLOOKUP($E77,Orders!$A:$I,8,FALSE),""))) | S77: =IF($E77="","",IF(COUNTIF($E$7:$E77,$E77)>1,"",IFERROR(VLOOKUP($E77,Orders!$A:$I,9,FALSE),""))) | T77: =IF($F77="","",P77+IF(R77="",0,R77)-IF(S77="",0,S77)) -> 70 | U77: =IF($F77="","",IF($E77="",T77,SUMIF(Sales!$E$7:$E$1506,$E77,Sales!$T$7:$T$1506))) -> 70 | V77: =IF(OR($C77<>"Online",$E77=""),"",IF(COUNTIF($E$7:$E77,$E77)>1,"",COUNT($V$6:V76)+1)) | W77: {=IF($V77="","",SUMPRODUCT((Sales!$V$7:$V$1506<>"")*(Sales!$E$7:$E$1506<$E77))+1)} | X77: =IF($A77="","",COUNTIFS($A$7:$A77,">="&EOMONTH($A77,-1)+1,$A$7:$A77,"<="&EOMONTH($A77,0))) -> 70 | Y77: =IF($A77="","",TEXT($A77,"yyyymm")&"-"&$X77) -> 202607-70 | AA77: =IF(Inventory!A75="","",Inventory!A75) -> CN-WAN-375G-002
A78: 46228 | B78: Sale | C78: Online | D78: From Facebook | F78: TR-CRMY-15G-001 | G78: =IF($F78="","",IFERROR(VLOOKUP($F78,Inventory!$A:$B,2,FALSE),"")) -> Creamy Treat 15G (Purry & Hyper Paws) | H78: 3 | I78: =IF($F78="","",IF($B78="Gift",0,J78-IF(K78="",0,K78))) -> 20 | J78: =IF($F78="","",IFERROR(VLOOKUP($F78,Inventory!$A:$K,11,FALSE),0)) -> 20 | L78: =IF($F78="","",IF($B78="Return",-H78*I78,H78*I78)) -> 60 | M78: Paid | N78: =IF($F78="","",IFERROR(VLOOKUP($F78,Inventory!$A:$I,9,FALSE),0)) -> 8.1474119 | O78: =IF($F78="","",IF($B78="Return",-H78*N78,H78*N78)) -> 24.442236 | P78: =IF($F78="","",L78-O78) -> 35.557764 | R78: =IF($E78="","",IF(COUNTIF($E$7:$E78,$E78)>1,"",IFERROR(VLOOKUP($E78,Orders!$A:$I,8,FALSE),""))) | S78: =IF($E78="","",IF(COUNTIF($E$7:$E78,$E78)>1,"",IFERROR(VLOOKUP($E78,Orders!$A:$I,9,FALSE),""))) | T78: =IF($F78="","",P78+IF(R78="",0,R78)-IF(S78="",0,S78)) -> 35.557764 | U78: =IF($F78="","",IF($E78="",T78,SUMIF(Sales!$E$7:$E$1506,$E78,Sales!$T$7:$T$1506))) -> 35.557764 | V78: =IF(OR($C78<>"Online",$E78=""),"",IF(COUNTIF($E$7:$E78,$E78)>1,"",COUNT($V$6:V77)+1)) | W78: {=IF($V78="","",SUMPRODUCT((Sales!$V$7:$V$1506<>"")*(Sales!$E$7:$E$1506<$E78))+1)} | X78: =IF($A78="","",COUNTIFS($A$7:$A78,">="&EOMONTH($A78,-1)+1,$A$7:$A78,"<="&EOMONTH($A78,0))) -> 71 | Y78: =IF($A78="","",TEXT($A78,"yyyymm")&"-"&$X78) -> 202607-71 | AA78: =IF(Inventory!A76="","",Inventory!A76) -> CN-PAW-400G-001
A79: 46228 | B79: Sale | C79: Shop | D79: PawfectBD Shop | F79: TR-CRMY-15G-001 | G79: =IF($F79="","",IFERROR(VLOOKUP($F79,Inventory!$A:$B,2,FALSE),"")) -> Creamy Treat 15G (Purry & Hyper Paws) | H79: 5 | I79: =IF($F79="","",IF($B79="Gift",0,J79-IF(K79="",0,K79))) -> 20 | J79: =IF($F79="","",IFERROR(VLOOKUP($F79,Inventory!$A:$K,11,FALSE),0)) -> 20 | L79: =IF($F79="","",IF($B79="Return",-H79*I79,H79*I79)) -> 100 | M79: Paid | N79: =IF($F79="","",IFERROR(VLOOKUP($F79,Inventory!$A:$I,9,FALSE),0)) -> 8.1474119 | O79: =IF($F79="","",IF($B79="Return",-H79*N79,H79*N79)) -> 40.737059 | P79: =IF($F79="","",L79-O79) -> 59.262941 | R79: =IF($E79="","",IF(COUNTIF($E$7:$E79,$E79)>1,"",IFERROR(VLOOKUP($E79,Orders!$A:$I,8,FALSE),""))) | S79: =IF($E79="","",IF(COUNTIF($E$7:$E79,$E79)>1,"",IFERROR(VLOOKUP($E79,Orders!$A:$I,9,FALSE),""))) | T79: =IF($F79="","",P79+IF(R79="",0,R79)-IF(S79="",0,S79)) -> 59.262941 | U79: =IF($F79="","",IF($E79="",T79,SUMIF(Sales!$E$7:$E$1506,$E79,Sales!$T$7:$T$1506))) -> 59.262941 | V79: =IF(OR($C79<>"Online",$E79=""),"",IF(COUNTIF($E$7:$E79,$E79)>1,"",COUNT($V$6:V78)+1)) | W79: {=IF($V79="","",SUMPRODUCT((Sales!$V$7:$V$1506<>"")*(Sales!$E$7:$E$1506<$E79))+1)} | X79: =IF($A79="","",COUNTIFS($A$7:$A79,">="&EOMONTH($A79,-1)+1,$A$7:$A79,"<="&EOMONTH($A79,0))) -> 72 | Y79: =IF($A79="","",TEXT($A79,"yyyymm")&"-"&$X79) -> 202607-72 | AA79: =IF(Inventory!A77="","",Inventory!A77) -> CN-PAW-400G-002
A80: 46228 | B80: Sale | C80: Online | D80: From Facebook | E80: PAWF-260725-A3949 | F80: FD-DRY-DR-DOG-3-0001 | G80: =IF($F80="","",IFERROR(VLOOKUP($F80,Inventory!$A:$B,2,FALSE),"")) -> Drools Puppy Dog Food Chicken & Egg 3kg | H80: 1 | I80: =IF($F80="","",IF($B80="Gift",0,J80-IF(K80="",0,K80))) -> 1400 | J80: =IF($F80="","",IFERROR(VLOOKUP($F80,Inventory!$A:$K,11,FALSE),0)) -> 1450 | K80: 50 | L80: =IF($F80="","",IF($B80="Return",-H80*I80,H80*I80)) -> 1400 | M80: Paid | N80: =IF($F80="","",IFERROR(VLOOKUP($F80,Inventory!$A:$I,9,FALSE),0)) -> 1050 | O80: =IF($F80="","",IF($B80="Return",-H80*N80,H80*N80)) -> 1050 | P80: =IF($F80="","",L80-O80) -> 350 | R80: =IF($E80="","",IF(COUNTIF($E$7:$E80,$E80)>1,"",IFERROR(VLOOKUP($E80,Orders!$A:$I,8,FALSE),""))) -> 150 | S80: =IF($E80="","",IF(COUNTIF($E$7:$E80,$E80)>1,"",IFERROR(VLOOKUP($E80,Orders!$A:$I,9,FALSE),""))) -> 94 | T80: =IF($F80="","",P80+IF(R80="",0,R80)-IF(S80="",0,S80)) -> 406 | U80: =IF($F80="","",IF($E80="",T80,SUMIF(Sales!$E$7:$E$1506,$E80,Sales!$T$7:$T$1506))) -> 406 | V80: =IF(OR($C80<>"Online",$E80=""),"",IF(COUNTIF($E$7:$E80,$E80)>1,"",COUNT($V$6:V79)+1)) -> 6 | W80: {=IF($V80="","",SUMPRODUCT((Sales!$V$7:$V$1506<>"")*(Sales!$E$7:$E$1506<$E80))+1)} -> 6 | X80: =IF($A80="","",COUNTIFS($A$7:$A80,">="&EOMONTH($A80,-1)+1,$A$7:$A80,"<="&EOMONTH($A80,0))) -> 73 | Y80: =IF($A80="","",TEXT($A80,"yyyymm")&"-"&$X80) -> 202607-73 | AA80: =IF(Inventory!A78="","",Inventory!A78) -> AC-BOWL-002
A81: 46228 | B81: Sale | C81: Shop | D81: PawfectBD Shop | F81: TR-CRMY-15G-001 | G81: =IF($F81="","",IFERROR(VLOOKUP($F81,Inventory!$A:$B,2,FALSE),"")) -> Creamy Treat 15G (Purry & Hyper Paws) | H81: 8 | I81: =IF($F81="","",IF($B81="Gift",0,J81-IF(K81="",0,K81))) -> 18.75 | J81: =IF($F81="","",IFERROR(VLOOKUP($F81,Inventory!$A:$K,11,FALSE),0)) -> 20 | K81: 1.25 | L81: =IF($F81="","",IF($B81="Return",-H81*I81,H81*I81)) -> 150 | M81: Paid | N81: =IF($F81="","",IFERROR(VLOOKUP($F81,Inventory!$A:$I,9,FALSE),0)) -> 8.1474119 | O81: =IF($F81="","",IF($B81="Return",-H81*N81,H81*N81)) -> 65.179295 | P81: =IF($F81="","",L81-O81) -> 84.820705 | R81: =IF($E81="","",IF(COUNTIF($E$7:$E81,$E81)>1,"",IFERROR(VLOOKUP($E81,Orders!$A:$I,8,FALSE),""))) | S81: =IF($E81="","",IF(COUNTIF($E$7:$E81,$E81)>1,"",IFERROR(VLOOKUP($E81,Orders!$A:$I,9,FALSE),""))) | T81: =IF($F81="","",P81+IF(R81="",0,R81)-IF(S81="",0,S81)) -> 84.820705 | U81: =IF($F81="","",IF($E81="",T81,SUMIF(Sales!$E$7:$E$1506,$E81,Sales!$T$7:$T$1506))) -> 84.820705 | V81: =IF(OR($C81<>"Online",$E81=""),"",IF(COUNTIF($E$7:$E81,$E81)>1,"",COUNT($V$6:V80)+1)) | W81: {=IF($V81="","",SUMPRODUCT((Sales!$V$7:$V$1506<>"")*(Sales!$E$7:$E$1506<$E81))+1)} | X81: =IF($A81="","",COUNTIFS($A$7:$A81,">="&EOMONTH($A81,-1)+1,$A$7:$A81,"<="&EOMONTH($A81,0))) -> 74 | Y81: =IF($A81="","",TEXT($A81,"yyyymm")&"-"&$X81) -> 202607-74 | AA81: =IF(Inventory!A79="","",Inventory!A79) -> PO-PP-85G-001
A82: 46228 | B82: Sale | C82: Shop | D82: PawfectBD Shop | F82: AC-CB-HRNS-001 | G82: =IF($F82="","",IFERROR(VLOOKUP($F82,Inventory!$A:$B,2,FALSE),"")) -> Cat Belt Harness | H82: 1 | I82: =IF($F82="","",IF($B82="Gift",0,J82-IF(K82="",0,K82))) -> 150 | J82: =IF($F82="","",IFERROR(VLOOKUP($F82,Inventory!$A:$K,11,FALSE),0)) -> 180 | K82: 30 | L82: =IF($F82="","",IF($B82="Return",-H82*I82,H82*I82)) -> 150 | M82: Paid | N82: =IF($F82="","",IFERROR(VLOOKUP($F82,Inventory!$A:$I,9,FALSE),0)) -> 90 | O82: =IF($F82="","",IF($B82="Return",-H82*N82,H82*N82)) -> 90 | P82: =IF($F82="","",L82-O82) -> 60 | R82: =IF($E82="","",IF(COUNTIF($E$7:$E82,$E82)>1,"",IFERROR(VLOOKUP($E82,Orders!$A:$I,8,FALSE),""))) | S82: =IF($E82="","",IF(COUNTIF($E$7:$E82,$E82)>1,"",IFERROR(VLOOKUP($E82,Orders!$A:$I,9,FALSE),""))) | T82: =IF($F82="","",P82+IF(R82="",0,R82)-IF(S82="",0,S82)) -> 60 | U82: =IF($F82="","",IF($E82="",T82,SUMIF(Sales!$E$7:$E$1506,$E82,Sales!$T$7:$T$1506))) -> 60 | V82: =IF(OR($C82<>"Online",$E82=""),"",IF(COUNTIF($E$7:$E82,$E82)>1,"",COUNT($V$6:V81)+1)) | W82: {=IF($V82="","",SUMPRODUCT((Sales!$V$7:$V$1506<>"")*(Sales!$E$7:$E$1506<$E82))+1)} | X82: =IF($A82="","",COUNTIFS($A$7:$A82,">="&EOMONTH($A82,-1)+1,$A$7:$A82,"<="&EOMONTH($A82,0))) -> 75 | Y82: =IF($A82="","",TEXT($A82,"yyyymm")&"-"&$X82) -> 202607-75 | AA82: =IF(Inventory!A80="","",Inventory!A80) -> PO-PP-85G-002
A83: 46228 | B83: Sale | C83: Shop | D83: PawfectBD Shop | F83: AC-CTOY-001 | G83: =IF($F83="","",IFERROR(VLOOKUP($F83,Inventory!$A:$B,2,FALSE),"")) -> Wind up Mouse Toy | H83: 1 | I83: =IF($F83="","",IF($B83="Gift",0,J83-IF(K83="",0,K83))) -> 250 | J83: =IF($F83="","",IFERROR(VLOOKUP($F83,Inventory!$A:$K,11,FALSE),0)) -> 250 | L83: =IF($F83="","",IF($B83="Return",-H83*I83,H83*I83)) -> 250 | M83: Paid | N83: =IF($F83="","",IFERROR(VLOOKUP($F83,Inventory!$A:$I,9,FALSE),0)) -> 160 | O83: =IF($F83="","",IF($B83="Return",-H83*N83,H83*N83)) -> 160 | P83: =IF($F83="","",L83-O83) -> 90 | R83: =IF($E83="","",IF(COUNTIF($E$7:$E83,$E83)>1,"",IFERROR(VLOOKUP($E83,Orders!$A:$I,8,FALSE),""))) | S83: =IF($E83="","",IF(COUNTIF($E$7:$E83,$E83)>1,"",IFERROR(VLOOKUP($E83,Orders!$A:$I,9,FALSE),""))) | T83: =IF($F83="","",P83+IF(R83="",0,R83)-IF(S83="",0,S83)) -> 90 | U83: =IF($F83="","",IF($E83="",T83,SUMIF(Sales!$E$7:$E$1506,$E83,Sales!$T$7:$T$1506))) -> 90 | V83: =IF(OR($C83<>"Online",$E83=""),"",IF(COUNTIF($E$7:$E83,$E83)>1,"",COUNT($V$6:V82)+1)) | W83: {=IF($V83="","",SUMPRODUCT((Sales!$V$7:$V$1506<>"")*(Sales!$E$7:$E$1506<$E83))+1)} | X83: =IF($A83="","",COUNTIFS($A$7:$A83,">="&EOMONTH($A83,-1)+1,$A$7:$A83,"<="&EOMONTH($A83,0))) -> 76 | Y83: =IF($A83="","",TEXT($A83,"yyyymm")&"-"&$X83) -> 202607-76 | AA83: =IF(Inventory!A81="","",Inventory!A81) -> PO-PP-100G-001
A84: 46228 | B84: Sale | C84: Shop | D84: PawfectBD Shop | F84: LT-LM-CZE-5L-001 | G84: =IF($F84="","",IFERROR(VLOOKUP($F84,Inventory!$A:$B,2,FALSE),"")) -> Cozie Cat Litter Lemon 5L | H84: 1 | I84: =IF($F84="","",IF($B84="Gift",0,J84-IF(K84="",0,K84))) -> 330 | J84: =IF($F84="","",IFERROR(VLOOKUP($F84,Inventory!$A:$K,11,FALSE),0)) -> 370 | K84: 40 | L84: =IF($F84="","",IF($B84="Return",-H84*I84,H84*I84)) -> 330 | M84: Paid | N84: =IF($F84="","",IFERROR(VLOOKUP($F84,Inventory!$A:$I,9,FALSE),0)) -> 230 | O84: =IF($F84="","",IF($B84="Return",-H84*N84,H84*N84)) -> 230 | P84: =IF($F84="","",L84-O84) -> 100 | R84: =IF($E84="","",IF(COUNTIF($E$7:$E84,$E84)>1,"",IFERROR(VLOOKUP($E84,Orders!$A:$I,8,FALSE),""))) | S84: =IF($E84="","",IF(COUNTIF($E$7:$E84,$E84)>1,"",IFERROR(VLOOKUP($E84,Orders!$A:$I,9,FALSE),""))) | T84: =IF($F84="","",P84+IF(R84="",0,R84)-IF(S84="",0,S84)) -> 100 | U84: =IF($F84="","",IF($E84="",T84,SUMIF(Sales!$E$7:$E$1506,$E84,Sales!$T$7:$T$1506))) -> 100 | V84: =IF(OR($C84<>"Online",$E84=""),"",IF(COUNTIF($E$7:$E84,$E84)>1,"",COUNT($V$6:V83)+1)) | W84: {=IF($V84="","",SUMPRODUCT((Sales!$V$7:$V$1506<>"")*(Sales!$E$7:$E$1506<$E84))+1)} | X84: =IF($A84="","",COUNTIFS($A$7:$A84,">="&EOMONTH($A84,-1)+1,$A$7:$A84,"<="&EOMONTH($A84,0))) -> 77 | Y84: =IF($A84="","",TEXT($A84,"yyyymm")&"-"&$X84) -> 202607-77 | AA84: =IF(Inventory!A82="","",Inventory!A82) -> PO-PP-100G-002
A85: 46229 | B85: Sale | C85: Shop | D85: PawfectBD Shop | F85: AC-CB-001 | G85: =IF($F85="","",IFERROR(VLOOKUP($F85,Inventory!$A:$B,2,FALSE),"")) -> Cat Belt | H85: 1 | I85: =IF($F85="","",IF($B85="Gift",0,J85-IF(K85="",0,K85))) -> 50 | J85: =IF($F85="","",IFERROR(VLOOKUP($F85,Inventory!$A:$K,11,FALSE),0)) -> 60 | K85: 10 | L85: =IF($F85="","",IF($B85="Return",-H85*I85,H85*I85)) -> 50 | M85: Paid | N85: =IF($F85="","",IFERROR(VLOOKUP($F85,Inventory!$A:$I,9,FALSE),0)) -> 29.351351 | O85: =IF($F85="","",IF($B85="Return",-H85*N85,H85*N85)) -> 29.351351 | P85: =IF($F85="","",L85-O85) -> 20.648649 | R85: =IF($E85="","",IF(COUNTIF($E$7:$E85,$E85)>1,"",IFERROR(VLOOKUP($E85,Orders!$A:$I,8,FALSE),""))) | S85: =IF($E85="","",IF(COUNTIF($E$7:$E85,$E85)>1,"",IFERROR(VLOOKUP($E85,Orders!$A:$I,9,FALSE),""))) | T85: =IF($F85="","",P85+IF(R85="",0,R85)-IF(S85="",0,S85)) -> 20.648649 | U85: =IF($F85="","",IF($E85="",T85,SUMIF(Sales!$E$7:$E$1506,$E85,Sales!$T$7:$T$1506))) -> 20.648649 | V85: =IF(OR($C85<>"Online",$E85=""),"",IF(COUNTIF($E$7:$E85,$E85)>1,"",COUNT($V$6:V84)+1)) | W85: {=IF($V85="","",SUMPRODUCT((Sales!$V$7:$V$1506<>"")*(Sales!$E$7:$E$1506<$E85))+1)} | X85: =IF($A85="","",COUNTIFS($A$7:$A85,">="&EOMONTH($A85,-1)+1,$A$7:$A85,"<="&EOMONTH($A85,0))) -> 78 | Y85: =IF($A85="","",TEXT($A85,"yyyymm")&"-"&$X85) -> 202607-78 | AA85: =IF(Inventory!A83="","",Inventory!A83) -> LT-AP-PM-5L-001
A86: 46229 | B86: Sale | C86: Shop | D86: PawfectBD Shop | F86: TR-CRMY-15G-001 | G86: =IF($F86="","",IFERROR(VLOOKUP($F86,Inventory!$A:$B,2,FALSE),"")) -> Creamy Treat 15G (Purry & Hyper Paws) | H86: 5 | I86: =IF($F86="","",IF($B86="Gift",0,J86-IF(K86="",0,K86))) -> 20 | J86: =IF($F86="","",IFERROR(VLOOKUP($F86,Inventory!$A:$K,11,FALSE),0)) -> 20 | L86: =IF($F86="","",IF($B86="Return",-H86*I86,H86*I86)) -> 100 | M86: Paid | N86: =IF($F86="","",IFERROR(VLOOKUP($F86,Inventory!$A:$I,9,FALSE),0)) -> 8.1474119 | O86: =IF($F86="","",IF($B86="Return",-H86*N86,H86*N86)) -> 40.737059 | P86: =IF($F86="","",L86-O86) -> 59.262941 | R86: =IF($E86="","",IF(COUNTIF($E$7:$E86,$E86)>1,"",IFERROR(VLOOKUP($E86,Orders!$A:$I,8,FALSE),""))) | S86: =IF($E86="","",IF(COUNTIF($E$7:$E86,$E86)>1,"",IFERROR(VLOOKUP($E86,Orders!$A:$I,9,FALSE),""))) | T86: =IF($F86="","",P86+IF(R86="",0,R86)-IF(S86="",0,S86)) -> 59.262941 | U86: =IF($F86="","",IF($E86="",T86,SUMIF(Sales!$E$7:$E$1506,$E86,Sales!$T$7:$T$1506))) -> 59.262941 | V86: =IF(OR($C86<>"Online",$E86=""),"",IF(COUNTIF($E$7:$E86,$E86)>1,"",COUNT($V$6:V85)+1)) | W86: {=IF($V86="","",SUMPRODUCT((Sales!$V$7:$V$1506<>"")*(Sales!$E$7:$E$1506<$E86))+1)} | X86: =IF($A86="","",COUNTIFS($A$7:$A86,">="&EOMONTH($A86,-1)+1,$A$7:$A86,"<="&EOMONTH($A86,0))) -> 79 | Y86: =IF($A86="","",TEXT($A86,"yyyymm")&"-"&$X86) -> 202607-79 | AA86: =IF(Inventory!A84="","",Inventory!A84) -> AC-CB-002
A87: 46229 | B87: Sale | C87: Shop | D87: PawfectBD Shop | F87: PO-TP-70G-001 | G87: =IF($F87="","",IFERROR(VLOOKUP($F87,Inventory!$A:$B,2,FALSE),"")) -> Taipet Chicken Tuna in Jelly | H87: 1 | I87: =IF($F87="","",IF($B87="Gift",0,J87-IF(K87="",0,K87))) -> 70 | J87: =IF($F87="","",IFERROR(VLOOKUP($F87,Inventory!$A:$K,11,FALSE),0)) -> 75 | K87: 5 | L87: =IF($F87="","",IF($B87="Return",-H87*I87,H87*I87)) -> 70 | M87: Paid | N87: =IF($F87="","",IFERROR(VLOOKUP($F87,Inventory!$A:$I,9,FALSE),0)) -> 52 | O87: =IF($F87="","",IF($B87="Return",-H87*N87,H87*N87)) -> 52 | P87: =IF($F87="","",L87-O87) -> 18 | R87: =IF($E87="","",IF(COUNTIF($E$7:$E87,$E87)>1,"",IFERROR(VLOOKUP($E87,Orders!$A:$I,8,FALSE),""))) | S87: =IF($E87="","",IF(COUNTIF($E$7:$E87,$E87)>1,"",IFERROR(VLOOKUP($E87,Orders!$A:$I,9,FALSE),""))) | T87: =IF($F87="","",P87+IF(R87="",0,R87)-IF(S87="",0,S87)) -> 18 | U87: =IF($F87="","",IF($E87="",T87,SUMIF(Sales!$E$7:$E$1506,$E87,Sales!$T$7:$T$1506))) -> 18 | V87: =IF(OR($C87<>"Online",$E87=""),"",IF(COUNTIF($E$7:$E87,$E87)>1,"",COUNT($V$6:V86)+1)) | W87: {=IF($V87="","",SUMPRODUCT((Sales!$V$7:$V$1506<>"")*(Sales!$E$7:$E$1506<$E87))+1)} | X87: =IF($A87="","",COUNTIFS($A$7:$A87,">="&EOMONTH($A87,-1)+1,$A$7:$A87,"<="&EOMONTH($A87,0))) -> 80 | Y87: =IF($A87="","",TEXT($A87,"yyyymm")&"-"&$X87) -> 202607-80 | AA87: =IF(Inventory!A85="","",Inventory!A85) -> AC-CN-001
A88: 46229 | B88: Sale | C88: Shop | D88: PawfectBD Shop | F88: TR-CRMY-15G-001 | G88: =IF($F88="","",IFERROR(VLOOKUP($F88,Inventory!$A:$B,2,FALSE),"")) -> Creamy Treat 15G (Purry & Hyper Paws) | H88: 5 | I88: =IF($F88="","",IF($B88="Gift",0,J88-IF(K88="",0,K88))) -> 20 | J88: =IF($F88="","",IFERROR(VLOOKUP($F88,Inventory!$A:$K,11,FALSE),0)) -> 20 | L88: =IF($F88="","",IF($B88="Return",-H88*I88,H88*I88)) -> 100 | M88: Paid | N88: =IF($F88="","",IFERROR(VLOOKUP($F88,Inventory!$A:$I,9,FALSE),0)) -> 8.1474119 | O88: =IF($F88="","",IF($B88="Return",-H88*N88,H88*N88)) -> 40.737059 | P88: =IF($F88="","",L88-O88) -> 59.262941 | R88: =IF($E88="","",IF(COUNTIF($E$7:$E88,$E88)>1,"",IFERROR(VLOOKUP($E88,Orders!$A:$I,8,FALSE),""))) | S88: =IF($E88="","",IF(COUNTIF($E$7:$E88,$E88)>1,"",IFERROR(VLOOKUP($E88,Orders!$A:$I,9,FALSE),""))) | T88: =IF($F88="","",P88+IF(R88="",0,R88)-IF(S88="",0,S88)) -> 59.262941 | U88: =IF($F88="","",IF($E88="",T88,SUMIF(Sales!$E$7:$E$1506,$E88,Sales!$T$7:$T$1506))) -> 59.262941 | V88: =IF(OR($C88<>"Online",$E88=""),"",IF(COUNTIF($E$7:$E88,$E88)>1,"",COUNT($V$6:V87)+1)) | W88: {=IF($V88="","",SUMPRODUCT((Sales!$V$7:$V$1506<>"")*(Sales!$E$7:$E$1506<$E88))+1)} | X88: =IF($A88="","",COUNTIFS($A$7:$A88,">="&EOMONTH($A88,-1)+1,$A$7:$A88,"<="&EOMONTH($A88,0))) -> 81 | Y88: =IF($A88="","",TEXT($A88,"yyyymm")&"-"&$X88) -> 202607-81 | AA88: =IF(Inventory!A86="","",Inventory!A86) -> LT-AP-PM-5L-002
A89: 46229 | B89: Sale | C89: Shop | D89: PawfectBD Shop | F89: TR-CRMY-15G-001 | G89: =IF($F89="","",IFERROR(VLOOKUP($F89,Inventory!$A:$B,2,FALSE),"")) -> Creamy Treat 15G (Purry & Hyper Paws) | H89: 3 | I89: =IF($F89="","",IF($B89="Gift",0,J89-IF(K89="",0,K89))) -> 20 | J89: =IF($F89="","",IFERROR(VLOOKUP($F89,Inventory!$A:$K,11,FALSE),0)) -> 20 | L89: =IF($F89="","",IF($B89="Return",-H89*I89,H89*I89)) -> 60 | M89: Paid | N89: =IF($F89="","",IFERROR(VLOOKUP($F89,Inventory!$A:$I,9,FALSE),0)) -> 8.1474119 | O89: =IF($F89="","",IF($B89="Return",-H89*N89,H89*N89)) -> 24.442236 | P89: =IF($F89="","",L89-O89) -> 35.557764 | R89: =IF($E89="","",IF(COUNTIF($E$7:$E89,$E89)>1,"",IFERROR(VLOOKUP($E89,Orders!$A:$I,8,FALSE),""))) | S89: =IF($E89="","",IF(COUNTIF($E$7:$E89,$E89)>1,"",IFERROR(VLOOKUP($E89,Orders!$A:$I,9,FALSE),""))) | T89: =IF($F89="","",P89+IF(R89="",0,R89)-IF(S89="",0,S89)) -> 35.557764 | U89: =IF($F89="","",IF($E89="",T89,SUMIF(Sales!$E$7:$E$1506,$E89,Sales!$T$7:$T$1506))) -> 35.557764 | V89: =IF(OR($C89<>"Online",$E89=""),"",IF(COUNTIF($E$7:$E89,$E89)>1,"",COUNT($V$6:V88)+1)) | W89: {=IF($V89="","",SUMPRODUCT((Sales!$V$7:$V$1506<>"")*(Sales!$E$7:$E$1506<$E89))+1)} | X89: =IF($A89="","",COUNTIFS($A$7:$A89,">="&EOMONTH($A89,-1)+1,$A$7:$A89,"<="&EOMONTH($A89,0))) -> 82 | Y89: =IF($A89="","",TEXT($A89,"yyyymm")&"-"&$X89) -> 202607-82 | AA89: =IF(Inventory!A87="","",Inventory!A87) -> FD-MX-0001
A90: 46229 | B90: Sale | C90: Shop | D90: Tanvir Bhai | F90: FD-DRY-KTCN-1.5G-001 | G90: =IF($F90="","",IFERROR(VLOOKUP($F90,Inventory!$A:$B,2,FALSE),"")) -> Kitchen Flavor Grain Free Adult 1.5KG | H90: 1 | I90: =IF($F90="","",IF($B90="Gift",0,J90-IF(K90="",0,K90))) -> 1210 | J90: =IF($F90="","",IFERROR(VLOOKUP($F90,Inventory!$A:$K,11,FALSE),0)) -> 1260 | K90: 50 | L90: =IF($F90="","",IF($B90="Return",-H90*I90,H90*I90)) -> 1210 | M90: Paid | N90: =IF($F90="","",IFERROR(VLOOKUP($F90,Inventory!$A:$I,9,FALSE),0)) -> 990 | O90: =IF($F90="","",IF($B90="Return",-H90*N90,H90*N90)) -> 990 | P90: =IF($F90="","",L90-O90) -> 220 | R90: =IF($E90="","",IF(COUNTIF($E$7:$E90,$E90)>1,"",IFERROR(VLOOKUP($E90,Orders!$A:$I,8,FALSE),""))) | S90: =IF($E90="","",IF(COUNTIF($E$7:$E90,$E90)>1,"",IFERROR(VLOOKUP($E90,Orders!$A:$I,9,FALSE),""))) | T90: =IF($F90="","",P90+IF(R90="",0,R90)-IF(S90="",0,S90)) -> 220 | U90: =IF($F90="","",IF($E90="",T90,SUMIF(Sales!$E$7:$E$1506,$E90,Sales!$T$7:$T$1506))) -> 220 | V90: =IF(OR($C90<>"Online",$E90=""),"",IF(COUNTIF($E$7:$E90,$E90)>1,"",COUNT($V$6:V89)+1)) | W90: {=IF($V90="","",SUMPRODUCT((Sales!$V$7:$V$1506<>"")*(Sales!$E$7:$E$1506<$E90))+1)} | X90: =IF($A90="","",COUNTIFS($A$7:$A90,">="&EOMONTH($A90,-1)+1,$A$7:$A90,"<="&EOMONTH($A90,0))) -> 83 | Y90: =IF($A90="","",TEXT($A90,"yyyymm")&"-"&$X90) -> 202607-83 | AA90: =IF(Inventory!A88="","",Inventory!A88) -> FD-DRY-JUN-KT-1.5KG-001
A91: 46229 | B91: Sale | C91: Shop | D91: Tanvir Bhai | F91: TR-CRMY-15G-001 | G91: =IF($F91="","",IFERROR(VLOOKUP($F91,Inventory!$A:$B,2,FALSE),"")) -> Creamy Treat 15G (Purry & Hyper Paws) | H91: 2 | I91: =IF($F91="","",IF($B91="Gift",0,J91-IF(K91="",0,K91))) -> 20 | J91: =IF($F91="","",IFERROR(VLOOKUP($F91,Inventory!$A:$K,11,FALSE),0)) -> 20 | L91: =IF($F91="","",IF($B91="Return",-H91*I91,H91*I91)) -> 40 | M91: Paid | N91: =IF($F91="","",IFERROR(VLOOKUP($F91,Inventory!$A:$I,9,FALSE),0)) -> 8.1474119 | O91: =IF($F91="","",IF($B91="Return",-H91*N91,H91*N91)) -> 16.294824 | P91: =IF($F91="","",L91-O91) -> 23.705176 | R91: =IF($E91="","",IF(COUNTIF($E$7:$E91,$E91)>1,"",IFERROR(VLOOKUP($E91,Orders!$A:$I,8,FALSE),""))) | S91: =IF($E91="","",IF(COUNTIF($E$7:$E91,$E91)>1,"",IFERROR(VLOOKUP($E91,Orders!$A:$I,9,FALSE),""))) | T91: =IF($F91="","",P91+IF(R91="",0,R91)-IF(S91="",0,S91)) -> 23.705176 | U91: =IF($F91="","",IF($E91="",T91,SUMIF(Sales!$E$7:$E$1506,$E91,Sales!$T$7:$T$1506))) -> 23.705176 | V91: =IF(OR($C91<>"Online",$E91=""),"",IF(COUNTIF($E$7:$E91,$E91)>1,"",COUNT($V$6:V90)+1)) | W91: {=IF($V91="","",SUMPRODUCT((Sales!$V$7:$V$1506<>"")*(Sales!$E$7:$E$1506<$E91))+1)} | X91: =IF($A91="","",COUNTIFS($A$7:$A91,">="&EOMONTH($A91,-1)+1,$A$7:$A91,"<="&EOMONTH($A91,0))) -> 84 | Y91: =IF($A91="","",TEXT($A91,"yyyymm")&"-"&$X91) -> 202607-84 | AA91: =IF(Inventory!A89="","",Inventory!A89) -> FD-DRY-KVF-1.5KG-001
A92: 46230 | B92: Sale | C92: Shop | D92: PawfectBD Shop | F92: AC-SHAMP-002 | G92: =IF($F92="","",IFERROR(VLOOKUP($F92,Inventory!$A:$B,2,FALSE),"")) -> Bengal Flea & Tick Shampoo | H92: 1 | I92: =IF($F92="","",IF($B92="Gift",0,J92-IF(K92="",0,K92))) -> 380 | J92: =IF($F92="","",IFERROR(VLOOKUP($F92,Inventory!$A:$K,11,FALSE),0)) -> 400 | K92: 20 | L92: =IF($F92="","",IF($B92="Return",-H92*I92,H92*I92)) -> 380 | M92: Paid | N92: =IF($F92="","",IFERROR(VLOOKUP($F92,Inventory!$A:$I,9,FALSE),0)) -> 240 | O92: =IF($F92="","",IF($B92="Return",-H92*N92,H92*N92)) -> 240 | P92: =IF($F92="","",L92-O92) -> 140 | R92: =IF($E92="","",IF(COUNTIF($E$7:$E92,$E92)>1,"",IFERROR(VLOOKUP($E92,Orders!$A:$I,8,FALSE),""))) | S92: =IF($E92="","",IF(COUNTIF($E$7:$E92,$E92)>1,"",IFERROR(VLOOKUP($E92,Orders!$A:$I,9,FALSE),""))) | T92: =IF($F92="","",P92+IF(R92="",0,R92)-IF(S92="",0,S92)) -> 140 | U92: =IF($F92="","",IF($E92="",T92,SUMIF(Sales!$E$7:$E$1506,$E92,Sales!$T$7:$T$1506))) -> 140 | V92: =IF(OR($C92<>"Online",$E92=""),"",IF(COUNTIF($E$7:$E92,$E92)>1,"",COUNT($V$6:V91)+1)) | W92: {=IF($V92="","",SUMPRODUCT((Sales!$V$7:$V$1506<>"")*(Sales!$E$7:$E$1506<$E92))+1)} | X92: =IF($A92="","",COUNTIFS($A$7:$A92,">="&EOMONTH($A92,-1)+1,$A$7:$A92,"<="&EOMONTH($A92,0))) -> 85 | Y92: =IF($A92="","",TEXT($A92,"yyyymm")&"-"&$X92) -> 202607-85 | AA92: =IF(Inventory!A90="","",Inventory!A90) -> LT-LM-LUM-5L-001
A93: 46230 | B93: Sale | C93: Shop | D93: PawfectBD Shop | F93: FD-DRY-SMHRT-450G-001 | G93: =IF($F93="","",IFERROR(VLOOKUP($F93,Inventory!$A:$B,2,FALSE),"")) -> Smart Heart Kitten Food Chicken, Fish, Egg & Milk 450gm | H93: 1 | I93: =IF($F93="","",IF($B93="Gift",0,J93-IF(K93="",0,K93))) -> 350 | J93: =IF($F93="","",IFERROR(VLOOKUP($F93,Inventory!$A:$K,11,FALSE),0)) -> 380 | K93: 30 | L93: =IF($F93="","",IF($B93="Return",-H93*I93,H93*I93)) -> 350 | M93: Paid | N93: =IF($F93="","",IFERROR(VLOOKUP($F93,Inventory!$A:$I,9,FALSE),0)) -> 290 | O93: =IF($F93="","",IF($B93="Return",-H93*N93,H93*N93)) -> 290 | P93: =IF($F93="","",L93-O93) -> 60 | R93: =IF($E93="","",IF(COUNTIF($E$7:$E93,$E93)>1,"",IFERROR(VLOOKUP($E93,Orders!$A:$I,8,FALSE),""))) | S93: =IF($E93="","",IF(COUNTIF($E$7:$E93,$E93)>1,"",IFERROR(VLOOKUP($E93,Orders!$A:$I,9,FALSE),""))) | T93: =IF($F93="","",P93+IF(R93="",0,R93)-IF(S93="",0,S93)) -> 60 | U93: =IF($F93="","",IF($E93="",T93,SUMIF(Sales!$E$7:$E$1506,$E93,Sales!$T$7:$T$1506))) -> 60 | V93: =IF(OR($C93<>"Online",$E93=""),"",IF(COUNTIF($E$7:$E93,$E93)>1,"",COUNT($V$6:V92)+1)) | W93: {=IF($V93="","",SUMPRODUCT((Sales!$V$7:$V$1506<>"")*(Sales!$E$7:$E$1506<$E93))+1)} | X93: =IF($A93="","",COUNTIFS($A$7:$A93,">="&EOMONTH($A93,-1)+1,$A$7:$A93,"<="&EOMONTH($A93,0))) -> 86 | Y93: =IF($A93="","",TEXT($A93,"yyyymm")&"-"&$X93) -> 202607-86 | AA93: =IF(Inventory!A91="","",Inventory!A91) -> LT-AP-LUM-5L-002
A94: 46230 | B94: Sale | C94: Shop | D94: PawfectBD Shop | F94: TR-CRMY-15G-001 | G94: =IF($F94="","",IFERROR(VLOOKUP($F94,Inventory!$A:$B,2,FALSE),"")) -> Creamy Treat 15G (Purry & Hyper Paws) | H94: 5 | I94: =IF($F94="","",IF($B94="Gift",0,J94-IF(K94="",0,K94))) -> 20 | J94: =IF($F94="","",IFERROR(VLOOKUP($F94,Inventory!$A:$K,11,FALSE),0)) -> 20 | L94: =IF($F94="","",IF($B94="Return",-H94*I94,H94*I94)) -> 100 | M94: Paid | N94: =IF($F94="","",IFERROR(VLOOKUP($F94,Inventory!$A:$I,9,FALSE),0)) -> 8.1474119 | O94: =IF($F94="","",IF($B94="Return",-H94*N94,H94*N94)) -> 40.737059 | P94: =IF($F94="","",L94-O94) -> 59.262941 | R94: =IF($E94="","",IF(COUNTIF($E$7:$E94,$E94)>1,"",IFERROR(VLOOKUP($E94,Orders!$A:$I,8,FALSE),""))) | S94: =IF($E94="","",IF(COUNTIF($E$7:$E94,$E94)>1,"",IFERROR(VLOOKUP($E94,Orders!$A:$I,9,FALSE),""))) | T94: =IF($F94="","",P94+IF(R94="",0,R94)-IF(S94="",0,S94)) -> 59.262941 | U94: =IF($F94="","",IF($E94="",T94,SUMIF(Sales!$E$7:$E$1506,$E94,Sales!$T$7:$T$1506))) -> 59.262941 | V94: =IF(OR($C94<>"Online",$E94=""),"",IF(COUNTIF($E$7:$E94,$E94)>1,"",COUNT($V$6:V93)+1)) | W94: {=IF($V94="","",SUMPRODUCT((Sales!$V$7:$V$1506<>"")*(Sales!$E$7:$E$1506<$E94))+1)} | X94: =IF($A94="","",COUNTIFS($A$7:$A94,">="&EOMONTH($A94,-1)+1,$A$7:$A94,"<="&EOMONTH($A94,0))) -> 87 | Y94: =IF($A94="","",TEXT($A94,"yyyymm")&"-"&$X94) -> 202607-87 | AA94: =IF(Inventory!A92="","",Inventory!A92) -> LT-CF-LUM-5L-003
A95: 46231 | B95: Sale | C95: Shop | D95: PawfectBD Shop | F95: TR-CRMY-15G-001 | G95: =IF($F95="","",IFERROR(VLOOKUP($F95,Inventory!$A:$B,2,FALSE),"")) -> Creamy Treat 15G (Purry & Hyper Paws) | H95: 4 | I95: =IF($F95="","",IF($B95="Gift",0,J95-IF(K95="",0,K95))) -> 12.5 | J95: =IF($F95="","",IFERROR(VLOOKUP($F95,Inventory!$A:$K,11,FALSE),0)) -> 20 | K95: 7.5 | L95: =IF($F95="","",IF($B95="Return",-H95*I95,H95*I95)) -> 50 | M95: Paid | N95: =IF($F95="","",IFERROR(VLOOKUP($F95,Inventory!$A:$I,9,FALSE),0)) -> 8.1474119 | O95: =IF($F95="","",IF($B95="Return",-H95*N95,H95*N95)) -> 32.589647 | P95: =IF($F95="","",L95-O95) -> 17.410353 | R95: =IF($E95="","",IF(COUNTIF($E$7:$E95,$E95)>1,"",IFERROR(VLOOKUP($E95,Orders!$A:$I,8,FALSE),""))) | S95: =IF($E95="","",IF(COUNTIF($E$7:$E95,$E95)>1,"",IFERROR(VLOOKUP($E95,Orders!$A:$I,9,FALSE),""))) | T95: =IF($F95="","",P95+IF(R95="",0,R95)-IF(S95="",0,S95)) -> 17.410353 | U95: =IF($F95="","",IF($E95="",T95,SUMIF(Sales!$E$7:$E$1506,$E95,Sales!$T$7:$T$1506))) -> 17.410353 | V95: =IF(OR($C95<>"Online",$E95=""),"",IF(COUNTIF($E$7:$E95,$E95)>1,"",COUNT($V$6:V94)+1)) | W95: {=IF($V95="","",SUMPRODUCT((Sales!$V$7:$V$1506<>"")*(Sales!$E$7:$E$1506<$E95))+1)} | X95: =IF($A95="","",COUNTIFS($A$7:$A95,">="&EOMONTH($A95,-1)+1,$A$7:$A95,"<="&EOMONTH($A95,0))) -> 88 | Y95: =IF($A95="","",TEXT($A95,"yyyymm")&"-"&$X95) -> 202607-88 | AA95: =IF(Inventory!A93="","",Inventory!A93) -> LT-LV-LUM-5L-004
A96: 46231 | B96: Sale | C96: Shop | D96: PawfectBD Shop | F96: TR-CRMY-15G-001 | G96: =IF($F96="","",IFERROR(VLOOKUP($F96,Inventory!$A:$B,2,FALSE),"")) -> Creamy Treat 15G (Purry & Hyper Paws) | H96: 3 | I96: =IF($F96="","",IF($B96="Gift",0,J96-IF(K96="",0,K96))) -> 20 | J96: =IF($F96="","",IFERROR(VLOOKUP($F96,Inventory!$A:$K,11,FALSE),0)) -> 20 | L96: =IF($F96="","",IF($B96="Return",-H96*I96,H96*I96)) -> 60 | M96: Paid | N96: =IF($F96="","",IFERROR(VLOOKUP($F96,Inventory!$A:$I,9,FALSE),0)) -> 8.1474119 | O96: =IF($F96="","",IF($B96="Return",-H96*N96,H96*N96)) -> 24.442236 | P96: =IF($F96="","",L96-O96) -> 35.557764 | R96: =IF($E96="","",IF(COUNTIF($E$7:$E96,$E96)>1,"",IFERROR(VLOOKUP($E96,Orders!$A:$I,8,FALSE),""))) | S96: =IF($E96="","",IF(COUNTIF($E$7:$E96,$E96)>1,"",IFERROR(VLOOKUP($E96,Orders!$A:$I,9,FALSE),""))) | T96: =IF($F96="","",P96+IF(R96="",0,R96)-IF(S96="",0,S96)) -> 35.557764 | U96: =IF($F96="","",IF($E96="",T96,SUMIF(Sales!$E$7:$E$1506,$E96,Sales!$T$7:$T$1506))) -> 35.557764 | V96: =IF(OR($C96<>"Online",$E96=""),"",IF(COUNTIF($E$7:$E96,$E96)>1,"",COUNT($V$6:V95)+1)) | W96: {=IF($V96="","",SUMPRODUCT((Sales!$V$7:$V$1506<>"")*(Sales!$E$7:$E$1506<$E96))+1)} | X96: =IF($A96="","",COUNTIFS($A$7:$A96,">="&EOMONTH($A96,-1)+1,$A$7:$A96,"<="&EOMONTH($A96,0))) -> 89 | Y96: =IF($A96="","",TEXT($A96,"yyyymm")&"-"&$X96) -> 202607-89 | AA96: =IF(Inventory!A94="","",Inventory!A94) -> LT-LM-NT-10L-001
A97: 46231 | B97: Sale | C97: Shop | D97: PawfectBD Shop | F97: TR-CRMY-15G-001 | G97: =IF($F97="","",IFERROR(VLOOKUP($F97,Inventory!$A:$B,2,FALSE),"")) -> Creamy Treat 15G (Purry & Hyper Paws) | H97: 1 | I97: =IF($F97="","",IF($B97="Gift",0,J97-IF(K97="",0,K97))) -> 20 | J97: =IF($F97="","",IFERROR(VLOOKUP($F97,Inventory!$A:$K,11,FALSE),0)) -> 20 | L97: =IF($F97="","",IF($B97="Return",-H97*I97,H97*I97)) -> 20 | M97: Paid | N97: =IF($F97="","",IFERROR(VLOOKUP($F97,Inventory!$A:$I,9,FALSE),0)) -> 8.1474119 | O97: =IF($F97="","",IF($B97="Return",-H97*N97,H97*N97)) -> 8.1474119 | P97: =IF($F97="","",L97-O97) -> 11.852588 | R97: =IF($E97="","",IF(COUNTIF($E$7:$E97,$E97)>1,"",IFERROR(VLOOKUP($E97,Orders!$A:$I,8,FALSE),""))) | S97: =IF($E97="","",IF(COUNTIF($E$7:$E97,$E97)>1,"",IFERROR(VLOOKUP($E97,Orders!$A:$I,9,FALSE),""))) | T97: =IF($F97="","",P97+IF(R97="",0,R97)-IF(S97="",0,S97)) -> 11.852588 | U97: =IF($F97="","",IF($E97="",T97,SUMIF(Sales!$E$7:$E$1506,$E97,Sales!$T$7:$T$1506))) -> 11.852588 | V97: =IF(OR($C97<>"Online",$E97=""),"",IF(COUNTIF($E$7:$E97,$E97)>1,"",COUNT($V$6:V96)+1)) | W97: {=IF($V97="","",SUMPRODUCT((Sales!$V$7:$V$1506<>"")*(Sales!$E$7:$E$1506<$E97))+1)} | X97: =IF($A97="","",COUNTIFS($A$7:$A97,">="&EOMONTH($A97,-1)+1,$A$7:$A97,"<="&EOMONTH($A97,0))) -> 90 | Y97: =IF($A97="","",TEXT($A97,"yyyymm")&"-"&$X97) -> 202607-90 | AA97: =IF(Inventory!A95="","",Inventory!A95) -> LT-AP-LUM-10L-002
A98: 46231 | B98: Sale | C98: Shop | D98: Nadim | F98: TR-CRMY-15G-001 | G98: =IF($F98="","",IFERROR(VLOOKUP($F98,Inventory!$A:$B,2,FALSE),"")) -> Creamy Treat 15G (Purry & Hyper Paws) | H98: 1 | I98: =IF($F98="","",IF($B98="Gift",0,J98-IF(K98="",0,K98))) -> 10 | J98: =IF($F98="","",IFERROR(VLOOKUP($F98,Inventory!$A:$K,11,FALSE),0)) -> 20 | K98: 10 | L98: =IF($F98="","",IF($B98="Return",-H98*I98,H98*I98)) -> 10 | M98: Paid | N98: =IF($F98="","",IFERROR(VLOOKUP($F98,Inventory!$A:$I,9,FALSE),0)) -> 8.1474119 | O98: =IF($F98="","",IF($B98="Return",-H98*N98,H98*N98)) -> 8.1474119 | P98: =IF($F98="","",L98-O98) -> 1.8525881 | R98: =IF($E98="","",IF(COUNTIF($E$7:$E98,$E98)>1,"",IFERROR(VLOOKUP($E98,Orders!$A:$I,8,FALSE),""))) | S98: =IF($E98="","",IF(COUNTIF($E$7:$E98,$E98)>1,"",IFERROR(VLOOKUP($E98,Orders!$A:$I,9,FALSE),""))) | T98: =IF($F98="","",P98+IF(R98="",0,R98)-IF(S98="",0,S98)) -> 1.8525881 | U98: =IF($F98="","",IF($E98="",T98,SUMIF(Sales!$E$7:$E$1506,$E98,Sales!$T$7:$T$1506))) -> 1.8525881 | V98: =IF(OR($C98<>"Online",$E98=""),"",IF(COUNTIF($E$7:$E98,$E98)>1,"",COUNT($V$6:V97)+1)) | W98: {=IF($V98="","",SUMPRODUCT((Sales!$V$7:$V$1506<>"")*(Sales!$E$7:$E$1506<$E98))+1)} | X98: =IF($A98="","",COUNTIFS($A$7:$A98,">="&EOMONTH($A98,-1)+1,$A$7:$A98,"<="&EOMONTH($A98,0))) -> 91 | Y98: =IF($A98="","",TEXT($A98,"yyyymm")&"-"&$X98) -> 202607-91 | AA98: =IF(Inventory!A96="","",Inventory!A96) -> LT-CF-FT-10L-003
A99: 46231 | B99: Sale | C99: Shop | D99: Nadim | F99: PO-WET-SMHRT-TWC-85G-001 | G99: =IF($F99="","",IFERROR(VLOOKUP($F99,Inventory!$A:$B,2,FALSE),"")) -> Smart Heart Pouch Tuna With Chicken in Jelly | H99: 1 | I99: =IF($F99="","",IF($B99="Gift",0,J99-IF(K99="",0,K99))) -> 90 | J99: =IF($F99="","",IFERROR(VLOOKUP($F99,Inventory!$A:$K,11,FALSE),0)) -> 95 | K99: 5 | L99: =IF($F99="","",IF($B99="Return",-H99*I99,H99*I99)) -> 90 | M99: Paid | N99: =IF($F99="","",IFERROR(VLOOKUP($F99,Inventory!$A:$I,9,FALSE),0)) -> 71.904762 | O99: =IF($F99="","",IF($B99="Return",-H99*N99,H99*N99)) -> 71.904762 | P99: =IF($F99="","",L99-O99) -> 18.095238 | R99: =IF($E99="","",IF(COUNTIF($E$7:$E99,$E99)>1,"",IFERROR(VLOOKUP($E99,Orders!$A:$I,8,FALSE),""))) | S99: =IF($E99="","",IF(COUNTIF($E$7:$E99,$E99)>1,"",IFERROR(VLOOKUP($E99,Orders!$A:$I,9,FALSE),""))) | T99: =IF($F99="","",P99+IF(R99="",0,R99)-IF(S99="",0,S99)) -> 18.095238 | U99: =IF($F99="","",IF($E99="",T99,SUMIF(Sales!$E$7:$E$1506,$E99,Sales!$T$7:$T$1506))) -> 18.095238 | V99: =IF(OR($C99<>"Online",$E99=""),"",IF(COUNTIF($E$7:$E99,$E99)>1,"",COUNT($V$6:V98)+1)) | W99: {=IF($V99="","",SUMPRODUCT((Sales!$V$7:$V$1506<>"")*(Sales!$E$7:$E$1506<$E99))+1)} | X99: =IF($A99="","",COUNTIFS($A$7:$A99,">="&EOMONTH($A99,-1)+1,$A$7:$A99,"<="&EOMONTH($A99,0))) -> 92 | Y99: =IF($A99="","",TEXT($A99,"yyyymm")&"-"&$X99) -> 202607-92 | AA99: =IF(Inventory!A97="","",Inventory!A97) -> LT-LV-LUM-10L-004
A100: 46219 | B100: Sale | C100: Shop | D100: PawfectBD Shop | F100: LT-MX-DCLP-5L-002 | G100: =IF($F100="","",IFERROR(VLOOKUP($F100,Inventory!$A:$B,2,FALSE),"")) -> Cat Litter Mix Flavor 5L DR. Clump | H100: 1 | I100: =IF($F100="","",IF($B100="Gift",0,J100-IF(K100="",0,K100))) -> 300 | J100: =IF($F100="","",IFERROR(VLOOKUP($F100,Inventory!$A:$K,11,FALSE),0)) -> 320 | K100: 20 | L100: =IF($F100="","",IF($B100="Return",-H100*I100,H100*I100)) -> 300 | M100: Paid | N100: =IF($F100="","",IFERROR(VLOOKUP($F100,Inventory!$A:$I,9,FALSE),0)) -> 220 | O100: =IF($F100="","",IF($B100="Return",-H100*N100,H100*N100)) -> 220 | P100: =IF($F100="","",L100-O100) -> 80 | R100: =IF($E100="","",IF(COUNTIF($E$7:$E100,$E100)>1,"",IFERROR(VLOOKUP($E100,Orders!$A:$I,8,FALSE),""))) | S100: =IF($E100="","",IF(COUNTIF($E$7:$E100,$E100)>1,"",IFERROR(VLOOKUP($E100,Orders!$A:$I,9,FALSE),""))) | T100: =IF($F100="","",P100+IF(R100="",0,R100)-IF(S100="",0,S100)) -> 80 | U100: =IF($F100="","",IF($E100="",T100,SUMIF(Sales!$E$7:$E$1506,$E100,Sales!$T$7:$T$1506))) -> 80 | V100: =IF(OR($C100<>"Online",$E100=""),"",IF(COUNTIF($E$7:$E100,$E100)>1,"",COUNT($V$6:V99)+1)) | W100: {=IF($V100="","",SUMPRODUCT((Sales!$V$7:$V$1506<>"")*(Sales!$E$7:$E$1506<$E100))+1)} | X100: =IF($A100="","",COUNTIFS($A$7:$A100,">="&EOMONTH($A100,-1)+1,$A$7:$A100,"<="&EOMONTH($A100,0))) -> 93 | Y100: =IF($A100="","",TEXT($A100,"yyyymm")&"-"&$X100) -> 202607-93 | AA100: =IF(Inventory!A98="","",Inventory!A98) -> LT-LM-LUM-25L-001
A101: 46221 | B101: Sale | C101: Shop | D101: PawfectBD Shop | F101: LT-MX-DCLP-5L-002 | G101: =IF($F101="","",IFERROR(VLOOKUP($F101,Inventory!$A:$B,2,FALSE),"")) -> Cat Litter Mix Flavor 5L DR. Clump | H101: 1 | I101: =IF($F101="","",IF($B101="Gift",0,J101-IF(K101="",0,K101))) -> 300 | J101: =IF($F101="","",IFERROR(VLOOKUP($F101,Inventory!$A:$K,11,FALSE),0)) -> 320 | K101: 20 | L101: =IF($F101="","",IF($B101="Return",-H101*I101,H101*I101)) -> 300 | M101: Paid | N101: =IF($F101="","",IFERROR(VLOOKUP($F101,Inventory!$A:$I,9,FALSE),0)) -> 220 | O101: =IF($F101="","",IF($B101="Return",-H101*N101,H101*N101)) -> 220 | P101: =IF($F101="","",L101-O101) -> 80 | R101: =IF($E101="","",IF(COUNTIF($E$7:$E101,$E101)>1,"",IFERROR(VLOOKUP($E101,Orders!$A:$I,8,FALSE),""))) | S101: =IF($E101="","",IF(COUNTIF($E$7:$E101,$E101)>1,"",IFERROR(VLOOKUP($E101,Orders!$A:$I,9,FALSE),""))) | T101: =IF($F101="","",P101+IF(R101="",0,R101)-IF(S101="",0,S101)) -> 80 | U101: =IF($F101="","",IF($E101="",T101,SUMIF(Sales!$E$7:$E$1506,$E101,Sales!$T$7:$T$1506))) -> 80 | V101: =IF(OR($C101<>"Online",$E101=""),"",IF(COUNTIF($E$7:$E101,$E101)>1,"",COUNT($V$6:V100)+1)) | W101: {=IF($V101="","",SUMPRODUCT((Sales!$V$7:$V$1506<>"")*(Sales!$E$7:$E$1506<$E101))+1)} | X101: =IF($A101="","",COUNTIFS($A$7:$A101,">="&EOMONTH($A101,-1)+1,$A$7:$A101,"<="&EOMONTH($A101,0))) -> 94 | Y101: =IF($A101="","",TEXT($A101,"yyyymm")&"-"&$X101) -> 202607-94 | AA101: =IF(Inventory!A99="","",Inventory!A99) -> LT-LV-LUM-25L-002
...

Sheet Monthly Summary
A1: MONTHLY SALES SUMMARY
A2: Everything here calculates from the Sales sheet by itself. Nothing to type. New months fill in as you add sales.
A4: Month | B4: Sales (Tk) | C4: Cost of Goods (Tk) | D4: Product Profit (Tk) | E4: Delivery Charged (Tk) | F4: Delivery You Paid (Tk) | G4: Real Profit (Tk) | H4: Sale Lines | I4: Online Orders | J4: Profit Margin %
A5: =EOMONTH(MIN(Sales!$A$7:$A$1506),-1)+1 -> 46174 | B5: =SUMIFS(Sales!$L$7:$L$1506,Sales!$A$7:$A$1506,">="&$A5,Sales!$A$7:$A$1506,"<="&EOMONTH($A5,0)) -> 770 | C5: =SUMIFS(Sales!$O$7:$O$1506,Sales!$A$7:$A$1506,">="&$A5,Sales!$A$7:$A$1506,"<="&EOMONTH($A5,0)) -> 600 | D5: =B5-C5 -> 170 | E5: =SUMIFS(Sales!$R$7:$R$1506,Sales!$A$7:$A$1506,">="&$A5,Sales!$A$7:$A$1506,"<="&EOMONTH($A5,0)) -> 0 | F5: =SUMIFS(Sales!$S$7:$S$1506,Sales!$A$7:$A$1506,">="&$A5,Sales!$A$7:$A$1506,"<="&EOMONTH($A5,0)) -> 0 | G5: =D5+E5-F5 -> 170 | H5: =COUNTIFS(Sales!$A$7:$A$1506,">="&$A5,Sales!$A$7:$A$1506,"<="&EOMONTH($A5,0)) -> 1 | I5: =COUNTIFS(Sales!$A$7:$A$1506,">="&$A5,Sales!$A$7:$A$1506,"<="&EOMONTH($A5,0),Sales!$V$7:$V$1506,">0") -> 0 | J5: =IF(B5=0,"",G5/B5) -> 0.22077922
A6: =EDATE($A$5,ROW()-5) -> 46204 | B6: =SUMIFS(Sales!$L$7:$L$1506,Sales!$A$7:$A$1506,">="&$A6,Sales!$A$7:$A$1506,"<="&EOMONTH($A6,0)) -> 53352 | C6: =SUMIFS(Sales!$O$7:$O$1506,Sales!$A$7:$A$1506,">="&$A6,Sales!$A$7:$A$1506,"<="&EOMONTH($A6,0)) -> 43013.892 | D6: =B6-C6 -> 10338.108 | E6: =SUMIFS(Sales!$R$7:$R$1506,Sales!$A$7:$A$1506,">="&$A6,Sales!$A$7:$A$1506,"<="&EOMONTH($A6,0)) -> 940 | F6: =SUMIFS(Sales!$S$7:$S$1506,Sales!$A$7:$A$1506,">="&$A6,Sales!$A$7:$A$1506,"<="&EOMONTH($A6,0)) -> 879 | G6: =D6+E6-F6 -> 10399.108 | H6: =COUNTIFS(Sales!$A$7:$A$1506,">="&$A6,Sales!$A$7:$A$1506,"<="&EOMONTH($A6,0)) -> 133 | I6: =COUNTIFS(Sales!$A$7:$A$1506,">="&$A6,Sales!$A$7:$A$1506,"<="&EOMONTH($A6,0),Sales!$V$7:$V$1506,">0") -> 9 | J6: =IF(B6=0,"",G6/B6) -> 0.19491505
A7: =EDATE($A$5,ROW()-5) -> 46235 | B7: =SUMIFS(Sales!$L$7:$L$1506,Sales!$A$7:$A$1506,">="&$A7,Sales!$A$7:$A$1506,"<="&EOMONTH($A7,0)) -> 87944.011 | C7: =SUMIFS(Sales!$O$7:$O$1506,Sales!$A$7:$A$1506,">="&$A7,Sales!$A$7:$A$1506,"<="&EOMONTH($A7,0)) -> 66853.083 | D7: =B7-C7 -> 21090.928 | E7: =SUMIFS(Sales!$R$7:$R$1506,Sales!$A$7:$A$1506,">="&$A7,Sales!$A$7:$A$1506,"<="&EOMONTH($A7,0)) -> 950 | F7: =SUMIFS(Sales!$S$7:$S$1506,Sales!$A$7:$A$1506,">="&$A7,Sales!$A$7:$A$1506,"<="&EOMONTH($A7,0)) -> 1116 | G7: =D7+E7-F7 -> 20924.928 | H7: =COUNTIFS(Sales!$A$7:$A$1506,">="&$A7,Sales!$A$7:$A$1506,"<="&EOMONTH($A7,0)) -> 354 | I7: =COUNTIFS(Sales!$A$7:$A$1506,">="&$A7,Sales!$A$7:$A$1506,"<="&EOMONTH($A7,0),Sales!$V$7:$V$1506,">0") -> 9 | J7: =IF(B7=0,"",G7/B7) -> 0.23793465
A8: =EDATE($A$5,ROW()-5) -> 46266 | B8: =SUMIFS(Sales!$L$7:$L$1506,Sales!$A$7:$A$1506,">="&$A8,Sales!$A$7:$A$1506,"<="&EOMONTH($A8,0)) -> 5644 | C8: =SUMIFS(Sales!$O$7:$O$1506,Sales!$A$7:$A$1506,">="&$A8,Sales!$A$7:$A$1506,"<="&EOMONTH($A8,0)) -> 4258.9041 | D8: =B8-C8 -> 1385.0959 | E8: =SUMIFS(Sales!$R$7:$R$1506,Sales!$A$7:$A$1506,">="&$A8,Sales!$A$7:$A$1506,"<="&EOMONTH($A8,0)) -> 0 | F8: =SUMIFS(Sales!$S$7:$S$1506,Sales!$A$7:$A$1506,">="&$A8,Sales!$A$7:$A$1506,"<="&EOMONTH($A8,0)) -> 0 | G8: =D8+E8-F8 -> 1385.0959 | H8: =COUNTIFS(Sales!$A$7:$A$1506,">="&$A8,Sales!$A$7:$A$1506,"<="&EOMONTH($A8,0)) -> 23 | I8: =COUNTIFS(Sales!$A$7:$A$1506,">="&$A8,Sales!$A$7:$A$1506,"<="&EOMONTH($A8,0),Sales!$V$7:$V$1506,">0") -> 0 | J8: =IF(B8=0,"",G8/B8) -> 0.24541034
A9: =EDATE($A$5,ROW()-5) -> 46296 | B9: =SUMIFS(Sales!$L$7:$L$1506,Sales!$A$7:$A$1506,">="&$A9,Sales!$A$7:$A$1506,"<="&EOMONTH($A9,0)) -> 0 | C9: =SUMIFS(Sales!$O$7:$O$1506,Sales!$A$7:$A$1506,">="&$A9,Sales!$A$7:$A$1506,"<="&EOMONTH($A9,0)) -> 0 | D9: =B9-C9 -> 0 | E9: =SUMIFS(Sales!$R$7:$R$1506,Sales!$A$7:$A$1506,">="&$A9,Sales!$A$7:$A$1506,"<="&EOMONTH($A9,0)) -> 0 | F9: =SUMIFS(Sales!$S$7:$S$1506,Sales!$A$7:$A$1506,">="&$A9,Sales!$A$7:$A$1506,"<="&EOMONTH($A9,0)) -> 0 | G9: =D9+E9-F9 -> 0 | H9: =COUNTIFS(Sales!$A$7:$A$1506,">="&$A9,Sales!$A$7:$A$1506,"<="&EOMONTH($A9,0)) -> 0 | I9: =COUNTIFS(Sales!$A$7:$A$1506,">="&$A9,Sales!$A$7:$A$1506,"<="&EOMONTH($A9,0),Sales!$V$7:$V$1506,">0") -> 0 | J9: =IF(B9=0,"",G9/B9)
A10: =EDATE($A$5,ROW()-5) -> 46327 | B10: =SUMIFS(Sales!$L$7:$L$1506,Sales!$A$7:$A$1506,">="&$A10,Sales!$A$7:$A$1506,"<="&EOMONTH($A10,0)) -> 0 | C10: =SUMIFS(Sales!$O$7:$O$1506,Sales!$A$7:$A$1506,">="&$A10,Sales!$A$7:$A$1506,"<="&EOMONTH($A10,0)) -> 0 | D10: =B10-C10 -> 0 | E10: =SUMIFS(Sales!$R$7:$R$1506,Sales!$A$7:$A$1506,">="&$A10,Sales!$A$7:$A$1506,"<="&EOMONTH($A10,0)) -> 0 | F10: =SUMIFS(Sales!$S$7:$S$1506,Sales!$A$7:$A$1506,">="&$A10,Sales!$A$7:$A$1506,"<="&EOMONTH($A10,0)) -> 0 | G10: =D10+E10-F10 -> 0 | H10: =COUNTIFS(Sales!$A$7:$A$1506,">="&$A10,Sales!$A$7:$A$1506,"<="&EOMONTH($A10,0)) -> 0 | I10: =COUNTIFS(Sales!$A$7:$A$1506,">="&$A10,Sales!$A$7:$A$1506,"<="&EOMONTH($A10,0),Sales!$V$7:$V$1506,">0") -> 0 | J10: =IF(B10=0,"",G10/B10)
A11: =EDATE($A$5,ROW()-5) -> 46357 | B11: =SUMIFS(Sales!$L$7:$L$1506,Sales!$A$7:$A$1506,">="&$A11,Sales!$A$7:$A$1506,"<="&EOMONTH($A11,0)) -> 0 | C11: =SUMIFS(Sales!$O$7:$O$1506,Sales!$A$7:$A$1506,">="&$A11,Sales!$A$7:$A$1506,"<="&EOMONTH($A11,0)) -> 0 | D11: =B11-C11 -> 0 | E11: =SUMIFS(Sales!$R$7:$R$1506,Sales!$A$7:$A$1506,">="&$A11,Sales!$A$7:$A$1506,"<="&EOMONTH($A11,0)) -> 0 | F11: =SUMIFS(Sales!$S$7:$S$1506,Sales!$A$7:$A$1506,">="&$A11,Sales!$A$7:$A$1506,"<="&EOMONTH($A11,0)) -> 0 | G11: =D11+E11-F11 -> 0 | H11: =COUNTIFS(Sales!$A$7:$A$1506,">="&$A11,Sales!$A$7:$A$1506,"<="&EOMONTH($A11,0)) -> 0 | I11: =COUNTIFS(Sales!$A$7:$A$1506,">="&$A11,Sales!$A$7:$A$1506,"<="&EOMONTH($A11,0),Sales!$V$7:$V$1506,">0") -> 0 | J11: =IF(B11=0,"",G11/B11)
A12: =EDATE($A$5,ROW()-5) -> 46388 | B12: =SUMIFS(Sales!$L$7:$L$1506,Sales!$A$7:$A$1506,">="&$A12,Sales!$A$7:$A$1506,"<="&EOMONTH($A12,0)) -> 0 | C12: =SUMIFS(Sales!$O$7:$O$1506,Sales!$A$7:$A$1506,">="&$A12,Sales!$A$7:$A$1506,"<="&EOMONTH($A12,0)) -> 0 | D12: =B12-C12 -> 0 | E12: =SUMIFS(Sales!$R$7:$R$1506,Sales!$A$7:$A$1506,">="&$A12,Sales!$A$7:$A$1506,"<="&EOMONTH($A12,0)) -> 0 | F12: =SUMIFS(Sales!$S$7:$S$1506,Sales!$A$7:$A$1506,">="&$A12,Sales!$A$7:$A$1506,"<="&EOMONTH($A12,0)) -> 0 | G12: =D12+E12-F12 -> 0 | H12: =COUNTIFS(Sales!$A$7:$A$1506,">="&$A12,Sales!$A$7:$A$1506,"<="&EOMONTH($A12,0)) -> 0 | I12: =COUNTIFS(Sales!$A$7:$A$1506,">="&$A12,Sales!$A$7:$A$1506,"<="&EOMONTH($A12,0),Sales!$V$7:$V$1506,">0") -> 0 | J12: =IF(B12=0,"",G12/B12)
A13: =EDATE($A$5,ROW()-5) -> 46419 | B13: =SUMIFS(Sales!$L$7:$L$1506,Sales!$A$7:$A$1506,">="&$A13,Sales!$A$7:$A$1506,"<="&EOMONTH($A13,0)) -> 0 | C13: =SUMIFS(Sales!$O$7:$O$1506,Sales!$A$7:$A$1506,">="&$A13,Sales!$A$7:$A$1506,"<="&EOMONTH($A13,0)) -> 0 | D13: =B13-C13 -> 0 | E13: =SUMIFS(Sales!$R$7:$R$1506,Sales!$A$7:$A$1506,">="&$A13,Sales!$A$7:$A$1506,"<="&EOMONTH($A13,0)) -> 0 | F13: =SUMIFS(Sales!$S$7:$S$1506,Sales!$A$7:$A$1506,">="&$A13,Sales!$A$7:$A$1506,"<="&EOMONTH($A13,0)) -> 0 | G13: =D13+E13-F13 -> 0 | H13: =COUNTIFS(Sales!$A$7:$A$1506,">="&$A13,Sales!$A$7:$A$1506,"<="&EOMONTH($A13,0)) -> 0 | I13: =COUNTIFS(Sales!$A$7:$A$1506,">="&$A13,Sales!$A$7:$A$1506,"<="&EOMONTH($A13,0),Sales!$V$7:$V$1506,">0") -> 0 | J13: =IF(B13=0,"",G13/B13)
A14: =EDATE($A$5,ROW()-5) -> 46447 | B14: =SUMIFS(Sales!$L$7:$L$1506,Sales!$A$7:$A$1506,">="&$A14,Sales!$A$7:$A$1506,"<="&EOMONTH($A14,0)) -> 0 | C14: =SUMIFS(Sales!$O$7:$O$1506,Sales!$A$7:$A$1506,">="&$A14,Sales!$A$7:$A$1506,"<="&EOMONTH($A14,0)) -> 0 | D14: =B14-C14 -> 0 | E14: =SUMIFS(Sales!$R$7:$R$1506,Sales!$A$7:$A$1506,">="&$A14,Sales!$A$7:$A$1506,"<="&EOMONTH($A14,0)) -> 0 | F14: =SUMIFS(Sales!$S$7:$S$1506,Sales!$A$7:$A$1506,">="&$A14,Sales!$A$7:$A$1506,"<="&EOMONTH($A14,0)) -> 0 | G14: =D14+E14-F14 -> 0 | H14: =COUNTIFS(Sales!$A$7:$A$1506,">="&$A14,Sales!$A$7:$A$1506,"<="&EOMONTH($A14,0)) -> 0 | I14: =COUNTIFS(Sales!$A$7:$A$1506,">="&$A14,Sales!$A$7:$A$1506,"<="&EOMONTH($A14,0),Sales!$V$7:$V$1506,">0") -> 0 | J14: =IF(B14=0,"",G14/B14)
A15: =EDATE($A$5,ROW()-5) -> 46478 | B15: =SUMIFS(Sales!$L$7:$L$1506,Sales!$A$7:$A$1506,">="&$A15,Sales!$A$7:$A$1506,"<="&EOMONTH($A15,0)) -> 0 | C15: =SUMIFS(Sales!$O$7:$O$1506,Sales!$A$7:$A$1506,">="&$A15,Sales!$A$7:$A$1506,"<="&EOMONTH($A15,0)) -> 0 | D15: =B15-C15 -> 0 | E15: =SUMIFS(Sales!$R$7:$R$1506,Sales!$A$7:$A$1506,">="&$A15,Sales!$A$7:$A$1506,"<="&EOMONTH($A15,0)) -> 0 | F15: =SUMIFS(Sales!$S$7:$S$1506,Sales!$A$7:$A$1506,">="&$A15,Sales!$A$7:$A$1506,"<="&EOMONTH($A15,0)) -> 0 | G15: =D15+E15-F15 -> 0 | H15: =COUNTIFS(Sales!$A$7:$A$1506,">="&$A15,Sales!$A$7:$A$1506,"<="&EOMONTH($A15,0)) -> 0 | I15: =COUNTIFS(Sales!$A$7:$A$1506,">="&$A15,Sales!$A$7:$A$1506,"<="&EOMONTH($A15,0),Sales!$V$7:$V$1506,">0") -> 0 | J15: =IF(B15=0,"",G15/B15)
A16: =EDATE($A$5,ROW()-5) -> 46508 | B16: =SUMIFS(Sales!$L$7:$L$1506,Sales!$A$7:$A$1506,">="&$A16,Sales!$A$7:$A$1506,"<="&EOMONTH($A16,0)) -> 0 | C16: =SUMIFS(Sales!$O$7:$O$1506,Sales!$A$7:$A$1506,">="&$A16,Sales!$A$7:$A$1506,"<="&EOMONTH($A16,0)) -> 0 | D16: =B16-C16 -> 0 | E16: =SUMIFS(Sales!$R$7:$R$1506,Sales!$A$7:$A$1506,">="&$A16,Sales!$A$7:$A$1506,"<="&EOMONTH($A16,0)) -> 0 | F16: =SUMIFS(Sales!$S$7:$S$1506,Sales!$A$7:$A$1506,">="&$A16,Sales!$A$7:$A$1506,"<="&EOMONTH($A16,0)) -> 0 | G16: =D16+E16-F16 -> 0 | H16: =COUNTIFS(Sales!$A$7:$A$1506,">="&$A16,Sales!$A$7:$A$1506,"<="&EOMONTH($A16,0)) -> 0 | I16: =COUNTIFS(Sales!$A$7:$A$1506,">="&$A16,Sales!$A$7:$A$1506,"<="&EOMONTH($A16,0),Sales!$V$7:$V$1506,">0") -> 0 | J16: =IF(B16=0,"",G16/B16)
A17: =EDATE($A$5,ROW()-5) -> 46539 | B17: =SUMIFS(Sales!$L$7:$L$1506,Sales!$A$7:$A$1506,">="&$A17,Sales!$A$7:$A$1506,"<="&EOMONTH($A17,0)) -> 0 | C17: =SUMIFS(Sales!$O$7:$O$1506,Sales!$A$7:$A$1506,">="&$A17,Sales!$A$7:$A$1506,"<="&EOMONTH($A17,0)) -> 0 | D17: =B17-C17 -> 0 | E17: =SUMIFS(Sales!$R$7:$R$1506,Sales!$A$7:$A$1506,">="&$A17,Sales!$A$7:$A$1506,"<="&EOMONTH($A17,0)) -> 0 | F17: =SUMIFS(Sales!$S$7:$S$1506,Sales!$A$7:$A$1506,">="&$A17,Sales!$A$7:$A$1506,"<="&EOMONTH($A17,0)) -> 0 | G17: =D17+E17-F17 -> 0 | H17: =COUNTIFS(Sales!$A$7:$A$1506,">="&$A17,Sales!$A$7:$A$1506,"<="&EOMONTH($A17,0)) -> 0 | I17: =COUNTIFS(Sales!$A$7:$A$1506,">="&$A17,Sales!$A$7:$A$1506,"<="&EOMONTH($A17,0),Sales!$V$7:$V$1506,">0") -> 0 | J17: =IF(B17=0,"",G17/B17)
... A40: =EDATE($A$5,ROW()-5) -> 47239 | B40: =SUMIFS(Sales!$L$7:$L$1506,Sales!$A$7:$A$1506,">="&$A40,Sales!$A$7:$A$1506,"<="&EOMONTH($A40,0)) -> 0 | C40: =SUMIFS(Sales!$O$7:$O$1506,Sales!$A$7:$A$1506,">="&$A40,Sales!$A$7:$A$1506,"<="&EOMONTH($A40,0)) -> 0 | D40: =B40-C40 -> 0 | E40: =SUMIFS(Sales!$R$7:$R$1506,Sales!$A$7:$A$1506,">="&$A40,Sales!$A$7:$A$1506,"<="&EOMONTH($A40,0)) -> 0 | F40: =SUMIFS(Sales!$S$7:$S$1506,Sales!$A$7:$A$1506,">="&$A40,Sales!$A$7:$A$1506,"<="&EOMONTH($A40,0)) -> 0 | G40: =D40+E40-F40 -> 0 | H40: =COUNTIFS(Sales!$A$7:$A$1506,">="&$A40,Sales!$A$7:$A$1506,"<="&EOMONTH($A40,0)) -> 0 | I40: =COUNTIFS(Sales!$A$7:$A$1506,">="&$A40,Sales!$A$7:$A$1506,"<="&EOMONTH($A40,0),Sales!$V$7:$V$1506,">0") -> 0 | J40: =IF(B40=0,"",G40/B40)
A41: TOTAL | B41: =SUM(B5:B40) -> 147710.01 | C41: =SUM(C5:C40) -> 114725.88 | D41: =SUM(D5:D40) -> 32984.131 | E41: =SUM(E5:E40) -> 1890 | F41: =SUM(F5:F40) -> 1995 | G41: =SUM(G5:G40) -> 32879.131 | H41: =SUM(H5:H40) -> 511 | I41: =SUM(I5:I40) -> 18 | J41: =IF(B41=0,"",G41/B41) -> 0.22259244

Sheet Sales by Month
A1: ="SALES — "&UPPER(TEXT($B$3,"mmmm yyyy")) -> SALES — JULY 2026
A2: READ ONLY — do not type in this sheet. Enter sales in the Sales sheet. Pick any month from the yellow dropdown in B3; new months appear there on their own.
A3: Month: | B3: 46204 | D3: ="Lines this month: "&COUNT($L$5:$L$504)&" | Today's month: "&TEXT(EOMONTH(TODAY(),-1)+1,"mmm-yyyy") -> Lines this month: 500 | Today's month: Sep-2026
A4: Date | B4: Type | C4: Channel | D4: Customer | E4: Invoice Number | F4: Item Code (click here ↓ for dropdown) | G4: Product Description (auto-fills, don't type) | H4: Qty | I4: Unit Price (Tk) | J4: MRP (Tk) | K4: Discount (Tk) | L4: Total Amount (Tk) | M4: Payment Status | O4: Helper - matched row
A5: {=IFERROR(INDEX(Sales!$A$7:$A$1506,$O5),"")} -> 46219 | B5: {=IFERROR(INDEX(Sales!$B$7:$B$1506,$O5),"")} -> Sale | C5: {=IFERROR(INDEX(Sales!$C$7:$C$1506,$O5),"")} -> Online | D5: {=IFERROR(INDEX(Sales!$D$7:$D$1506,$O5),"")} -> Samreen islam | E5: {=IFERROR(IF(INDEX(Sales!$E$7:$E$1506,$O5)="","",INDEX(Sales!$E$7:$E$1506,$O5)),"")} -> PAWF-260715-04EAA | F5: {=IFERROR(INDEX(Sales!$F$7:$F$1506,$O5),"")} -> FD-DRY-SMHRT-15KG-001 | G5: {=IFERROR(INDEX(Sales!$G$7:$G$1506,$O5),"")} -> Smart Heart Adult Cat Food Chicken & Tuna [15kg] | H5: {=IFERROR(INDEX(Sales!$H$7:$H$1506,$O5),"")} -> 1 | I5: {=IFERROR(INDEX(Sales!$I$7:$I$1506,$O5),"")} -> 6400 | J5: {=IFERROR(INDEX(Sales!$J$7:$J$1506,$O5),"")} -> 6700 | K5: {=IFERROR(INDEX(Sales!$K$7:$K$1506,$O5),"")} -> 300 | L5: {=IFERROR(INDEX(Sales!$L$7:$L$1506,$O5),"")} -> 6400 | M5: {=IFERROR(INDEX(Sales!$M$7:$M$1506,$O5),"")} -> Paid | O5: =IFERROR(MATCH(TEXT($B$3,"yyyymm")&"-"&(ROW()-4),Sales!$Y$7:$Y$1506,0),"") -> 1
